Workbook

Sheet Curriculum
A1: Mechatronics & Robotics English Vocabulary — المنهج الكامل
A2: 7-stage learning path: Robotics Fundamentals → Control & Motion → Motors & Sensors → Embedded Systems → Industrial Automation → Robot Operation → Troubleshooting & Job Interviews
A4: Stage # | B4: Stage | C4: المرحلة | D4: What you learn | E4: ماذا ستتعلم | F4: Terms | G4: Beginner | H4: Intermediate | I4: Advanced | J4: Go to sheet
A5: 1 | B5: Robotics Fundamentals | C5: أساسيات الروبوتات | D5: What a robot is: parts, joints, robot types, basic geometry and terms. | E5: ما هو الروبوت: أجزاؤه ومفاصله وأنواعه والمصطلحات والهندسة الأساسية. | F5: =COUNTIF('All Terms'!$M$5:$M$436,A5) -> 100 | G5: =COUNTIFS('All Terms'!$M$5:$M$436,$A5,'All Terms'!$L$5:$L$436,"Beginner") -> 58 | H5: =COUNTIFS('All Terms'!$M$5:$M$436,$A5,'All Terms'!$L$5:$L$436,"Intermediate") -> 12 | I5: =COUNTIFS('All Terms'!$M$5:$M$436,$A5,'All Terms'!$L$5:$L$436,"Advanced") -> 30 | J5: S1 Fundamentals
A6: 2 | B6: Control & Motion | C6: التحكم والحركة | D6: Kinematics, feedback, PID, paths, trajectories, accuracy and the math behind them. | E6: الكينماتيكا والتغذية الراجعة وPID والمسارات والدقة والرياضيات المرتبطة بها. | F6: =COUNTIF('All Terms'!$M$5:$M$436,A6) -> 110 | G6: =COUNTIFS('All Terms'!$M$5:$M$436,$A6,'All Terms'!$L$5:$L$436,"Beginner") -> 16 | H6: =COUNTIFS('All Terms'!$M$5:$M$436,$A6,'All Terms'!$L$5:$L$436,"Intermediate") -> 39 | I6: =COUNTIFS('All Terms'!$M$5:$M$436,$A6,'All Terms'!$L$5:$L$436,"Advanced") -> 55 | J6: S2 Control & Motion
A7: 3 | B7: Motors & Sensors | C7: المحركات والحساسات | D7: Actuators, motors, drives, gears, encoders and all kinds of sensors. | E7: المشغّلات والمحركات والمخفضات والتروس والمُرمِّزات وأنواع الحساسات. | F7: =COUNTIF('All Terms'!$M$5:$M$436,A7) -> 76 | G7: =COUNTIFS('All Terms'!$M$5:$M$436,$A7,'All Terms'!$L$5:$L$436,"Beginner") -> 20 | H7: =COUNTIFS('All Terms'!$M$5:$M$436,$A7,'All Terms'!$L$5:$L$436,"Intermediate") -> 35 | I7: =COUNTIFS('All Terms'!$M$5:$M$436,$A7,'All Terms'!$L$5:$L$436,"Advanced") -> 21 | J7: S3 Motors & Sensors
A8: 4 | B8: Embedded Systems | C8: الأنظمة المضمنة | D8: Microcontrollers, firmware, interrupts, electronics, and controller hardware. | E8: المتحكمات الدقيقة والبرامج الثابتة والمقاطعات والإلكترونيات وعتاد المتحكم. | F8: =COUNTIF('All Terms'!$M$5:$M$436,A8) -> 29 | G8: =COUNTIFS('All Terms'!$M$5:$M$436,$A8,'All Terms'!$L$5:$L$436,"Beginner") -> 9 | H8: =COUNTIFS('All Terms'!$M$5:$M$436,$A8,'All Terms'!$L$5:$L$436,"Intermediate") -> 12 | I8: =COUNTIFS('All Terms'!$M$5:$M$436,$A8,'All Terms'!$L$5:$L$436,"Advanced") -> 8 | J8: S4 Embedded Systems
A9: 5 | B9: Industrial Automation | C9: الأتمتة الصناعية | D9: PLCs, work cells, integrators, tooling, and real factory applications. | E9: المتحكمات المنطقية وخلايا العمل والمُكامِلون والأدوات والتطبيقات المصنعية. | F9: =COUNTIF('All Terms'!$M$5:$M$436,A9) -> 52 | G9: =COUNTIFS('All Terms'!$M$5:$M$436,$A9,'All Terms'!$L$5:$L$436,"Beginner") -> 23 | H9: =COUNTIFS('All Terms'!$M$5:$M$436,$A9,'All Terms'!$L$5:$L$436,"Intermediate") -> 23 | I9: =COUNTIFS('All Terms'!$M$5:$M$436,$A9,'All Terms'!$L$5:$L$436,"Advanced") -> 6 | J9: S5 Industrial Automation
A10: 6 | B10: Robot Operation | C10: تشغيل الروبوتات | D10: Programming, teaching, operating modes, safety rules and specifications. | E10: البرمجة والتعليم وأنماط التشغيل وقواعد السلامة والمواصفات. | F10: =COUNTIF('All Terms'!$M$5:$M$436,A10) -> 49 | G10: =COUNTIFS('All Terms'!$M$5:$M$436,$A10,'All Terms'!$L$5:$L$436,"Beginner") -> 18 | H10: =COUNTIFS('All Terms'!$M$5:$M$436,$A10,'All Terms'!$L$5:$L$436,"Intermediate") -> 21 | I10: =COUNTIFS('All Terms'!$M$5:$M$436,$A10,'All Terms'!$L$5:$L$436,"Advanced") -> 10 | J10: S6 Robot Operation
A11: 7 | B11: Troubleshooting & Job Interviews | C11: استكشاف الأعطال والمقابلات المهنية | D11: Maintenance, downtime, faults, reliability, quality, and typical interview terms. | E11: الصيانة والتوقف والأعطال والموثوقية والجودة ومصطلحات المقابلات المعتادة. | F11: =COUNTIF('All Terms'!$M$5:$M$436,A11) -> 16 | G11: =COUNTIFS('All Terms'!$M$5:$M$436,$A11,'All Terms'!$L$5:$L$436,"Beginner") -> 7 | H11: =COUNTIFS('All Terms'!$M$5:$M$436,$A11,'All Terms'!$L$5:$L$436,"Intermediate") -> 5 | I11: =COUNTIFS('All Terms'!$M$5:$M$436,$A11,'All Terms'!$L$5:$L$436,"Advanced") -> 4 | J11: S7 Troubleshoot & Interview
B12: Total | C12: المجموع | F12: =SUM(F5:F11) -> 432 | G12: =SUM(G5:G11) -> 151 | H12: =SUM(H5:H11) -> 147 | I12: =SUM(I5:I11) -> 134
B14: Column guide / شرح الأعمدة
B15: content_id | D15: Permanent ID, e.g. S3-SENS-014 = stage 3, category SENS, item 14. Never renumber it.
B16: Term / Arabic meaning | D16: The English term and its Arabic meaning
B17: Pronunciation | D17: Simple English respelling; capital letters = stressed syllable
B18: Category | D18: Topic of the term (Kinematics, Sensors, Safety...)
B19: Simple English definition | D19: Short, plain-English explanation
B20: Example 1 / 2 | D20: Two example sentences, each with an Arabic translation
B21: Difficulty level | D21: Beginner / Intermediate / Advanced
B22: Interview priority | D22: High = used in the Interview Q&A or Troubleshooting Guide, or key career vocabulary
B23: Linked Q&A / troubleshooting | D23: IDs of interview questions and fault cases that use this term
B24: Source / source_url | D24: Which of the 3 sources the term came from, and the link
B25: Copyright/source note | D25: What was taken from the source and what is original

Sheet All Terms
A1: All Terms — جميع المصطلحات (sorted by curriculum stage, then level)
A2: 432 unique terms merged from 3 sources. Use the filter arrows on row 4 to filter by stage, level, category, priority or source.
A4: content_id | B4: # | C4: Term | D4: Arabic meaning | E4: Pronunciation | F4: Category | G4: Simple English definition | H4: Example 1 | I4: Arabic translation 1 | J4: Example 2 | K4: Arabic translation 2 | L4: Difficulty level | M4: Stage # | N4: Curriculum stage | O4: Interview priority | P4: Linked Q&A / troubleshooting | Q4: Source | R4: source_url | S4: Copyright/source note
A5: S1-KINE-001 | B5: 1 | C5: Acceleration | D5: التسارع | E5: ak-sel-er-AY-shun | F5: Kinematics | G5: A change in how fast something moves or in its direction of travel. | H5: The robot needs high acceleration to move quickly. | I5: يحتاج الروبوت إلى تسارع عالٍ ليتحرك بسرعة. | J5: Acceleration is the change of velocity over time. | K5: التسارع هو تغير السرعة عبر الزمن. | L5: Beginner | M5: 1 | N5: 1 – Robotics Fundamentals | أساسيات الروبوتات | O5: Normal | Q5: FutureLearn (Univ. of Reading) | R5: https://ugc.futurelearn.com/uploads/files/7a/0f/7a0fcf86-09f0-4ebf-a134-02b1290a950e/Glossary.pdf | S5: Definition paraphrased from the listed source(s); pronunciation, Arabic, examples and level are original additions.
A6: S1-PROG-001 | B6: 2 | C6: Algorithm | D6: خوارزمية | E6: AL-guh-rith-um | F6: Programming | G6: A set of steps for solving a problem. | H6: The algorithm tells the robot how to find the shortest path. | I6: تخبر الخوارزمية الروبوت كيف يجد أقصر مسار. | J6: We improved the algorithm to reduce the calculation time. | K6: حسّنا الخوارزمية لتقليل زمن الحساب. | L6: Beginner | M6: 1 | N6: 1 – Robotics Fundamentals | أساسيات الروبوتات | O6: Normal | Q6: FutureLearn (Univ. of Reading) + Productivity Inc | R6: https://ugc.futurelearn.com/uploads/files/7a/0f/7a0fcf86-09f0-4ebf-a134-02b1290a950e/Glossary.pdf | https://www.productivity.com/wp-content/uploads/2015/04/PI_RoboticGlossaryTerms.pdf | S6: Definition paraphrased from the listed source(s); pronunciation, Arabic, examples and level are original additions.
A7: S1-ROBT-001 | B7: 3 | C7: Android | D7: روبوت شبيه بالإنسان (أندرويد) | E7: AN-droyd | F7: Robot Types | G7: A robot that resembles a human to some degree. | H7: An android is a robot that looks like a human. | I7: الأندرويد روبوت يشبه الإنسان. | J7: The museum has an android that greets visitors. | K7: لدى المتحف روبوت شبيه بالإنسان يستقبل الزوار. | L7: Beginner | M7: 1 | N7: 1 – Robotics Fundamentals | أساسيات الروبوتات | O7: Normal | Q7: FutureLearn (Univ. of Reading) | R7: https://ugc.futurelearn.com/uploads/files/7a/0f/7a0fcf86-09f0-4ebf-a134-02b1290a950e/Glossary.pdf | S7: Definition paraphrased from the listed source(s); pronunciation, Arabic, examples and level are original additions.
A8: S1-MECH-001 | B8: 4 | C8: Arm | D8: الذراع | E8: ARM | F8: Mechanical | G8: The linked, powered segments of a manipulator that move the wrist and end-effector, excluding the end-effector itself. | H8: The robot arm can lift up to ten kilograms. | I8: يستطيع ذراع الروبوت رفع ما يصل إلى عشرة كيلوغرامات. | J8: The arm has six joints and a gripper at its end. | K8: للذراع ستة مفاصل وقابض في نهايتها. | L8: Beginner | M8: 1 | N8: 1 – Robotics Fundamentals | أساسيات الروبوتات | O8: Normal | Q8: Productivity Inc | R8: https://www.productivity.com/wp-content/uploads/2015/04/PI_RoboticGlossaryTerms.pdf | S8: Definition paraphrased from the listed source(s); pronunciation, Arabic, examples and level are original additions.
A9: S1-CMAI-001 | B9: 5 | C9: Artificial Intelligence | D9: الذكاء الاصطناعي | E9: ar-tih-FISH-ul in-TEL-ih-juns | F9: Computing & AI | G9: Intelligence shown by a machine. | H9: Artificial intelligence lets machines learn from data. | I9: يتيح الذكاء الاصطناعي للآلات التعلم من البيانات. | J9: Modern robots use artificial intelligence to recognize objects. | K9: تستخدم الروبوتات الحديثة الذكاء الاصطناعي للتعرف على الأجسام. | L9: Beginner | M9: 1 | N9: 1 – Robotics Fundamentals | أساسيات الروبوتات | O9: Normal | Q9: FutureLearn (Univ. of Reading) | R9: https://ugc.futurelearn.com/uploads/files/7a/0f/7a0fcf86-09f0-4ebf-a134-02b1290a950e/Glossary.pdf | S9: Definition paraphrased from the listed source(s); pronunciation, Arabic, examples and level are original additions.
A10: S1-ROBT-003 | B10: 6 | C10: Autonomous | D10: ذاتي التشغيل / مستقل | E10: aw-TON-uh-mus | F10: Robot Types | G10: Procedures that run without worker involvement and follow pre-programmed operations. | H10: An autonomous robot makes its own decisions without a human. | I10: يتخذ الروبوت الذاتي التشغيل قراراته بنفسه دون إنسان. | J10: Autonomous vehicles use sensors to avoid obstacles. | K10: تستخدم المركبات ذاتية القيادة الحساسات لتجنب العوائق. | L10: Beginner | M10: 1 | N10: 1 – Robotics Fundamentals | أساسيات الروبوتات | O10: Normal | Q10: FutureLearn (Univ. of Reading) + Productivity Inc | R10: https://ugc.futurelearn.com/uploads/files/7a/0f/7a0fcf86-09f0-4ebf-a134-02b1290a950e/Glossary.pdf | https://www.productivity.com/wp-content/uploads/2015/04/PI_RoboticGlossaryTerms.pdf | S10: Definition paraphrased from the listed source(s); pronunciation, Arabic, examples and level are original additions.
A11: S1-KINE-002 | B11: 7 | C11: Axis | D11: محور | E11: AK-sis | F11: Kinematics | G11: A direction or line of rotation along which a robot moves; most industrial robots have four or six. | H11: This robot has six axes of movement. | I11: لهذا الروبوت ستة محاور للحركة. | J11: Each axis is driven by its own servo motor. | K11: يُدار كل محور بمحرك مؤازر خاص به. | L11: Beginner | M11: 1 | N11: 1 – Robotics Fundamentals | أساسيات الروبوتات | O11: High | P11: S7-INTV-002 | Q11: Productivity Inc | R11: https://www.productivity.com/wp-content/uploads/2015/04/PI_RoboticGlossaryTerms.pdf | S11: Definition paraphrased from the listed source(s); pronunciation, Arabic, examples and level are original additions.
A12: S1-MECH-003 | B12: 8 | C12: Base | D12: القاعدة | E12: BAYSS | F12: Mechanical | G12: The stable platform to which a robotic arm is attached. | H12: The robot arm is bolted to a stable base. | I12: الذراع الآلية مثبّتة بمسامير على قاعدة ثابتة. | J12: The base must be level before installation. | K12: يجب أن تكون القاعدة مستوية قبل التركيب. | L12: Beginner | M12: 1 | N12: 1 – Robotics Fundamentals | أساسيات الروبوتات | O12: Normal | Q12: Productivity Inc | R12: https://www.productivity.com/wp-content/uploads/2015/04/PI_RoboticGlossaryTerms.pdf | S12: Definition paraphrased from the listed source(s); pronunciation, Arabic, examples and level are original additions.
A13: S1-SWDS-001 | B13: 9 | C13: CAD (Computer-Aided Design) | D13: التصميم بمساعدة الحاسوب | E13: KAD | F13: Software & Design | G13: Software for designing manufacturable parts, creating schematics, and simulating stresses on them. | H13: We drew the gripper in CAD before building it. | I13: رسمنا القابض في برنامج التصميم بمساعدة الحاسوب قبل تصنيعه. | J13: CAD software can simulate stress on a part. | K13: يستطيع برنامج التصميم بمساعدة الحاسوب محاكاة الإجهاد على القطعة. | L13: Beginner | M13: 1 | N13: 1 – Robotics Fundamentals | أساسيات الروبوتات | O13: Normal | Q13: Productivity Inc | R13: https://www.productivity.com/wp-content/uploads/2015/04/PI_RoboticGlossaryTerms.pdf | S13: Definition paraphrased from the listed source(s); pronunciation, Arabic, examples and level are original additions.
A14: S1-ROBT-006 | B14: 10 | C14: Cartesian Robot | D14: روبوت ديكارتي | E14: kar-TEE-zhun ROH-bot | F14: Robot Types | G14: A robot whose three linear joints run in the directions of a Cartesian coordinate system. | H14: A Cartesian robot has three linear axes. | I14: للروبوت الديكارتي ثلاثة محاور خطية. | J14: We used a Cartesian robot to stack boxes. | K14: استخدمنا روبوتاً ديكارتياً لتكديس الصناديق. | L14: Beginner | M14: 1 | N14: 1 – Robotics Fundamentals | أساسيات الروبوتات | O14: Normal | Q14: Productivity Inc | R14: https://www.productivity.com/wp-content/uploads/2015/04/PI_RoboticGlossaryTerms.pdf | S14: Definition paraphrased from the listed source(s); pronunciation, Arabic, examples and level are original additions.
A15: S1-MECH-004 | B15: 11 | C15: Chassis | D15: الهيكل | E15: SHAS-ee | F15: Mechanical | G15: The framework and internal parts of a machine, excluding its body or casing. | H15: The motors and batteries are mounted on the chassis. | I15: المحركات والبطاريات مركّبة على الهيكل. | J15: A strong chassis protects the electronics. | K15: الهيكل المتين يحمي الإلكترونيات. | L15: Beginner | M15: 1 | N15: 1 – Robotics Fundamentals | أساسيات الروبوتات | O15: Normal | Q15: Productivity Inc | R15: https://www.productivity.com/wp-content/uploads/2015/04/PI_RoboticGlossaryTerms.pdf | S15: Definition paraphrased from the listed source(s); pronunciation, Arabic, examples and level are original additions.
A16: S1-KINE-003 | B16: 12 | C16: Coordinates | D16: الإحداثيات | E16: koh-OR-dih-nits | F16: Kinematics | G16: A set of numbers that describes a position in two or three dimensions. | H16: The coordinates give the position of the point. | I16: تعطي الإحداثيات موضع النقطة. | J16: Enter the coordinates in millimeters. | K16: أدخل الإحداثيات بالملّيمترات. | L16: Beginner | M16: 1 | N16: 1 – Robotics Fundamentals | أساسيات الروبوتات | O16: Normal | Q16: FutureLearn (Univ. of Reading) | R16: https://ugc.futurelearn.com/uploads/files/7a/0f/7a0fcf86-09f0-4ebf-a134-02b1290a950e/Glossary.pdf | S16: Definition paraphrased from the listed source(s); pronunciation, Arabic, examples and level are original additions.
A17: S1-ROBT-009 | B17: 13 | C17: Cyborg | D17: سايبورغ (كائن سيبراني) | E17: SY-borg | F17: Robot Types | G17: An organism combining biological and mechanical or electronic parts. | H17: A cyborg combines a living body with machine parts. | I17: يجمع السايبورغ بين جسم حي وأجزاء آلية. | J17: Science fiction often shows cyborgs with robotic arms. | K17: يعرض الخيال العلمي غالباً سايبورغ بأذرع آلية. | L17: Beginner | M17: 1 | N17: 1 – Robotics Fundamentals | أساسيات الروبوتات | O17: Normal | Q17: FutureLearn (Univ. of Reading) | R17: https://ugc.futurelearn.com/uploads/files/7a/0f/7a0fcf86-09f0-4ebf-a134-02b1290a950e/Glossary.pdf | S17: Definition paraphrased from the listed source(s); pronunciation, Arabic, examples and level are original additions.
A18: S1-FUND-001 | B18: 14 | C18: Degrees | D18: الدرجات | E18: dih-GREEZ | F18: Fundamentals | G18: A unit for measuring angles, where a full turn is 360 degrees. | H18: A full circle has 360 degrees. | I18: للدائرة الكاملة 360 درجة. | J18: The joint rotates 90 degrees. | K18: يدور المفصل 90 درجة. | L18: Beginner | M18: 1 | N18: 1 – Robotics Fundamentals | أساسيات الروبوتات | O18: Normal | Q18: FutureLearn (Univ. of Reading) | R18: https://ugc.futurelearn.com/uploads/files/7a/0f/7a0fcf86-09f0-4ebf-a134-02b1290a950e/Glossary.pdf | S18: Definition paraphrased from the listed source(s); pronunciation, Arabic, examples and level are original additions.
A19: S1-KINE-004 | B19: 15 | C19: Degrees of Freedom (DOF) | D19: درجات الحرية | E19: dih-GREEZ uv FREE-dum | F19: Kinematics | G19: The number of independent parameters needed to define a system's position and orientation. | H19: This robot has six degrees of freedom. | I19: لهذا الروبوت ست درجات حرية. | J19: More degrees of freedom give more flexibility but harder control. | K19: مزيد من درجات الحرية يعطي مرونة أكبر لكن تحكماً أصعب. | L19: Beginner | M19: 1 | N19: 1 – Robotics Fundamentals | أساسيات الروبوتات | O19: High | P19: S7-INTV-002 | Q19: Engineers Universe + FutureLearn (Univ. of Reading) + Productivity Inc | R19: https://engineersuniverse.com/studios/mechatronics/mechatronics-terminology-glossary | https://ugc.futurelearn.com/uploads/files/7a/0f/7a0fcf86-09f0-4ebf-a134-02b1290a950e/Glossary.pdf | https://www.productivity.com/wp-content/uploads/2015/04/PI_RoboticGlossaryTerms.pdf | S19: Definition paraphrased from the listed source(s); pronunciation, Arabic, examples and level are original additions.
A20: S1-FUND-002 | B20: 16 | C20: Device | D20: جهاز | E20: dih-VYSE | F20: Fundamentals | G20: Hardware used to control parts of a system. | H20: Each device on the network has its own address. | I20: لكل جهاز على الشبكة عنوانه الخاص. | J20: The device controls part of the system. | K20: يتحكم الجهاز في جزء من النظام. | L20: Beginner | M20: 1 | N20: 1 – Robotics Fundamentals | أساسيات الروبوتات | O20: Normal | Q20: Productivity Inc | R20: https://www.productivity.com/wp-content/uploads/2015/04/PI_RoboticGlossaryTerms.pdf | S20: Definition paraphrased from the listed source(s); pronunciation, Arabic, examples and level are original additions.
A21: S1-ELEC-001 | B21: 17 | C21: Electronics | D21: الإلكترونيات | E21: ih-lek-TRON-iks | F21: Electronics | G21: The study of how electrons flow through and are controlled by components like batteries, resistors, and motors. | H21: Electronics is the study of circuits and components. | I21: الإلكترونيات هي دراسة الدوائر والمكونات. | J21: Robots depend on electronics to sense and control. | K21: تعتمد الروبوتات على الإلكترونيات للاستشعار والتحكم. | L21: Beginner | M21: 1 | N21: 1 – Robotics Fundamentals | أساسيات الروبوتات | O21: Normal | Q21: FutureLearn (Univ. of Reading) | R21: https://ugc.futurelearn.com/uploads/files/7a/0f/7a0fcf86-09f0-4ebf-a134-02b1290a950e/Glossary.pdf | S21: Definition paraphrased from the listed source(s); pronunciation, Arabic, examples and level are original additions.
A22: S1-TOOL-001 | B22: 18 | C22: End Effector | D22: المؤثر النهائي | E22: END ih-FEK-ter | F22: Tooling | G22: The tool at the end of a robot arm that interacts with the environment, such as a gripper or torch. | H22: The end effector of this robot is a vacuum gripper. | I22: المؤثر النهائي لهذا الروبوت قابض تفريغ. | J22: We changed the end effector to handle a larger part. | K22: غيّرنا المؤثر النهائي للتعامل مع قطعة أكبر. | L22: Beginner | M22: 1 | N22: 1 – Robotics Fundamentals | أساسيات الروبوتات | O22: Normal | Q22: Engineers Universe + FutureLearn (Univ. of Reading) + Productivity Inc | R22: https://engineersuniverse.com/studios/mechatronics/mechatronics-terminology-glossary | https://ugc.futurelearn.com/uploads/files/7a/0f/7a0fcf86-09f0-4ebf-a134-02b1290a950e/Glossary.pdf | https://www.productivity.com/wp-content/uploads/2015/04/PI_RoboticGlossaryTerms.pdf | S22: Definition paraphrased from the listed source(s); pronunciation, Arabic, examples and level are original additions.
A23: S1-FUND-003 | B23: 19 | C23: Energy Source | D23: مصدر الطاقة | E23: EN-er-jee SORS | F23: Fundamentals | G23: Where energy comes from, such as chemical, thermal, or mechanical processes. | H23: A battery is the energy source of a mobile robot. | I23: البطارية هي مصدر الطاقة للروبوت المتنقل. | J23: Choose an energy source that matches the actuators. | K23: اختر مصدر طاقة يناسب المشغّلات. | L23: Beginner | M23: 1 | N23: 1 – Robotics Fundamentals | أساسيات الروبوتات | O23: Normal | Q23: Productivity Inc | R23: https://www.productivity.com/wp-content/uploads/2015/04/PI_RoboticGlossaryTerms.pdf | S23: Definition paraphrased from the listed source(s); pronunciation, Arabic, examples and level are original additions.
A24: S1-FUND-004 | B24: 20 | C24: Flexibility | D24: المرونة | E24: flek-suh-BIL-ih-tee | F24: Fundamentals | G24: The range of diverse jobs a robot can perform. | H24: Flexibility lets one robot do many different jobs. | I24: تتيح المرونة لروبوت واحد القيام بمهام كثيرة مختلفة. | J24: The line needs flexibility because products change often. | K24: يحتاج الخط إلى المرونة لأن المنتجات تتغير كثيراً. | L24: Beginner | M24: 1 | N24: 1 – Robotics Fundamentals | أساسيات الروبوتات | O24: Normal | Q24: Productivity Inc | R24: https://www.productivity.com/wp-content/uploads/2015/04/PI_RoboticGlossaryTerms.pdf | S24: Definition paraphrased from the listed source(s); pronunciation, Arabic, examples and level are original additions.
A25: S1-DYNM-001 | B25: 21 | C25: Force | D25: القوة | E25: FORS | F25: Dynamics | G25: The strength behind an action or movement. | H25: The motor creates a force that moves the arm. | I25: يخلق المحرك قوة تحرك الذراع. | J25: Force is measured in newtons. | K25: تُقاس القوة بالنيوتن. | L25: Beginner | M25: 1 | N25: 1 – Robotics Fundamentals | أساسيات الروبوتات | O25: Normal | Q25: FutureLearn (Univ. of Reading) | R25: https://ugc.futurelearn.com/uploads/files/7a/0f/7a0fcf86-09f0-4ebf-a134-02b1290a950e/Glossary.pdf | S25: Definition paraphrased from the listed source(s); pronunciation, Arabic, examples and level are original additions.
A26: S1-TOOL-002 | B26: 22 | C26: Gripper | D26: القابض | E26: GRIP-er | F26: Tooling | G26: An end-effector that seizes and holds objects through pressure, magnetism, or vacuum. | H26: The gripper holds the bottle without dropping it. | I26: يمسك القابض الزجاجة دون إسقاطها. | J26: A magnetic gripper can pick up steel parts. | K26: يستطيع القابض المغناطيسي التقاط القطع الفولاذية. | L26: Beginner | M26: 1 | N26: 1 – Robotics Fundamentals | أساسيات الروبوتات | O26: High | P26: S7-TRBL-006 | Q26: FutureLearn (Univ. of Reading) + Productivity Inc | R26: https://ugc.futurelearn.com/uploads/files/7a/0f/7a0fcf86-09f0-4ebf-a134-02b1290a950e/Glossary.pdf | https://www.productivity.com/wp-content/uploads/2015/04/PI_RoboticGlossaryTerms.pdf | S26: Definition paraphrased from the listed source(s); pronunciation, Arabic, examples and level are original additions.
A27: S1-TOOL-003 | B27: 23 | C27: Hand | D27: اليد | E27: HAND | F27: Tooling | G27: A clamp or gripper used as an end-effector to grasp objects. | H27: The robot hand can hold small objects. | I27: تستطيع يد الروبوت حمل الأشياء الصغيرة. | J27: A two-finger hand is enough for this task. | K27: يد بإصبعين تكفي لهذه المهمة. | L27: Beginner | M27: 1 | N27: 1 – Robotics Fundamentals | أساسيات الروبوتات | O27: Normal | Q27: Productivity Inc | R27: https://www.productivity.com/wp-content/uploads/2015/04/PI_RoboticGlossaryTerms.pdf | S27: Definition paraphrased from the listed source(s); pronunciation, Arabic, examples and level are original additions.
A28: S1-EMBD-001 | B28: 24 | C28: Hardware | D28: العتاد (الأجهزة) | E28: HARD-wair | F28: Embedded Systems | G28: The physical parts of a computer. | H28: The hardware includes the motors, sensors, and controller. | I28: يشمل العتاد المحركات والحساسات والمتحكم. | J28: We replaced the faulty hardware, not the software. | K28: استبدلنا العتاد المعطوب وليس البرمجيات. | L28: Beginner | M28: 1 | N28: 1 – Robotics Fundamentals | أساسيات الروبوتات | O28: Normal | Q28: FutureLearn (Univ. of Reading) | R28: https://ugc.futurelearn.com/uploads/files/7a/0f/7a0fcf86-09f0-4ebf-a134-02b1290a950e/Glossary.pdf | S28: Definition paraphrased from the listed source(s); pronunciation, Arabic, examples and level are original additions.
A29: S1-ROBT-014 | B29: 25 | C29: Industrial Robot | D29: روبوت صناعي | E29: in-DUS-tree-ul ROH-bot | F29: Robot Types | G29: A reprogrammable multifunction manipulator that moves materials, parts, tools, or devices through varied programmed motions. | H29: An industrial robot is a reprogrammable multi-purpose manipulator. | I29: الروبوت الصناعي ذراع متعددة الأغراض قابلة لإعادة البرمجة. | J29: The industrial robot paints car bodies all day. | K29: يطلي الروبوت الصناعي هياكل السيارات طوال اليوم. | L29: Beginner | M29: 1 | N29: 1 – Robotics Fundamentals | أساسيات الروبوتات | O29: Normal | Q29: FutureLearn (Univ. of Reading) + Productivity Inc | R29: https://ugc.futurelearn.com/uploads/files/7a/0f/7a0fcf86-09f0-4ebf-a134-02b1290a950e/Glossary.pdf | https://www.productivity.com/wp-content/uploads/2015/04/PI_RoboticGlossaryTerms.pdf | S29: Definition paraphrased from the listed source(s); pronunciation, Arabic, examples and level are original additions.
A30: S1-ROBT-015 | B30: 26 | C30: Insect robot | D30: روبوت حشري | E30: IN-sekt ROH-bot | F30: Robot Types | G30: A small mobile robot. | H30: An insect robot is small and walks on six legs. | I30: الروبوت الحشري صغير ويمشي على ست أرجل. | J30: The insect robot can climb over small obstacles. | K30: يستطيع الروبوت الحشري تسلق عوائق صغيرة. | L30: Beginner | M30: 1 | N30: 1 – Robotics Fundamentals | أساسيات الروبوتات | O30: Normal | Q30: FutureLearn (Univ. of Reading) | R30: https://ugc.futurelearn.com/uploads/files/7a/0f/7a0fcf86-09f0-4ebf-a134-02b1290a950e/Glossary.pdf | S30: Definition paraphrased from the listed source(s); pronunciation, Arabic, examples and level are original additions.
A31: S1-CMAI-004 | B31: 27 | C31: Intelligence | D31: الذكاء | E31: in-TEL-ih-juns | F31: Computing & AI | G31: The capacity to gain and use skills and knowledge. | H31: Intelligence is the ability to learn and use knowledge. | I31: الذكاء هو القدرة على التعلم واستخدام المعرفة. | J31: Robots with some intelligence can adapt to change. | K31: الروبوتات ذات الذكاء المحدود تستطيع التكيف مع التغيير. | L31: Beginner | M31: 1 | N31: 1 – Robotics Fundamentals | أساسيات الروبوتات | O31: Normal | Q31: FutureLearn (Univ. of Reading) | R31: https://ugc.futurelearn.com/uploads/files/7a/0f/7a0fcf86-09f0-4ebf-a134-02b1290a950e/Glossary.pdf | S31: Definition paraphrased from the listed source(s); pronunciation, Arabic, examples and level are original additions.
A32: S1-ROBT-016 | B32: 28 | C32: Intelligent Robot | D32: روبوت ذكي | E32: in-TEL-ih-junt ROH-bot | F32: Robot Types | G32: A robot that can make performance choices based on sensory input with little human help. | H32: An intelligent robot can choose actions based on its sensors. | I32: يستطيع الروبوت الذكي اختيار الأفعال بناءً على حساساته. | J32: Intelligent robots need little help from humans. | K32: لا تحتاج الروبوتات الذكية إلا إلى مساعدة قليلة من البشر. | L32: Beginner | M32: 1 | N32: 1 – Robotics Fundamentals | أساسيات الروبوتات | O32: Normal | Q32: FutureLearn (Univ. of Reading) + Productivity Inc | R32: https://ugc.futurelearn.com/uploads/files/7a/0f/7a0fcf86-09f0-4ebf-a134-02b1290a950e/Glossary.pdf | https://www.productivity.com/wp-content/uploads/2015/04/PI_RoboticGlossaryTerms.pdf | S32: Definition paraphrased from the listed source(s); pronunciation, Arabic, examples and level are original additions.
A33: S1-MECH-005 | B33: 29 | C33: Joint | D33: مفصل | E33: JOYNT | F33: Mechanical | G33: A rotational or translational degree of freedom between links or between a link and the end-effector. | H33: Each joint of the robot has its own motor. | I33: لكل مفصل في الروبوت محركه الخاص. | J33: The elbow joint rotates up to 150 degrees. | K33: يدور مفصل المرفق حتى 150 درجة. | L33: Beginner | M33: 1 | N33: 1 – Robotics Fundamentals | أساسيات الروبوتات | O33: High | P33: S7-INTV-002 | Q33: FutureLearn (Univ. of Reading) + Productivity Inc | R33: https://ugc.futurelearn.com/uploads/files/7a/0f/7a0fcf86-09f0-4ebf-a134-02b1290a950e/Glossary.pdf | https://www.productivity.com/wp-content/uploads/2015/04/PI_RoboticGlossaryTerms.pdf | S33: Definition paraphrased from the listed source(s); pronunciation, Arabic, examples and level are original additions.
A34: S1-ROBT-017 | B34: 30 | C34: Jointed Arm Robot | D34: روبوت ذو ذراع مفصلية | E34: JOYN-tid ARM ROH-bot | F34: Robot Types | G34: A robot arm with two junctions that allow motion similar to a human shoulder and elbow. | H34: A jointed arm robot moves like a human shoulder and elbow. | I34: يتحرك الروبوت ذو الذراع المفصلية مثل كتف الإنسان ومرفقه. | J34: Most welding robots are jointed arm robots. | K34: معظم روبوتات اللحام ذات أذرع مفصلية. | L34: Beginner | M34: 1 | N34: 1 – Robotics Fundamentals | أساسيات الروبوتات | O34: Normal | Q34: Productivity Inc | R34: https://www.productivity.com/wp-content/uploads/2015/04/PI_RoboticGlossaryTerms.pdf | S34: Definition paraphrased from the listed source(s); pronunciation, Arabic, examples and level are original additions.
A35: S1-ETHC-001 | B35: 31 | C35: Law of Robotics | D35: قوانين الروبوتات | E35: LAW uv roh-BOT-iks | F35: Robotics Ethics | G35: Rules created by Isaac Asimov in his robot stories to govern robot behavior. | H35: Asimov wrote the three laws of robotics. | I35: كتب أسيموف قوانين الروبوتات الثلاثة. | J35: The first law says a robot must not harm a human. | K35: ينص القانون الأول على أن الروبوت يجب ألا يؤذي إنساناً. | L35: Beginner | M35: 1 | N35: 1 – Robotics Fundamentals | أساسيات الروبوتات | O35: Normal | Q35: FutureLearn (Univ. of Reading) | R35: https://ugc.futurelearn.com/uploads/files/7a/0f/7a0fcf86-09f0-4ebf-a134-02b1290a950e/Glossary.pdf | S35: Definition paraphrased from the listed source(s); pronunciation, Arabic, examples and level are original additions.
A36: S1-BIOL-014 | B36: 32 | C36: Light seeker | D36: باحث الضوء | E36: LYTE SEEK-er | F36: Biology-Inspired | G36: A Braitenberg vehicle that turns toward lights. | H36: A light seeker turns toward the light. | I36: يتجه باحث الضوء نحو الضوء. | J36: The light seeker robot found the lamp. | K36: وجد روبوت باحث الضوء المصباح. | L36: Beginner | M36: 1 | N36: 1 – Robotics Fundamentals | أساسيات الروبوتات | O36: Normal | Q36: FutureLearn (Univ. of Reading) | R36: https://ugc.futurelearn.com/uploads/files/7a/0f/7a0fcf86-09f0-4ebf-a134-02b1290a950e/Glossary.pdf | S36: Definition paraphrased from the listed source(s); pronunciation, Arabic, examples and level are original additions.
A37: S1-KINE-005 | B37: 33 | C37: Linear motion | D37: الحركة الخطية | E37: LIN-ee-er MOH-shun | F37: Kinematics | G37: Movement in a straight line rather than rotation. | H37: Linear motion is movement in a straight line. | I37: الحركة الخطية هي حركة في خط مستقيم. | J37: A linear actuator creates linear motion. | K37: ينتج المشغّل الخطي حركة خطية. | L37: Beginner | M37: 1 | N37: 1 – Robotics Fundamentals | أساسيات الروبوتات | O37: Normal | Q37: FutureLearn (Univ. of Reading) | R37: https://ugc.futurelearn.com/uploads/files/7a/0f/7a0fcf86-09f0-4ebf-a134-02b1290a950e/Glossary.pdf | S37: Definition paraphrased from the listed source(s); pronunciation, Arabic, examples and level are original additions.
A38: S1-MECH-006 | B38: 34 | C38: Link | D38: وصلة | E38: LINK | F38: Mechanical | G38: A rigid part of a manipulator that connects adjacent joints. | H38: A link is a rigid part between two joints. | I38: الوصلة جزء صلب بين مفصلين. | J38: The upper arm link is made of aluminum. | K38: وصلة الذراع العلوية مصنوعة من الألمنيوم. | L38: Beginner | M38: 1 | N38: 1 – Robotics Fundamentals | أساسيات الروبوتات | O38: Normal | Q38: FutureLearn (Univ. of Reading) + Productivity Inc | R38: https://ugc.futurelearn.com/uploads/files/7a/0f/7a0fcf86-09f0-4ebf-a134-02b1290a950e/Glossary.pdf | https://www.productivity.com/wp-content/uploads/2015/04/PI_RoboticGlossaryTerms.pdf | S38: Definition paraphrased from the listed source(s); pronunciation, Arabic, examples and level are original additions.
A39: S1-ROBT-018 | B39: 35 | C39: Manipulator | D39: المُناوِل (الذراع الآلية) | E39: muh-NIP-yuh-lay-ter | F39: Robot Types | G39: A segmented, jointed mechanism that grasps or moves objects, controlled by an operator or programmable logic. | H39: The manipulator moves objects with its jointed arm. | I39: يحرّك المُناوِل الأجسام بذراعه المفصلية. | J39: A manipulator can be controlled by an operator or a program. | K39: يمكن التحكم بالمُناوِل بواسطة مشغّل أو برنامج. | L39: Beginner | M39: 1 | N39: 1 – Robotics Fundamentals | أساسيات الروبوتات | O39: Normal | Q39: FutureLearn (Univ. of Reading) + Productivity Inc | R39: https://ugc.futurelearn.com/uploads/files/7a/0f/7a0fcf86-09f0-4ebf-a134-02b1290a950e/Glossary.pdf | https://www.productivity.com/wp-content/uploads/2015/04/PI_RoboticGlossaryTerms.pdf | S39: Definition paraphrased from the listed source(s); pronunciation, Arabic, examples and level are original additions.
A40: S1-MECH-007 | B40: 36 | C40: Mechanical | D40: ميكانيكي | E40: muh-KAN-ih-kul | F40: Mechanical | G40: Relating to machines and apparatus. | H40: The mechanical parts of the robot include gears and links. | I40: تشمل الأجزاء الميكانيكية للروبوت التروس والوصلات. | J40: A mechanical fault can cause noise and vibration. | K40: قد يسبب العطل الميكانيكي ضجيجاً واهتزازاً. | L40: Beginner | M40: 1 | N40: 1 – Robotics Fundamentals | أساسيات الروبوتات | O40: Normal | Q40: Productivity Inc | R40: https://www.productivity.com/wp-content/uploads/2015/04/PI_RoboticGlossaryTerms.pdf | S40: Definition paraphrased from the listed source(s); pronunciation, Arabic, examples and level are original additions.
A41: S1-FUND-005 | B41: 37 | C41: Mechatronics | D41: الميكاترونيكس | E41: mek-uh-TRON-iks | F41: Fundamentals | G41: The integrated design approach combining mechanical, electronic, control, and software engineering in one system. | H41: Mechatronics combines mechanics, electronics, and software. | I41: تجمع الميكاترونيكس بين الميكانيك والإلكترونيات والبرمجيات. | J41: He studies mechatronics at the engineering faculty. | K41: يدرس الميكاترونيكس في كلية الهندسة. | L41: Beginner | M41: 1 | N41: 1 – Robotics Fundamentals | أساسيات الروبوتات | O41: Normal | Q41: Engineers Universe + FutureLearn (Univ. of Reading) | R41: https://engineersuniverse.com/studios/mechatronics/mechatronics-terminology-glossary | https://ugc.futurelearn.com/uploads/files/7a/0f/7a0fcf86-09f0-4ebf-a134-02b1290a950e/Glossary.pdf | S41: Definition paraphrased from the listed source(s); pronunciation, Arabic, examples and level are original additions.
A42: S1-ROBT-019 | B42: 38 | C42: Mobile Robot | D42: روبوت متنقل | E42: MOH-bul ROH-bot | F42: Robot Types | G42: A robot with its own power source that can move without path constraints. | H42: A mobile robot can move around without fixed tracks. | I42: يستطيع الروبوت المتنقل التحرك دون مسارات ثابتة. | J42: The mobile robot delivers parts across the factory floor. | K42: ينقل الروبوت المتنقل القطع عبر أرضية المصنع. | L42: Beginner | M42: 1 | N42: 1 – Robotics Fundamentals | أساسيات الروبوتات | O42: Normal | Q42: Productivity Inc | R42: https://www.productivity.com/wp-content/uploads/2015/04/PI_RoboticGlossaryTerms.pdf | S42: Definition paraphrased from the listed source(s); pronunciation, Arabic, examples and level are original additions.
A43: S1-BIOL-016 | B43: 39 | C43: Neuron | D43: عصبون (خلية عصبية) | E43: NOOR-on | F43: Biology-Inspired | G43: A basic processing unit in the brain, of which humans have billions. | H43: A neuron is a basic processing unit in the brain. | I43: العصبون وحدة معالجة أساسية في الدماغ. | J43: Artificial neurons are used in neural networks. | K43: تُستخدم العصبونات الاصطناعية في الشبكات العصبية. | L43: Beginner | M43: 1 | N43: 1 – Robotics Fundamentals | أساسيات الروبوتات | O43: Normal | Q43: FutureLearn (Univ. of Reading) | R43: https://ugc.futurelearn.com/uploads/files/7a/0f/7a0fcf86-09f0-4ebf-a134-02b1290a950e/Glossary.pdf | S43: Definition paraphrased from the listed source(s); pronunciation, Arabic, examples and level are original additions.
A44: S1-KINE-006 | B44: 40 | C44: Position | D44: الموضع | E44: puh-ZISH-un | F44: Kinematics | G44: An object's location in three-dimensional space, usually given by X, Y, and Z coordinates. | H44: The position of the tool is given by X, Y, and Z. | I44: يُعطى موضع الأداة بالقيم X وY وZ. | J44: The sensor measures the position of the arm. | K44: يقيس الحساس موضع الذراع. | L44: Beginner | M44: 1 | N44: 1 – Robotics Fundamentals | أساسيات الروبوتات | O44: Normal | Q44: FutureLearn (Univ. of Reading) + Productivity Inc | R44: https://ugc.futurelearn.com/uploads/files/7a/0f/7a0fcf86-09f0-4ebf-a134-02b1290a950e/Glossary.pdf | https://www.productivity.com/wp-content/uploads/2015/04/PI_RoboticGlossaryTerms.pdf | S44: Definition paraphrased from the listed source(s); pronunciation, Arabic, examples and level are original additions.
A45: S1-PROG-002 | B45: 41 | C45: Program | D45: برنامج / يبرمج | E45: PROH-gram | F45: Programming | G45: As a noun, a set of tasks for a controller or computer; as a verb, supplying those procedures and tasks. | H45: The robot follows a program to do its job. | I45: يتبع الروبوت برنامجاً لأداء عمله. | J45: We saved a backup copy of the program. | K45: حفظنا نسخة احتياطية من البرنامج. | L45: Beginner | M45: 1 | N45: 1 – Robotics Fundamentals | أساسيات الروبوتات | O45: Normal | Q45: FutureLearn (Univ. of Reading) + Productivity Inc | R45: https://ugc.futurelearn.com/uploads/files/7a/0f/7a0fcf86-09f0-4ebf-a134-02b1290a950e/Glossary.pdf | https://www.productivity.com/wp-content/uploads/2015/04/PI_RoboticGlossaryTerms.pdf | S45: Definition paraphrased from the listed source(s); pronunciation, Arabic, examples and level are original additions.
... A52: S1-KINE-008 | B52: 48 | C52: Rotational Motion | D52: الحركة الدورانية | E52: roh-TAY-shun-ul MOH-shun | F52: Kinematics | G52: Circular movement about an axis. | H52: Rotational motion is movement around an axis. | I52: الحركة الدورانية هي حركة حول محور. | J52: The motor produces rotational motion. | K52: ينتج المحرك حركة دورانية. | L52: Beginner | M52: 1 | N52: 1 – Robotics Fundamentals | أساسيات الروبوتات | O52: Normal | Q52: Productivity Inc | R52: https://www.productivity.com/wp-content/uploads/2015/04/PI_RoboticGlossaryTerms.pdf | S52: Definition paraphrased from the listed source(s); pronunciation, Arabic, examples and level are original additions.
A53: S1-SENS-001 | B53: 49 | C53: Sensor | D53: حساس / مستشعر | E53: SEN-ser | F53: Sensors | G53: An instrument that detects physical stimuli and reports data about the robot's environment or its own position. | H53: A sensor measures distance, temperature, or force. | I53: يقيس الحساس المسافة أو الحرارة أو القوة. | J53: The robot uses a sensor to find the object. | K53: يستخدم الروبوت حساساً لإيجاد الجسم. | L53: Beginner | M53: 1 | N53: 1 – Robotics Fundamentals | أساسيات الروبوتات | O53: High | P53: S7-TRBL-007 | Q53: FutureLearn (Univ. of Reading) + Productivity Inc | R53: https://ugc.futurelearn.com/uploads/files/7a/0f/7a0fcf86-09f0-4ebf-a134-02b1290a950e/Glossary.pdf | https://www.productivity.com/wp-content/uploads/2015/04/PI_RoboticGlossaryTerms.pdf | S53: Definition paraphrased from the listed source(s); pronunciation, Arabic, examples and level are original additions.
A54: S1-MECH-010 | B54: 50 | C54: Shoulder | D54: الكتف | E54: SHOHL-der | F54: Mechanical | G54: The joint connecting the manipulator arm to the base. | H54: The shoulder joint connects the arm to the base. | I54: يربط مفصل الكتف الذراع بالقاعدة. | J54: The shoulder motor carries the most load. | K54: يحمل محرك الكتف أكبر حِمل. | L54: Beginner | M54: 1 | N54: 1 – Robotics Fundamentals | أساسيات الروبوتات | O54: Normal | Q54: Productivity Inc | R54: https://www.productivity.com/wp-content/uploads/2015/04/PI_RoboticGlossaryTerms.pdf | S54: Definition paraphrased from the listed source(s); pronunciation, Arabic, examples and level are original additions.
A55: S1-ELEC-002 | B55: 51 | C55: Signal | D55: إشارة | E55: SIG-nul | F55: Electronics | G55: A current, voltage, or electromagnetic field used to carry information. | H55: The sensor sends a signal to the controller. | I55: يرسل الحساس إشارة إلى المتحكم. | J55: A noisy signal can cause wrong readings. | K55: قد تسبب الإشارة المشوّشة قراءات خاطئة. | L55: Beginner | M55: 1 | N55: 1 – Robotics Fundamentals | أساسيات الروبوتات | O55: High | P55: S7-TRBL-008 | Q55: FutureLearn (Univ. of Reading) | R55: https://ugc.futurelearn.com/uploads/files/7a/0f/7a0fcf86-09f0-4ebf-a134-02b1290a950e/Glossary.pdf | S55: Definition paraphrased from the listed source(s); pronunciation, Arabic, examples and level are original additions.
A56: S1-PROG-003 | B56: 52 | C56: Software | D56: البرمجيات | E56: SOFT-wair | F56: Programming | G56: A written program that instructs hardware to perform tasks. | H56: The software controls the robot's movements. | I56: تتحكم البرمجيات في حركات الروبوت. | J56: We updated the software to fix a bug. | K56: حدّثنا البرمجيات لإصلاح خلل. | L56: Beginner | M56: 1 | N56: 1 – Robotics Fundamentals | أساسيات الروبوتات | O56: Normal | Q56: FutureLearn (Univ. of Reading) + Productivity Inc | R56: https://ugc.futurelearn.com/uploads/files/7a/0f/7a0fcf86-09f0-4ebf-a134-02b1290a950e/Glossary.pdf | https://www.productivity.com/wp-content/uploads/2015/04/PI_RoboticGlossaryTerms.pdf | S56: Definition paraphrased from the listed source(s); pronunciation, Arabic, examples and level are original additions.
A57: S1-FUND-009 | B57: 53 | C57: System | D57: نظام | E57: SIS-tum | F57: Fundamentals | G57: A group of parts that work together. | H57: A robot is a system of many parts working together. | I57: الروبوت نظام من أجزاء كثيرة تعمل معاً. | J57: If one part of the system fails, the whole system may stop. | K57: إذا تعطل جزء من النظام قد يتوقف النظام بأكمله. | L57: Beginner | M57: 1 | N57: 1 – Robotics Fundamentals | أساسيات الروبوتات | O57: Normal | Q57: FutureLearn (Univ. of Reading) | R57: https://ugc.futurelearn.com/uploads/files/7a/0f/7a0fcf86-09f0-4ebf-a134-02b1290a950e/Glossary.pdf | S57: Definition paraphrased from the listed source(s); pronunciation, Arabic, examples and level are original additions.
A58: S1-TOOL-004 | B58: 54 | C58: Tool | D58: الأداة | E58: TOOL | F58: Tooling | G58: A working apparatus mounted at the arm's end, such as a gripper or welding torch. | H58: The robot changes its tool for each job. | I58: يغيّر الروبوت أداته لكل مهمة. | J58: A welding torch is a tool mounted on the arm. | K58: شعلة اللحام أداة مثبتة على الذراع. | L58: Beginner | M58: 1 | N58: 1 – Robotics Fundamentals | أساسيات الروبوتات | O58: Normal | Q58: Productivity Inc | R58: https://www.productivity.com/wp-content/uploads/2015/04/PI_RoboticGlossaryTerms.pdf | S58: Definition paraphrased from the listed source(s); pronunciation, Arabic, examples and level are original additions.
A59: S1-KINE-009 | B59: 55 | C59: Velocity | D59: السرعة المتجهة | E59: vuh-LOS-ih-tee | F59: Kinematics | G59: An object's speed together with the direction it travels. | H59: Velocity includes both speed and direction. | I59: تشمل السرعة المتجهة السرعة والاتجاه. | J59: The velocity of the arm is limited for safety. | K59: سرعة الذراع محدودة لأسباب السلامة. | L59: Beginner | M59: 1 | N59: 1 – Robotics Fundamentals | أساسيات الروبوتات | O59: Normal | Q59: FutureLearn (Univ. of Reading) | R59: https://ugc.futurelearn.com/uploads/files/7a/0f/7a0fcf86-09f0-4ebf-a134-02b1290a950e/Glossary.pdf | S59: Definition paraphrased from the listed source(s); pronunciation, Arabic, examples and level are original additions.
A60: S1-SPEC-001 | B60: 56 | C60: Workspace | D60: فضاء العمل | E60: WURK-spays | F60: Specifications | G60: The volume a robot's end effector can reach, distinguishing reachable from dexterous regions. | H60: The robot's workspace is the area it can reach. | I60: فضاء عمل الروبوت هو المنطقة التي يستطيع الوصول إليها. | J60: Remove all tools from the workspace before starting. | K60: أزل جميع الأدوات من فضاء العمل قبل البدء. | L60: Beginner | M60: 1 | N60: 1 – Robotics Fundamentals | أساسيات الروبوتات | O60: High | P60: S7-INTV-014 | Q60: Engineers Universe + Productivity Inc | R60: https://engineersuniverse.com/studios/mechatronics/mechatronics-terminology-glossary | https://www.productivity.com/wp-content/uploads/2015/04/PI_RoboticGlossaryTerms.pdf | S60: Definition paraphrased from the listed source(s); pronunciation, Arabic, examples and level are original additions.
A61: S1-MECH-011 | B61: 57 | C61: Wrist | D61: المعصم | E61: RIST | F61: Mechanical | G61: A set of rotary joints between the arm and end-effector that orient the end-effector toward the workpiece. | H61: The wrist orients the tool toward the work-piece. | I61: يوجّه المعصم الأداة نحو قطعة العمل. | J61: The wrist has three rotary joints. | K61: للمعصم ثلاثة مفاصل دوّارة. | L61: Beginner | M61: 1 | N61: 1 – Robotics Fundamentals | أساسيات الروبوتات | O61: Normal | Q61: Productivity Inc | R61: https://www.productivity.com/wp-content/uploads/2015/04/PI_RoboticGlossaryTerms.pdf | S61: Definition paraphrased from the listed source(s); pronunciation, Arabic, examples and level are original additions.
A62: S1-KINE-010 | B62: 58 | C62: XYZ Coordinates | D62: إحداثيات XYZ | E62: EKS-WY-ZEE koh-OR-dih-nits | F62: Kinematics | G62: Names for the lines forming a Cartesian solid. | H62: XYZ coordinates describe a point in three dimensions. | I62: تصف إحداثيات XYZ نقطة في ثلاثة أبعاد. | J62: Enter the XYZ coordinates of the target position. | K62: أدخل إحداثيات XYZ للموضع المستهدف. | L62: Beginner | M62: 1 | N62: 1 – Robotics Fundamentals | أساسيات الروبوتات | O62: Normal | Q62: Productivity Inc | R62: https://www.productivity.com/wp-content/uploads/2015/04/PI_RoboticGlossaryTerms.pdf | S62: Definition paraphrased from the listed source(s); pronunciation, Arabic, examples and level are original additions.
A63: S1-ROBT-002 | B63: 59 | C63: Articulated Manipulator | D63: ذراع مفصلية | E63: ar-TIK-yuh-lay-tid muh-NIP-yuh-lay-ter | F63: Robot Types | G63: A manipulator whose arm has jointed sections, with each joint adding a degree of freedom. | H63: An articulated manipulator looks like a human arm with a shoulder and elbow. | I63: يشبه الذراع المفصلية ذراع الإنسان بكتف ومرفق. | J63: Most factory robots are articulated manipulators. | K63: معظم روبوتات المصانع أذرع مفصلية. | L63: Intermediate | M63: 1 | N63: 1 – Robotics Fundamentals | أساسيات الروبوتات | O63: Normal | Q63: Productivity Inc | R63: https://www.productivity.com/wp-content/uploads/2015/04/PI_RoboticGlossaryTerms.pdf | S63: Definition paraphrased from the listed source(s); pronunciation, Arabic, examples and level are original additions.
A64: S1-MECH-002 | B64: 60 | C64: Articulation | D64: التمفصل | E64: ar-tik-yuh-LAY-shun | F64: Mechanical | G64: A jointed design that rotates and bends, letting a robot reach into confined spaces. | H64: The articulation of the arm lets it reach inside a machine. | I64: يتيح تمفصل الذراع لها الوصول إلى داخل الآلة. | J64: Good articulation gives the robot more flexibility in tight spaces. | K64: التمفصل الجيد يمنح الروبوت مرونة أكبر في الأماكن الضيقة. | L64: Intermediate | M64: 1 | N64: 1 – Robotics Fundamentals | أساسيات الروبوتات | O64: Normal | Q64: Productivity Inc | R64: https://www.productivity.com/wp-content/uploads/2015/04/PI_RoboticGlossaryTerms.pdf | S64: Definition paraphrased from the listed source(s); pronunciation, Arabic, examples and level are original additions.
A65: S1-ROBT-004 | B65: 61 | C65: Baxter robot | D65: روبوت باكستر | E65: BAK-ster ROH-bot | F65: Robot Types | G65: A modern industrial robot built to work safely alongside people. | H65: The Baxter robot was designed to work safely beside people. | I65: صُمم روبوت باكستر للعمل بأمان بجانب الناس. | J65: Small factories used Baxter for simple packing tasks. | K65: استخدمت المصانع الصغيرة باكستر لمهام تعبئة بسيطة. | L65: Intermediate | M65: 1 | N65: 1 – Robotics Fundamentals | أساسيات الروبوتات | O65: Normal | Q65: FutureLearn (Univ. of Reading) | R65: https://ugc.futurelearn.com/uploads/files/7a/0f/7a0fcf86-09f0-4ebf-a134-02b1290a950e/Glossary.pdf | S65: Definition paraphrased from the listed source(s); pronunciation, Arabic, examples and level are original additions.
A66: S1-ROBT-005 | B66: 62 | C66: Cartesian Manipulator | D66: ذراع ديكارتية | E66: kar-TEE-zhun muh-NIP-yuh-lay-ter | F66: Robot Types | G66: A robot arm with prismatic joints that move along the X, Y, and Z axes. | H66: A Cartesian manipulator uses prismatic joints on three perpendicular axes. | I66: يستخدم الذراع الديكارتي مفاصل منزلقة على ثلاثة محاور متعامدة. | J66: The Cartesian manipulator is easy to program. | K66: الذراع الديكارتي سهل البرمجة. | L66: Intermediate | M66: 1 | N66: 1 – Robotics Fundamentals | أساسيات الروبوتات | O66: Normal | Q66: Productivity Inc | R66: https://www.productivity.com/wp-content/uploads/2015/04/PI_RoboticGlossaryTerms.pdf | S66: Definition paraphrased from the listed source(s); pronunciation, Arabic, examples and level are original additions.
A67: S1-ROBT-008 | B67: 63 | C67: Cartesian-Coordinate Robot | D67: روبوت الإحداثيات الديكارتية | E67: kar-TEE-zhun koh-OR-dih-nit ROH-bot | F67: Robot Types | G67: A robot whose arm motions are defined by Cartesian coordinates, plus rotary motion for orientation. | H67: A Cartesian-coordinate robot moves along straight X, Y, and Z lines. | I67: يتحرك روبوت الإحداثيات الديكارتية على خطوط مستقيمة X وY وZ. | J67: 3D printers are simple Cartesian-coordinate robots. | K67: الطابعات ثلاثية الأبعاد روبوتات إحداثيات ديكارتية بسيطة. | L67: Intermediate | M67: 1 | N67: 1 – Robotics Fundamentals | أساسيات الروبوتات | O67: Normal | Q67: Productivity Inc | R67: https://www.productivity.com/wp-content/uploads/2015/04/PI_RoboticGlossaryTerms.pdf | S67: Definition paraphrased from the listed source(s); pronunciation, Arabic, examples and level are original additions.
A68: S1-ROBT-010 | B68: 64 | C68: Cylindrical Robot | D68: روبوت أسطواني | E68: sih-LIN-drih-kul ROH-bot | F68: Robot Types | G68: A robot whose axes correspond to a cylindrical coordinate system. | H68: A cylindrical robot moves in a circle and up and down. | I68: يتحرك الروبوت الأسطواني في دائرة وللأعلى والأسفل. | J68: The cylindrical robot loads parts into the machine. | K68: يحمّل الروبوت الأسطواني القطع في الآلة. | L68: Intermediate | M68: 1 | N68: 1 – Robotics Fundamentals | أساسيات الروبوتات | O68: Normal | Q68: Productivity Inc | R68: https://www.productivity.com/wp-content/uploads/2015/04/PI_RoboticGlossaryTerms.pdf | S68: Definition paraphrased from the listed source(s); pronunciation, Arabic, examples and level are original additions.
A69: S1-CMAI-003 | B69: 65 | C69: Human-Computer Interaction (HCI) | D69: التفاعل بين الإنسان والحاسوب | E69: HYOO-mun kum-PYOO-ter in-ter-AK-shun | F69: Computing & AI | G69: The study of how computers and humans relate to each other. | H69: HCI studies how people use computers and machines. | I69: يدرس التفاعل بين الإنسان والحاسوب كيف يستخدم الناس الحواسيب والآلات. | J69: Good HCI makes the robot panel easy to understand. | K69: التفاعل الجيد بين الإنسان والحاسوب يجعل لوحة الروبوت سهلة الفهم. | L69: Intermediate | M69: 1 | N69: 1 – Robotics Fundamentals | أساسيات الروبوتات | O69: Normal | Q69: FutureLearn (Univ. of Reading) + Productivity Inc | R69: https://ugc.futurelearn.com/uploads/files/7a/0f/7a0fcf86-09f0-4ebf-a134-02b1290a950e/Glossary.pdf | https://www.productivity.com/wp-content/uploads/2015/04/PI_RoboticGlossaryTerms.pdf | S69: Definition paraphrased from the listed source(s); pronunciation, Arabic, examples and level are original additions.
A70: S1-FUND-006 | B70: 66 | C70: Modularity | D70: النمطية / القابلية للتجزئة | E70: moj-uh-LAIR-ih-tee | F70: Fundamentals | G70: A design property allowing separate units to be easily joined or rearranged. | H70: Modularity makes the robot easy to repair and upgrade. | I70: تجعل النمطية الروبوت سهل الإصلاح والترقية. | J70: Thanks to modularity, we replaced only the gripper module. | K70: بفضل النمطية استبدلنا وحدة القابض فقط. | L70: Intermediate | M70: 1 | N70: 1 – Robotics Fundamentals | أساسيات الروبوتات | O70: Normal | Q70: Productivity Inc | R70: https://www.productivity.com/wp-content/uploads/2015/04/PI_RoboticGlossaryTerms.pdf | S70: Definition paraphrased from the listed source(s); pronunciation, Arabic, examples and level are original additions.
A71: S1-ROBT-023 | B71: 67 | C71: Rectangular-Coordinate Robot | D71: روبوت الإحداثيات المستطيلة | E71: rek-TANG-gyuh-ler koh-OR-dih-nit ROH-bot | F71: Robot Types | G71: A robot moving linearly along X, Y, and Z axes, creating a rectangular work envelope. | H71: A rectangular-coordinate robot has a box-shaped work area. | I71: لروبوت الإحداثيات المستطيلة منطقة عمل على شكل صندوق. | J71: It moves linearly along the X, Y, and Z axes. | K71: يتحرك خطياً على المحاور X وY وZ. | L71: Intermediate | M71: 1 | N71: 1 – Robotics Fundamentals | أساسيات الروبوتات | O71: Normal | Q71: Productivity Inc | R71: https://www.productivity.com/wp-content/uploads/2015/04/PI_RoboticGlossaryTerms.pdf | S71: Definition paraphrased from the listed source(s); pronunciation, Arabic, examples and level are original additions.
A72: S1-MECH-008 | B72: 68 | C72: Revolute Joint | D72: مفصل دوراني | E72: REV-uh-loot JOYNT | F72: Mechanical | G72: A joint capable of rotary motion. | H72: A revolute joint rotates around one axis. | I72: يدور المفصل الدوراني حول محور واحد. | J72: The elbow of the arm is a revolute joint. | K72: مرفق الذراع مفصل دوراني. | L72: Intermediate | M72: 1 | N72: 1 – Robotics Fundamentals | أساسيات الروبوتات | O72: Normal | Q72: Productivity Inc | R72: https://www.productivity.com/wp-content/uploads/2015/04/PI_RoboticGlossaryTerms.pdf | S72: Definition paraphrased from the listed source(s); pronunciation, Arabic, examples and level are original additions.
... A104: S1-CMAI-005 | B104: 100 | C104: World Model | D104: نموذج البيئة | E104: WURLD MOD-ul | F104: Computing & AI | G104: A stored three-dimensional representation of the robot's environment, updated as objects are sensed. | H104: The robot keeps a world model of its environment. | I104: يحتفظ الروبوت بنموذج للبيئة المحيطة به. | J104: The world model is updated when new objects are sensed. | K104: يُحدَّث نموذج البيئة عند استشعار أجسام جديدة. | L104: Advanced | M104: 1 | N104: 1 – Robotics Fundamentals | أساسيات الروبوتات | O104: Normal | Q104: Productivity Inc | R104: https://www.productivity.com/wp-content/uploads/2015/04/PI_RoboticGlossaryTerms.pdf | S104: Definition paraphrased from the listed source(s); pronunciation, Arabic, examples and level are original additions.
A105: S2-QUAL-001 | B105: 101 | C105: Accuracy | D105: الدقة | E105: AK-yer-uh-see | F105: Quality & Measurement | G105: How closely a robot reaches a commanded point, which is usually less precise than its repeatability. | H105: The accuracy of the robot is 0.1 mm at the target point. | I105: دقة الروبوت 0.1 ملم عند النقطة المستهدفة. | J105: Accuracy is usually worse than repeatability in industrial arms. | K105: الدقة عادةً أسوأ من قابلية التكرار في الأذرع الصناعية. | L105: Beginner | M105: 2 | N105: 2 – Control & Motion | التحكم والحركة | O105: High | P105: S7-INTV-001 | Q105: FutureLearn (Univ. of Reading) + Productivity Inc | R105: https://ugc.futurelearn.com/uploads/files/7a/0f/7a0fcf86-09f0-4ebf-a134-02b1290a950e/Glossary.pdf | https://www.productivity.com/wp-content/uploads/2015/04/PI_RoboticGlossaryTerms.pdf | S105: Definition paraphrased from the listed source(s); pronunciation, Arabic, examples and level are original additions.
A106: S2-CTRL-003 | B106: 102 | C106: Closed-Loop Control | D106: التحكم بالحلقة المغلقة | E106: KLOHZD LOOP kun-TROHL | F106: Control Systems | G106: A control method that measures the output and corrects the command based on the error. | H106: Closed-loop control uses sensor feedback to correct the error. | I106: يستخدم التحكم بالحلقة المغلقة تغذية راجعة من الحساس لتصحيح الخطأ. | J106: A thermostat is a simple closed-loop control system. | K106: منظم الحرارة نظام تحكم بسيط بالحلقة المغلقة. | L106: Beginner | M106: 2 | N106: 2 – Control & Motion | التحكم والحركة | O106: High | P106: S7-INTV-003 | Q106: Engineers Universe + FutureLearn (Univ. of Reading) + Productivity Inc | R106: https://engineersuniverse.com/studios/mechatronics/mechatronics-terminology-glossary | https://ugc.futurelearn.com/uploads/files/7a/0f/7a0fcf86-09f0-4ebf-a134-02b1290a950e/Glossary.pdf | https://www.productivity.com/wp-content/uploads/2015/04/PI_RoboticGlossaryTerms.pdf | S106: Definition paraphrased from the listed source(s); pronunciation, Arabic, examples and level are original additions.
A107: S2-CTRL-005 | B107: 103 | C107: Control Engineering | D107: هندسة التحكم | E107: kun-TROHL en-juh-NEER-ing | F107: Control Systems | G107: The study of how to achieve control of systems. | H107: Control engineering designs systems that keep machines stable. | I107: تصمم هندسة التحكم أنظمة تُبقي الآلات مستقرة. | J107: He took a course in control engineering. | K107: أخذ مساقاً في هندسة التحكم. | L107: Beginner | M107: 2 | N107: 2 – Control & Motion | التحكم والحركة | O107: Normal | Q107: FutureLearn (Univ. of Reading) | R107: https://ugc.futurelearn.com/uploads/files/7a/0f/7a0fcf86-09f0-4ebf-a134-02b1290a950e/Glossary.pdf | S107: Definition paraphrased from the listed source(s); pronunciation, Arabic, examples and level are original additions.
A108: S2-CTRL-007 | B108: 104 | C108: Controller | D108: المتحكم | E108: kun-TROH-ler | F108: Control Systems | G108: A processing device that compares desired and measured values and outputs drive signals to motors or actuators. | H108: The controller compares the target value with the measured value. | I108: يقارن المتحكم القيمة المطلوبة بالقيمة المقاسة. | J108: We replaced the controller after it overheated. | K108: استبدلنا المتحكم بعد أن سخن بشكل زائد. | L108: Beginner | M108: 2 | N108: 2 – Control & Motion | التحكم والحركة | O108: High | P108: S7-TRBL-009 | Q108: FutureLearn (Univ. of Reading) + Productivity Inc | R108: https://ugc.futurelearn.com/uploads/files/7a/0f/7a0fcf86-09f0-4ebf-a134-02b1290a950e/Glossary.pdf | https://www.productivity.com/wp-content/uploads/2015/04/PI_RoboticGlossaryTerms.pdf | S108: Definition paraphrased from the listed source(s); pronunciation, Arabic, examples and level are original additions.
A109: S2-CTRL-010 | B109: 105 | C109: Error | D109: الخطأ | E109: ER-er | F109: Control Systems | G109: The difference between a robot's actual response and the command issued. | H109: The error is the difference between the target and the actual position. | I109: الخطأ هو الفرق بين الموضع المستهدف والموضع الفعلي. | J109: The controller works to reduce the error to zero. | K109: يعمل المتحكم على خفض الخطأ إلى الصفر. | L109: Beginner | M109: 2 | N109: 2 – Control & Motion | التحكم والحركة | O109: Normal | Q109: FutureLearn (Univ. of Reading) + Productivity Inc | R109: https://ugc.futurelearn.com/uploads/files/7a/0f/7a0fcf86-09f0-4ebf-a134-02b1290a950e/Glossary.pdf | https://www.productivity.com/wp-content/uploads/2015/04/PI_RoboticGlossaryTerms.pdf | S109: Definition paraphrased from the listed source(s); pronunciation, Arabic, examples and level are original additions.
A110: S2-CTRL-011 | B110: 106 | C110: Feedback | D110: التغذية الراجعة | E110: FEED-bak | F110: Control Systems | G110: A signal from robot equipment reporting actual conditions rather than what the computer commanded. | H110: Feedback tells the controller what the robot is really doing. | I110: تخبر التغذية الراجعة المتحكم بما يفعله الروبوت فعلاً. | J110: Without feedback the system cannot correct its errors. | K110: بدون تغذية راجعة لا يستطيع النظام تصحيح أخطائه. | L110: Beginner | M110: 2 | N110: 2 – Control & Motion | التحكم والحركة | O110: High | P110: S7-INTV-003 | Q110: FutureLearn (Univ. of Reading) + Productivity Inc | R110: https://ugc.futurelearn.com/uploads/files/7a/0f/7a0fcf86-09f0-4ebf-a134-02b1290a950e/Glossary.pdf | https://www.productivity.com/wp-content/uploads/2015/04/PI_RoboticGlossaryTerms.pdf | S110: Definition paraphrased from the listed source(s); pronunciation, Arabic, examples and level are original additions.
A111: S2-CTRL-012 | B111: 107 | C111: Feedback Control | D111: التحكم بالتغذية الراجعة | E111: FEED-bak kun-TROHL | F111: Control Systems | G111: Control achieved by returning manipulator or sensor information to the controller to produce a desired effect. | H111: Feedback control keeps the motor at the desired speed. | I111: يُبقي التحكم بالتغذية الراجعة المحرك عند السرعة المطلوبة. | J111: Most industrial robots use feedback control. | K111: معظم الروبوتات الصناعية تستخدم التحكم بالتغذية الراجعة. | L111: Beginner | M111: 2 | N111: 2 – Control & Motion | التحكم والحركة | O111: Normal | Q111: Productivity Inc | R111: https://www.productivity.com/wp-content/uploads/2015/04/PI_RoboticGlossaryTerms.pdf | S111: Definition paraphrased from the listed source(s); pronunciation, Arabic, examples and level are original additions.
A112: S2-CTRL-013 | B112: 108 | C112: Feedback Loop | D112: حلقة التغذية الراجعة | E112: FEED-bak LOOP | F112: Control Systems | G112: A circular route along which information travels. | H112: A feedback loop sends the output back to the input. | I112: تعيد حلقة التغذية الراجعة المخرجات إلى المدخلات. | J112: The thermostat is a classic feedback loop. | K112: منظم الحرارة مثال كلاسيكي على حلقة التغذية الراجعة. | L112: Beginner | M112: 2 | N112: 2 – Control & Motion | التحكم والحركة | O112: Normal | Q112: FutureLearn (Univ. of Reading) | R112: https://ugc.futurelearn.com/uploads/files/7a/0f/7a0fcf86-09f0-4ebf-a134-02b1290a950e/Glossary.pdf | S112: Definition paraphrased from the listed source(s); pronunciation, Arabic, examples and level are original additions.
A113: S2-CTRL-016 | B113: 109 | C113: Gain | D113: الكسب | E113: GAYN | F113: Control Systems | G113: A multiplier applied to a control signal; PID gains set responses to error, accumulated error, and error rate. | H113: Increasing the gain makes the controller respond faster. | I113: زيادة الكسب تجعل المتحكم يستجيب أسرع. | J113: Too much gain can cause oscillation. | K113: الكسب الزائد قد يسبب التذبذب. | L113: Beginner | M113: 2 | N113: 2 – Control & Motion | التحكم والحركة | O113: High | P113: S7-INTV-004; S7-TRBL-002 | Q113: Engineers Universe + FutureLearn (Univ. of Reading) | R113: https://engineersuniverse.com/studios/mechatronics/mechatronics-terminology-glossary | https://ugc.futurelearn.com/uploads/files/7a/0f/7a0fcf86-09f0-4ebf-a134-02b1290a950e/Glossary.pdf | S113: Definition paraphrased from the listed source(s); pronunciation, Arabic, examples and level are original additions.
A114: S2-CTRL-018 | B114: 110 | C114: Open-Loop Control | D114: التحكم بالحلقة المفتوحة | E114: OH-pun LOOP kun-TROHL | F114: Control Systems | G114: Control that issues commands without sensor feedback, so missed steps go undetected. | H114: Open-loop control has no sensor feedback. | I114: التحكم بالحلقة المفتوحة لا يحتوي تغذية راجعة من الحساس. | J114: A stepper motor can run with open-loop control. | K114: يستطيع المحرك الخطوي العمل بالتحكم بالحلقة المفتوحة. | L114: Beginner | M114: 2 | N114: 2 – Control & Motion | التحكم والحركة | O114: High | P114: S7-INTV-003; S7-TRBL-004 | Q114: Engineers Universe | R114: https://engineersuniverse.com/studios/mechatronics/mechatronics-terminology-glossary | S114: Definition paraphrased from the listed source(s); pronunciation, Arabic, examples and level are original additions.
A115: S2-MOTN-011 | B115: 111 | C115: Path | D115: المسار | E115: PATH | F115: Motion Control | G115: The continuous set of points traced by the tool center point in a coordinate system. | H115: The robot follows a path from point A to point B. | I115: يتبع الروبوت مساراً من النقطة A إلى النقطة B. | J115: We changed the path to avoid the obstacle. | K115: غيّرنا المسار لتجنب العائق. | L115: Beginner | M115: 2 | N115: 2 – Control & Motion | التحكم والحركة | O115: Normal | Q115: Productivity Inc | R115: https://www.productivity.com/wp-content/uploads/2015/04/PI_RoboticGlossaryTerms.pdf | S115: Definition paraphrased from the listed source(s); pronunciation, Arabic, examples and level are original additions.
A116: S2-CTRL-020 | B116: 112 | C116: PID Controller | D116: متحكم PID | E116: PEE-EYE-DEE kun-TROH-ler | F116: Control Systems | G116: A feedback controller combining proportional, integral, and derivative actions, widely used because it needs no detailed model. | H116: A PID controller uses proportional, integral, and derivative actions. | I116: يستخدم متحكم PID الإجراءات التناسبية والتكاملية والتفاضلية. | J116: We tuned the PID controller to remove the overshoot. | K116: ضبطنا متحكم PID لإزالة التجاوز. | L116: Beginner | M116: 2 | N116: 2 – Control & Motion | التحكم والحركة | O116: High | P116: S7-INTV-004; S7-TRBL-002 | Q116: Engineers Universe + FutureLearn (Univ. of Reading) | R116: https://engineersuniverse.com/studios/mechatronics/mechatronics-terminology-glossary | https://ugc.futurelearn.com/uploads/files/7a/0f/7a0fcf86-09f0-4ebf-a134-02b1290a950e/Glossary.pdf | S116: Definition paraphrased from the listed source(s); pronunciation, Arabic, examples and level are original additions.
A117: S2-QUAL-003 | B117: 113 | C117: Precision | D117: الضبط (الإحكام) | E117: prih-SIZH-un | F117: Quality & Measurement | G117: How close repeated measurements are to each other. | H117: Precision means repeated measurements are close to each other. | I117: الضبط يعني أن القياسات المتكررة متقاربة. | J117: A sensor can be precise but not accurate. | K117: قد يكون الحساس مضبوطاً لكنه غير دقيق. | L117: Beginner | M117: 2 | N117: 2 – Control & Motion | التحكم والحركة | O117: High | P117: S7-INTV-001 | Q117: FutureLearn (Univ. of Reading) | R117: https://ugc.futurelearn.com/uploads/files/7a/0f/7a0fcf86-09f0-4ebf-a134-02b1290a950e/Glossary.pdf | S117: Definition paraphrased from the listed source(s); pronunciation, Arabic, examples and level are original additions.
A118: S2-CTRL-022 | B118: 114 | C118: Proportional Control | D118: التحكم التناسبي | E118: pruh-POR-shuh-nul kun-TROHL | F118: Control Systems | G118: A control strategy where the output equals the error multiplied by a constant. | H118: Proportional control makes the output proportional to the error. | I118: يجعل التحكم التناسبي الخرج متناسباً مع الخطأ. | J118: A higher proportional gain gives a faster response. | K118: كسب تناسبي أعلى يعطي استجابة أسرع. | L118: Beginner | M118: 2 | N118: 2 – Control & Motion | التحكم والحركة | O118: Normal | Q118: FutureLearn (Univ. of Reading) | R118: https://ugc.futurelearn.com/uploads/files/7a/0f/7a0fcf86-09f0-4ebf-a134-02b1290a950e/Glossary.pdf | S118: Definition paraphrased from the listed source(s); pronunciation, Arabic, examples and level are original additions.
A119: S2-MATH-019 | B119: 115 | C119: Scale | D119: التحجيم / المقياس | E119: SKAYL | F119: Math | G119: Changing magnitude by multiplying with a scalar. | H119: We scale the signal to match the controller input range. | I119: نحجّم الإشارة لتطابق مدى دخل المتحكم. | J119: The scale factor is 0.5. | K119: معامل التحجيم 0.5. | L119: Beginner | M119: 2 | N119: 2 – Control & Motion | التحكم والحركة | O119: Normal | Q119: Productivity Inc | R119: https://www.productivity.com/wp-content/uploads/2015/04/PI_RoboticGlossaryTerms.pdf | S119: Definition paraphrased from the listed source(s); pronunciation, Arabic, examples and level are original additions.
A120: S2-KINE-025 | B120: 116 | C120: Swing | D120: التأرجح / الدوران | E120: SWING | F120: Kinematics | G120: Rotational movement of a robot about its centerline. | H120: The robot swings around its base. | I120: يدور الروبوت حول قاعدته. | J120: The swing of the arm is limited by the cable. | K120: يُحدّ الكابل من تأرجح الذراع. | L120: Beginner | M120: 2 | N120: 2 – Control & Motion | التحكم والحركة | O120: Normal | Q120: Productivity Inc | R120: https://www.productivity.com/wp-content/uploads/2015/04/PI_RoboticGlossaryTerms.pdf | S120: Definition paraphrased from the listed source(s); pronunciation, Arabic, examples and level are original additions.
A121: S2-KINE-002 | B121: 117 | C121: Actual Position | D121: الموضع الفعلي | E121: AK-choo-ul puh-ZISH-un | F121: Kinematics | G121: Where the tool control point really is, which can differ from the commanded position because of unsensed errors. | H121: The encoder reports the actual position of the joint. | I121: يُبلغ المُرمِّز عن الموضع الفعلي للمفصل. | J121: The actual position differs slightly from the command position because of load. | K121: يختلف الموضع الفعلي قليلاً عن الموضع المطلوب بسبب الحِمل. | L121: Intermediate | M121: 2 | N121: 2 – Control & Motion | التحكم والحركة | O121: Normal | Q121: Productivity Inc | R121: https://www.productivity.com/wp-content/uploads/2015/04/PI_RoboticGlossaryTerms.pdf | S121: Definition paraphrased from the listed source(s); pronunciation, Arabic, examples and level are original additions.
A122: S2-DYNM-001 | B122: 118 | C122: Centrifugal Force | D122: القوة الطاردة المركزية | E122: sen-TRIF-yuh-gul FORS | F122: Dynamics | G122: The outward radial force from a body rotating about an axis other than its center, which the joint must counter with torque. | H122: Centrifugal force pushes the load outward when the arm spins quickly. | I122: تدفع القوة الطاردة المركزية الحِمل إلى الخارج عندما تدور الذراع بسرعة. | J122: The joint motor must resist centrifugal force at high speed. | K122: يجب أن يقاوم محرك المفصل القوة الطاردة المركزية عند السرعة العالية. | L122: Intermediate | M122: 2 | N122: 2 – Control & Motion | التحكم والحركة | O122: Normal | Q122: Productivity Inc | R122: https://www.productivity.com/wp-content/uploads/2015/04/PI_RoboticGlossaryTerms.pdf | S122: Definition paraphrased from the listed source(s); pronunciation, Arabic, examples and level are original additions.
A123: S2-MOTN-001 | B123: 119 | C123: Circular Motion Type | D123: نوع الحركة الدائرية | E123: SUR-kyuh-ler MOH-shun TYPE | F123: Motion Control | G123: A programmed robot path that is circular in shape. | H123: Circular motion type moves the tool along an arc. | I123: يحرّك نوع الحركة الدائرية الأداة على قوس. | J123: We used circular motion type to weld around a pipe. | K123: استخدمنا نوع الحركة الدائرية للحام حول أنبوب. | L123: Intermediate | M123: 2 | N123: 2 – Control & Motion | التحكم والحركة | O123: Normal | Q123: Productivity Inc | R123: https://www.productivity.com/wp-content/uploads/2015/04/PI_RoboticGlossaryTerms.pdf | S123: Definition paraphrased from the listed source(s); pronunciation, Arabic, examples and level are original additions.
A124: S2-KINE-004 | B124: 120 | C124: Command Position | D124: الموضع المطلوب | E124: kuh-MAND puh-ZISH-un | F124: Kinematics | G124: The endpoint the controller is trying to reach during a motion. | H124: The controller sends the command position to the motors. | I124: يرسل المتحكم الموضع المطلوب إلى المحركات. | J124: The error is the difference between command position and actual position. | K124: الخطأ هو الفرق بين الموضع المطلوب والموضع الفعلي. | L124: Intermediate | M124: 2 | N124: 2 – Control & Motion | التحكم والحركة | O124: Normal | Q124: Productivity Inc | R124: https://www.productivity.com/wp-content/uploads/2015/04/PI_RoboticGlossaryTerms.pdf | S124: Definition paraphrased from the listed source(s); pronunciation, Arabic, examples and level are original additions.
A125: S2-MECH-001 | B125: 121 | C125: Compliance | D125: المطاوعة | E125: kum-PLY-unts | F125: Mechanical | G125: How much a structure deflects under load; the inverse of stiffness and different from backlash. | H125: Compliance measures how much a structure bends under force. | I125: تقيس المطاوعة مقدار انحناء الهيكل تحت القوة. | J125: Too much compliance makes the arm springy and less precise. | K125: المطاوعة الزائدة تجعل الذراع مرنة وأقل دقة. | L125: Intermediate | M125: 2 | N125: 2 – Control & Motion | التحكم والحركة | O125: Normal | Q125: Engineers Universe + Productivity Inc | R125: https://engineersuniverse.com/studios/mechatronics/mechatronics-terminology-glossary | https://www.productivity.com/wp-content/uploads/2015/04/PI_RoboticGlossaryTerms.pdf | S125: Definition paraphrased from the listed source(s); pronunciation, Arabic, examples and level are original additions.
A126: S2-ROBT-002 | B126: 122 | C126: Compliant Robot | D126: روبوت مطاوع | E126: kum-PLY-unt ROH-bot | F126: Robot Types | G126: A robot that adjusts its motions to minimize external forces while performing tasks. | H126: A compliant robot adjusts its motion to reduce contact forces. | I126: يعدّل الروبوت المطاوع حركته لتقليل قوى التلامس. | J126: Compliant robots are safer to work beside people. | K126: الروبوتات المطاوعة أكثر أماناً للعمل بجانب الناس. | L126: Intermediate | M126: 2 | N126: 2 – Control & Motion | التحكم والحركة | O126: Normal | Q126: Productivity Inc | R126: https://www.productivity.com/wp-content/uploads/2015/04/PI_RoboticGlossaryTerms.pdf | S126: Definition paraphrased from the listed source(s); pronunciation, Arabic, examples and level are original additions.
A127: S2-KINE-005 | B127: 123 | C127: Configuration | D127: التهيئة / الوضعية | E127: kun-fig-yuh-RAY-shun | F127: Kinematics | G127: The arrangement of links produced by a particular set of joint positions; several configurations can reach the same endpoint. | H127: The same endpoint can be reached with more than one arm configuration. | I127: يمكن الوصول إلى نقطة النهاية نفسها بأكثر من وضعية للذراع. | J127: Choose the configuration that avoids the obstacle. | K127: اختر الوضعية التي تتجنب العائق. | L127: Intermediate | M127: 2 | N127: 2 – Control & Motion | التحكم والحركة | O127: High | P127: S7-INTV-009; S7-TRBL-012 | Q127: Productivity Inc | R127: https://www.productivity.com/wp-content/uploads/2015/04/PI_RoboticGlossaryTerms.pdf | S127: Definition paraphrased from the listed source(s); pronunciation, Arabic, examples and level are original additions.
A128: S2-MOTN-003 | B128: 124 | C128: Continuous Path | D128: المسار المستمر | E128: kun-TIN-yoo-us PATH | F128: Motion Control | G128: Control over the entire traversed path for smooth motion, as in spray painting. | H128: Spray painting needs continuous path control for smooth coverage. | I128: يحتاج الطلاء بالرش إلى تحكم بالمسار المستمر لتغطية سلسة. | J128: The robot follows a continuous path along the car door. | K128: يتبع الروبوت مساراً مستمراً على طول باب السيارة. | L128: Intermediate | M128: 2 | N128: 2 – Control & Motion | التحكم والحركة | O128: Normal | Q128: Productivity Inc | R128: https://www.productivity.com/wp-content/uploads/2015/04/PI_RoboticGlossaryTerms.pdf | S128: Definition paraphrased from the listed source(s); pronunciation, Arabic, examples and level are original additions.
A129: S2-CTRL-004 | B129: 125 | C129: Control Algorithm | D129: خوارزمية التحكم | E129: kun-TROHL AL-guh-rith-um | F129: Control Systems | G129: A method that detects trajectory deviations and computes actuator torques to correct them. | H129: The control algorithm corrects the error between target and actual motion. | I129: تصحح خوارزمية التحكم الخطأ بين الحركة المطلوبة والفعلية. | J129: We tuned the control algorithm to reduce vibration. | K129: ضبطنا خوارزمية التحكم لتقليل الاهتزاز. | L129: Intermediate | M129: 2 | N129: 2 – Control & Motion | التحكم والحركة | O129: Normal | Q129: Productivity Inc | R129: https://www.productivity.com/wp-content/uploads/2015/04/PI_RoboticGlossaryTerms.pdf | S129: Definition paraphrased from the listed source(s); pronunciation, Arabic, examples and level are original additions.
A130: S2-KINE-007 | B130: 126 | C130: Dexterity | D130: البراعة / المهارة الحركية | E130: dek-STAIR-ih-tee | F130: Kinematics | G130: A measure of a robot's skill at completing difficult paths. | H130: Dexterity shows how well a robot can follow a difficult path. | I130: تُظهر البراعة مدى قدرة الروبوت على اتباع مسار صعب. | J130: Surgical robots need high dexterity. | K130: تحتاج الروبوتات الجراحية إلى براعة عالية. | L130: Intermediate | M130: 2 | N130: 2 – Control & Motion | التحكم والحركة | O130: Normal | Q130: Productivity Inc | R130: https://www.productivity.com/wp-content/uploads/2015/04/PI_RoboticGlossaryTerms.pdf | S130: Definition paraphrased from the listed source(s); pronunciation, Arabic, examples and level are original additions.
A131: S2-MATH-003 | B131: 127 | C131: Differentiation | D131: التفاضل | E131: dif-uh-ren-shee-AY-shun | F131: Math | G131: A calculus operation that finds the rate of change of a function; the reverse of integration. | H131: Differentiation gives the rate of change of a function. | I131: يعطي التفاضل معدل تغير الدالة. | J131: Velocity is found by differentiation of position. | K131: تُوجد السرعة بتفاضل الموضع. | L131: Intermediate | M131: 2 | N131: 2 – Control & Motion | التحكم والحركة | O131: Normal | Q131: FutureLearn (Univ. of Reading) | R131: https://ugc.futurelearn.com/uploads/files/7a/0f/7a0fcf86-09f0-4ebf-a134-02b1290a950e/Glossary.pdf | S131: Definition paraphrased from the listed source(s); pronunciation, Arabic, examples and level are original additions.
A132: S2-DYNM-002 | B132: 128 | C132: Dynamics | D132: الديناميكا | E132: dy-NAM-iks | F132: Dynamics | G132: The study of motion, the forces causing it, and forces arising from it, which are complex in robot arms. | H132: Robot dynamics studies motion and the forces that cause it. | I132: تدرس ديناميكا الروبوت الحركة والقوى المسببة لها. | J132: The dynamics of a long arm are complex. | K132: ديناميكا الذراع الطويلة معقدة. | L132: Intermediate | M132: 2 | N132: 2 – Control & Motion | التحكم والحركة | O132: Normal | Q132: Productivity Inc | R132: https://www.productivity.com/wp-content/uploads/2015/04/PI_RoboticGlossaryTerms.pdf | S132: Definition paraphrased from the listed source(s); pronunciation, Arabic, examples and level are original additions.
A133: S2-KINE-009 | B133: 129 | C133: Endpoint | D133: نقطة النهاية | E133: END-point | F133: Kinematics | G133: The nominal commanded position a manipulator aims for at the end of a motion path, located at the distal link. | H133: The endpoint of the motion is the target position. | I133: نقطة نهاية الحركة هي الموضع المستهدف. | J133: The robot stops at the endpoint and waits for the next command. | K133: يتوقف الروبوت عند نقطة النهاية وينتظر الأمر التالي. | L133: Intermediate | M133: 2 | N133: 2 – Control & Motion | التحكم والحركة | O133: Normal | Q133: Productivity Inc | R133: https://www.productivity.com/wp-content/uploads/2015/04/PI_RoboticGlossaryTerms.pdf | S133: Definition paraphrased from the listed source(s); pronunciation, Arabic, examples and level are original additions.
A134: S2-KINE-011 | B134: 130 | C134: Frame | D134: إطار مرجعي | E134: FRAYM | F134: Kinematics | G134: A coordinate system that defines an object's or the robot's position and orientation in space. | H134: Each tool has its own coordinate frame. | I134: لكل أداة إطار إحداثيات خاص بها. | J134: Define the base frame before teaching the points. | K134: عرِّف إطار القاعدة قبل تعليم النقاط. | L134: Intermediate | M134: 2 | N134: 2 – Control & Motion | التحكم والحركة | O134: Normal | Q134: Productivity Inc | R134: https://www.productivity.com/wp-content/uploads/2015/04/PI_RoboticGlossaryTerms.pdf | S134: Definition paraphrased from the listed source(s); pronunciation, Arabic, examples and level are original additions.
A135: S2-CTRL-017 | B135: 131 | C135: Integral control | D135: التحكم التكاملي | E135: IN-tuh-grul kun-TROHL | F135: Control Systems | G135: A feedback control method where the output depends on the error and its past values. | H135: Integral control removes the steady-state error. | I135: يزيل التحكم التكاملي الخطأ المستقر. | J135: Integral control adds up the error over time. | K135: يجمع التحكم التكاملي الخطأ عبر الزمن. | L135: Intermediate | M135: 2 | N135: 2 – Control & Motion | التحكم والحركة | O135: High | P135: S7-INTV-004 | Q135: FutureLearn (Univ. of Reading) | R135: https://ugc.futurelearn.com/uploads/files/7a/0f/7a0fcf86-09f0-4ebf-a134-02b1290a950e/Glossary.pdf | S135: Definition paraphrased from the listed source(s); pronunciation, Arabic, examples and level are original additions.
A136: S2-MATH-008 | B136: 132 | C136: Integration | D136: التكامل | E136: in-tuh-GRAY-shun | F136: Math | G136: A calculus operation that finds the area under a function; the reverse of differentiation. | H136: Integration finds the area under a curve. | I136: يجد التكامل المساحة تحت المنحنى. | J136: Position is found by integration of velocity. | K136: يُوجد الموضع بتكامل السرعة. | L136: Intermediate | M136: 2 | N136: 2 – Control & Motion | التحكم والحركة | O136: Normal | Q136: FutureLearn (Univ. of Reading) | R136: https://ugc.futurelearn.com/uploads/files/7a/0f/7a0fcf86-09f0-4ebf-a134-02b1290a950e/Glossary.pdf | S136: Definition paraphrased from the listed source(s); pronunciation, Arabic, examples and level are original additions.
A137: S2-MATH-009 | B137: 133 | C137: Iteration | D137: التكرار | E137: it-uh-RAY-shun | F137: Math | G137: Repeating a procedure to refine a solution. | H137: Each iteration brings the answer closer to the target. | I137: كل تكرار يقرّب الإجابة من الهدف. | J137: The solver stopped after ten iterations. | K137: توقف الحلّال بعد عشرة تكرارات. | L137: Intermediate | M137: 2 | N137: 2 – Control & Motion | التحكم والحركة | O137: Normal | Q137: Productivity Inc | R137: https://www.productivity.com/wp-content/uploads/2015/04/PI_RoboticGlossaryTerms.pdf | S137: Definition paraphrased from the listed source(s); pronunciation, Arabic, examples and level are original additions.
A138: S2-MOTN-007 | B138: 134 | C138: Joint Motion Type | D138: نوع الحركة المفصلية | E138: JOYNT MOH-shun TYPE | F138: Motion Control | G138: Point-to-point motion in which each joint moves directly to its target, so all axes arrive together along a non-linear path. | H138: Joint motion type moves each joint directly to its target. | I138: يحرّك نوع الحركة المفصلية كل مفصل مباشرة إلى هدفه. | J138: The path in joint motion type is not a straight line. | K138: المسار في نوع الحركة المفصلية ليس خطاً مستقيماً. | L138: Intermediate | M138: 2 | N138: 2 – Control & Motion | التحكم والحركة | O138: Normal | Q138: Productivity Inc | R138: https://www.productivity.com/wp-content/uploads/2015/04/PI_RoboticGlossaryTerms.pdf | S138: Definition paraphrased from the listed source(s); pronunciation, Arabic, examples and level are original additions.
...

Sheet S1 Fundamentals
A1: Stage 1: Robotics Fundamentals — أساسيات الروبوتات
A2: What a robot is: parts, joints, robot types, basic geometry and terms. | ما هو الروبوت: أجزاؤه ومفاصله وأنواعه والمصطلحات والهندسة الأساسية.
A4: content_id | B4: # | C4: Term | D4: Arabic meaning | E4: Pronunciation | F4: Category | G4: Simple English definition | H4: Example 1 | I4: Arabic translation 1 | J4: Example 2 | K4: Arabic translation 2 | L4: Difficulty level | M4: Stage # | N4: Curriculum stage | O4: Interview priority | P4: Linked Q&A / troubleshooting | Q4: Source | R4: source_url | S4: Copyright/source note
A5: S1-KINE-001 | B5: 1 | C5: Acceleration | D5: التسارع | E5: ak-sel-er-AY-shun | F5: Kinematics | G5: A change in how fast something moves or in its direction of travel. | H5: The robot needs high acceleration to move quickly. | I5: يحتاج الروبوت إلى تسارع عالٍ ليتحرك بسرعة. | J5: Acceleration is the change of velocity over time. | K5: التسارع هو تغير السرعة عبر الزمن. | L5: Beginner | M5: 1 | N5: 1 – Robotics Fundamentals | أساسيات الروبوتات | O5: Normal | Q5: FutureLearn (Univ. of Reading) | R5: https://ugc.futurelearn.com/uploads/files/7a/0f/7a0fcf86-09f0-4ebf-a134-02b1290a950e/Glossary.pdf | S5: Definition paraphrased from the listed source(s); pronunciation, Arabic, examples and level are original additions.
A6: S1-PROG-001 | B6: 2 | C6: Algorithm | D6: خوارزمية | E6: AL-guh-rith-um | F6: Programming | G6: A set of steps for solving a problem. | H6: The algorithm tells the robot how to find the shortest path. | I6: تخبر الخوارزمية الروبوت كيف يجد أقصر مسار. | J6: We improved the algorithm to reduce the calculation time. | K6: حسّنا الخوارزمية لتقليل زمن الحساب. | L6: Beginner | M6: 1 | N6: 1 – Robotics Fundamentals | أساسيات الروبوتات | O6: Normal | Q6: FutureLearn (Univ. of Reading) + Productivity Inc | R6: https://ugc.futurelearn.com/uploads/files/7a/0f/7a0fcf86-09f0-4ebf-a134-02b1290a950e/Glossary.pdf | https://www.productivity.com/wp-content/uploads/2015/04/PI_RoboticGlossaryTerms.pdf | S6: Definition paraphrased from the listed source(s); pronunciation, Arabic, examples and level are original additions.
A7: S1-ROBT-001 | B7: 3 | C7: Android | D7: روبوت شبيه بالإنسان (أندرويد) | E7: AN-droyd | F7: Robot Types | G7: A robot that resembles a human to some degree. | H7: An android is a robot that looks like a human. | I7: الأندرويد روبوت يشبه الإنسان. | J7: The museum has an android that greets visitors. | K7: لدى المتحف روبوت شبيه بالإنسان يستقبل الزوار. | L7: Beginner | M7: 1 | N7: 1 – Robotics Fundamentals | أساسيات الروبوتات | O7: Normal | Q7: FutureLearn (Univ. of Reading) | R7: https://ugc.futurelearn.com/uploads/files/7a/0f/7a0fcf86-09f0-4ebf-a134-02b1290a950e/Glossary.pdf | S7: Definition paraphrased from the listed source(s); pronunciation, Arabic, examples and level are original additions.
A8: S1-MECH-001 | B8: 4 | C8: Arm | D8: الذراع | E8: ARM | F8: Mechanical | G8: The linked, powered segments of a manipulator that move the wrist and end-effector, excluding the end-effector itself. | H8: The robot arm can lift up to ten kilograms. | I8: يستطيع ذراع الروبوت رفع ما يصل إلى عشرة كيلوغرامات. | J8: The arm has six joints and a gripper at its end. | K8: للذراع ستة مفاصل وقابض في نهايتها. | L8: Beginner | M8: 1 | N8: 1 – Robotics Fundamentals | أساسيات الروبوتات | O8: Normal | Q8: Productivity Inc | R8: https://www.productivity.com/wp-content/uploads/2015/04/PI_RoboticGlossaryTerms.pdf | S8: Definition paraphrased from the listed source(s); pronunciation, Arabic, examples and level are original additions.
A9: S1-CMAI-001 | B9: 5 | C9: Artificial Intelligence | D9: الذكاء الاصطناعي | E9: ar-tih-FISH-ul in-TEL-ih-juns | F9: Computing & AI | G9: Intelligence shown by a machine. | H9: Artificial intelligence lets machines learn from data. | I9: يتيح الذكاء الاصطناعي للآلات التعلم من البيانات. | J9: Modern robots use artificial intelligence to recognize objects. | K9: تستخدم الروبوتات الحديثة الذكاء الاصطناعي للتعرف على الأجسام. | L9: Beginner | M9: 1 | N9: 1 – Robotics Fundamentals | أساسيات الروبوتات | O9: Normal | Q9: FutureLearn (Univ. of Reading) | R9: https://ugc.futurelearn.com/uploads/files/7a/0f/7a0fcf86-09f0-4ebf-a134-02b1290a950e/Glossary.pdf | S9: Definition paraphrased from the listed source(s); pronunciation, Arabic, examples and level are original additions.
A10: S1-ROBT-003 | B10: 6 | C10: Autonomous | D10: ذاتي التشغيل / مستقل | E10: aw-TON-uh-mus | F10: Robot Types | G10: Procedures that run without worker involvement and follow pre-programmed operations. | H10: An autonomous robot makes its own decisions without a human. | I10: يتخذ الروبوت الذاتي التشغيل قراراته بنفسه دون إنسان. | J10: Autonomous vehicles use sensors to avoid obstacles. | K10: تستخدم المركبات ذاتية القيادة الحساسات لتجنب العوائق. | L10: Beginner | M10: 1 | N10: 1 – Robotics Fundamentals | أساسيات الروبوتات | O10: Normal | Q10: FutureLearn (Univ. of Reading) + Productivity Inc | R10: https://ugc.futurelearn.com/uploads/files/7a/0f/7a0fcf86-09f0-4ebf-a134-02b1290a950e/Glossary.pdf | https://www.productivity.com/wp-content/uploads/2015/04/PI_RoboticGlossaryTerms.pdf | S10: Definition paraphrased from the listed source(s); pronunciation, Arabic, examples and level are original additions.
A11: S1-KINE-002 | B11: 7 | C11: Axis | D11: محور | E11: AK-sis | F11: Kinematics | G11: A direction or line of rotation along which a robot moves; most industrial robots have four or six. | H11: This robot has six axes of movement. | I11: لهذا الروبوت ستة محاور للحركة. | J11: Each axis is driven by its own servo motor. | K11: يُدار كل محور بمحرك مؤازر خاص به. | L11: Beginner | M11: 1 | N11: 1 – Robotics Fundamentals | أساسيات الروبوتات | O11: High | P11: S7-INTV-002 | Q11: Productivity Inc | R11: https://www.productivity.com/wp-content/uploads/2015/04/PI_RoboticGlossaryTerms.pdf | S11: Definition paraphrased from the listed source(s); pronunciation, Arabic, examples and level are original additions.
A12: S1-MECH-003 | B12: 8 | C12: Base | D12: القاعدة | E12: BAYSS | F12: Mechanical | G12: The stable platform to which a robotic arm is attached. | H12: The robot arm is bolted to a stable base. | I12: الذراع الآلية مثبّتة بمسامير على قاعدة ثابتة. | J12: The base must be level before installation. | K12: يجب أن تكون القاعدة مستوية قبل التركيب. | L12: Beginner | M12: 1 | N12: 1 – Robotics Fundamentals | أساسيات الروبوتات | O12: Normal | Q12: Productivity Inc | R12: https://www.productivity.com/wp-content/uploads/2015/04/PI_RoboticGlossaryTerms.pdf | S12: Definition paraphrased from the listed source(s); pronunciation, Arabic, examples and level are original additions.
A13: S1-SWDS-001 | B13: 9 | C13: CAD (Computer-Aided Design) | D13: التصميم بمساعدة الحاسوب | E13: KAD | F13: Software & Design | G13: Software for designing manufacturable parts, creating schematics, and simulating stresses on them. | H13: We drew the gripper in CAD before building it. | I13: رسمنا القابض في برنامج التصميم بمساعدة الحاسوب قبل تصنيعه. | J13: CAD software can simulate stress on a part. | K13: يستطيع برنامج التصميم بمساعدة الحاسوب محاكاة الإجهاد على القطعة. | L13: Beginner | M13: 1 | N13: 1 – Robotics Fundamentals | أساسيات الروبوتات | O13: Normal | Q13: Productivity Inc | R13: https://www.productivity.com/wp-content/uploads/2015/04/PI_RoboticGlossaryTerms.pdf | S13: Definition paraphrased from the listed source(s); pronunciation, Arabic, examples and level are original additions.
A14: S1-ROBT-006 | B14: 10 | C14: Cartesian Robot | D14: روبوت ديكارتي | E14: kar-TEE-zhun ROH-bot | F14: Robot Types | G14: A robot whose three linear joints run in the directions of a Cartesian coordinate system. | H14: A Cartesian robot has three linear axes. | I14: للروبوت الديكارتي ثلاثة محاور خطية. | J14: We used a Cartesian robot to stack boxes. | K14: استخدمنا روبوتاً ديكارتياً لتكديس الصناديق. | L14: Beginner | M14: 1 | N14: 1 – Robotics Fundamentals | أساسيات الروبوتات | O14: Normal | Q14: Productivity Inc | R14: https://www.productivity.com/wp-content/uploads/2015/04/PI_RoboticGlossaryTerms.pdf | S14: Definition paraphrased from the listed source(s); pronunciation, Arabic, examples and level are original additions.
A15: S1-MECH-004 | B15: 11 | C15: Chassis | D15: الهيكل | E15: SHAS-ee | F15: Mechanical | G15: The framework and internal parts of a machine, excluding its body or casing. | H15: The motors and batteries are mounted on the chassis. | I15: المحركات والبطاريات مركّبة على الهيكل. | J15: A strong chassis protects the electronics. | K15: الهيكل المتين يحمي الإلكترونيات. | L15: Beginner | M15: 1 | N15: 1 – Robotics Fundamentals | أساسيات الروبوتات | O15: Normal | Q15: Productivity Inc | R15: https://www.productivity.com/wp-content/uploads/2015/04/PI_RoboticGlossaryTerms.pdf | S15: Definition paraphrased from the listed source(s); pronunciation, Arabic, examples and level are original additions.
A16: S1-KINE-003 | B16: 12 | C16: Coordinates | D16: الإحداثيات | E16: koh-OR-dih-nits | F16: Kinematics | G16: A set of numbers that describes a position in two or three dimensions. | H16: The coordinates give the position of the point. | I16: تعطي الإحداثيات موضع النقطة. | J16: Enter the coordinates in millimeters. | K16: أدخل الإحداثيات بالملّيمترات. | L16: Beginner | M16: 1 | N16: 1 – Robotics Fundamentals | أساسيات الروبوتات | O16: Normal | Q16: FutureLearn (Univ. of Reading) | R16: https://ugc.futurelearn.com/uploads/files/7a/0f/7a0fcf86-09f0-4ebf-a134-02b1290a950e/Glossary.pdf | S16: Definition paraphrased from the listed source(s); pronunciation, Arabic, examples and level are original additions.
A17: S1-ROBT-009 | B17: 13 | C17: Cyborg | D17: سايبورغ (كائن سيبراني) | E17: SY-borg | F17: Robot Types | G17: An organism combining biological and mechanical or electronic parts. | H17: A cyborg combines a living body with machine parts. | I17: يجمع السايبورغ بين جسم حي وأجزاء آلية. | J17: Science fiction often shows cyborgs with robotic arms. | K17: يعرض الخيال العلمي غالباً سايبورغ بأذرع آلية. | L17: Beginner | M17: 1 | N17: 1 – Robotics Fundamentals | أساسيات الروبوتات | O17: Normal | Q17: FutureLearn (Univ. of Reading) | R17: https://ugc.futurelearn.com/uploads/files/7a/0f/7a0fcf86-09f0-4ebf-a134-02b1290a950e/Glossary.pdf | S17: Definition paraphrased from the listed source(s); pronunciation, Arabic, examples and level are original additions.
A18: S1-FUND-001 | B18: 14 | C18: Degrees | D18: الدرجات | E18: dih-GREEZ | F18: Fundamentals | G18: A unit for measuring angles, where a full turn is 360 degrees. | H18: A full circle has 360 degrees. | I18: للدائرة الكاملة 360 درجة. | J18: The joint rotates 90 degrees. | K18: يدور المفصل 90 درجة. | L18: Beginner | M18: 1 | N18: 1 – Robotics Fundamentals | أساسيات الروبوتات | O18: Normal | Q18: FutureLearn (Univ. of Reading) | R18: https://ugc.futurelearn.com/uploads/files/7a/0f/7a0fcf86-09f0-4ebf-a134-02b1290a950e/Glossary.pdf | S18: Definition paraphrased from the listed source(s); pronunciation, Arabic, examples and level are original additions.
A19: S1-KINE-004 | B19: 15 | C19: Degrees of Freedom (DOF) | D19: درجات الحرية | E19: dih-GREEZ uv FREE-dum | F19: Kinematics | G19: The number of independent parameters needed to define a system's position and orientation. | H19: This robot has six degrees of freedom. | I19: لهذا الروبوت ست درجات حرية. | J19: More degrees of freedom give more flexibility but harder control. | K19: مزيد من درجات الحرية يعطي مرونة أكبر لكن تحكماً أصعب. | L19: Beginner | M19: 1 | N19: 1 – Robotics Fundamentals | أساسيات الروبوتات | O19: High | P19: S7-INTV-002 | Q19: Engineers Universe + FutureLearn (Univ. of Reading) + Productivity Inc | R19: https://engineersuniverse.com/studios/mechatronics/mechatronics-terminology-glossary | https://ugc.futurelearn.com/uploads/files/7a/0f/7a0fcf86-09f0-4ebf-a134-02b1290a950e/Glossary.pdf | https://www.productivity.com/wp-content/uploads/2015/04/PI_RoboticGlossaryTerms.pdf | S19: Definition paraphrased from the listed source(s); pronunciation, Arabic, examples and level are original additions.
A20: S1-FUND-002 | B20: 16 | C20: Device | D20: جهاز | E20: dih-VYSE | F20: Fundamentals | G20: Hardware used to control parts of a system. | H20: Each device on the network has its own address. | I20: لكل جهاز على الشبكة عنوانه الخاص. | J20: The device controls part of the system. | K20: يتحكم الجهاز في جزء من النظام. | L20: Beginner | M20: 1 | N20: 1 – Robotics Fundamentals | أساسيات الروبوتات | O20: Normal | Q20: Productivity Inc | R20: https://www.productivity.com/wp-content/uploads/2015/04/PI_RoboticGlossaryTerms.pdf | S20: Definition paraphrased from the listed source(s); pronunciation, Arabic, examples and level are original additions.
A21: S1-ELEC-001 | B21: 17 | C21: Electronics | D21: الإلكترونيات | E21: ih-lek-TRON-iks | F21: Electronics | G21: The study of how electrons flow through and are controlled by components like batteries, resistors, and motors. | H21: Electronics is the study of circuits and components. | I21: الإلكترونيات هي دراسة الدوائر والمكونات. | J21: Robots depend on electronics to sense and control. | K21: تعتمد الروبوتات على الإلكترونيات للاستشعار والتحكم. | L21: Beginner | M21: 1 | N21: 1 – Robotics Fundamentals | أساسيات الروبوتات | O21: Normal | Q21: FutureLearn (Univ. of Reading) | R21: https://ugc.futurelearn.com/uploads/files/7a/0f/7a0fcf86-09f0-4ebf-a134-02b1290a950e/Glossary.pdf | S21: Definition paraphrased from the listed source(s); pronunciation, Arabic, examples and level are original additions.
A22: S1-TOOL-001 | B22: 18 | C22: End Effector | D22: المؤثر النهائي | E22: END ih-FEK-ter | F22: Tooling | G22: The tool at the end of a robot arm that interacts with the environment, such as a gripper or torch. | H22: The end effector of this robot is a vacuum gripper. | I22: المؤثر النهائي لهذا الروبوت قابض تفريغ. | J22: We changed the end effector to handle a larger part. | K22: غيّرنا المؤثر النهائي للتعامل مع قطعة أكبر. | L22: Beginner | M22: 1 | N22: 1 – Robotics Fundamentals | أساسيات الروبوتات | O22: Normal | Q22: Engineers Universe + FutureLearn (Univ. of Reading) + Productivity Inc | R22: https://engineersuniverse.com/studios/mechatronics/mechatronics-terminology-glossary | https://ugc.futurelearn.com/uploads/files/7a/0f/7a0fcf86-09f0-4ebf-a134-02b1290a950e/Glossary.pdf | https://www.productivity.com/wp-content/uploads/2015/04/PI_RoboticGlossaryTerms.pdf | S22: Definition paraphrased from the listed source(s); pronunciation, Arabic, examples and level are original additions.
A23: S1-FUND-003 | B23: 19 | C23: Energy Source | D23: مصدر الطاقة | E23: EN-er-jee SORS | F23: Fundamentals | G23: Where energy comes from, such as chemical, thermal, or mechanical processes. | H23: A battery is the energy source of a mobile robot. | I23: البطارية هي مصدر الطاقة للروبوت المتنقل. | J23: Choose an energy source that matches the actuators. | K23: اختر مصدر طاقة يناسب المشغّلات. | L23: Beginner | M23: 1 | N23: 1 – Robotics Fundamentals | أساسيات الروبوتات | O23: Normal | Q23: Productivity Inc | R23: https://www.productivity.com/wp-content/uploads/2015/04/PI_RoboticGlossaryTerms.pdf | S23: Definition paraphrased from the listed source(s); pronunciation, Arabic, examples and level are original additions.
A24: S1-FUND-004 | B24: 20 | C24: Flexibility | D24: المرونة | E24: flek-suh-BIL-ih-tee | F24: Fundamentals | G24: The range of diverse jobs a robot can perform. | H24: Flexibility lets one robot do many different jobs. | I24: تتيح المرونة لروبوت واحد القيام بمهام كثيرة مختلفة. | J24: The line needs flexibility because products change often. | K24: يحتاج الخط إلى المرونة لأن المنتجات تتغير كثيراً. | L24: Beginner | M24: 1 | N24: 1 – Robotics Fundamentals | أساسيات الروبوتات | O24: Normal | Q24: Productivity Inc | R24: https://www.productivity.com/wp-content/uploads/2015/04/PI_RoboticGlossaryTerms.pdf | S24: Definition paraphrased from the listed source(s); pronunciation, Arabic, examples and level are original additions.
A25: S1-DYNM-001 | B25: 21 | C25: Force | D25: القوة | E25: FORS | F25: Dynamics | G25: The strength behind an action or movement. | H25: The motor creates a force that moves the arm. | I25: يخلق المحرك قوة تحرك الذراع. | J25: Force is measured in newtons. | K25: تُقاس القوة بالنيوتن. | L25: Beginner | M25: 1 | N25: 1 – Robotics Fundamentals | أساسيات الروبوتات | O25: Normal | Q25: FutureLearn (Univ. of Reading) | R25: https://ugc.futurelearn.com/uploads/files/7a/0f/7a0fcf86-09f0-4ebf-a134-02b1290a950e/Glossary.pdf | S25: Definition paraphrased from the listed source(s); pronunciation, Arabic, examples and level are original additions.
A26: S1-TOOL-002 | B26: 22 | C26: Gripper | D26: القابض | E26: GRIP-er | F26: Tooling | G26: An end-effector that seizes and holds objects through pressure, magnetism, or vacuum. | H26: The gripper holds the bottle without dropping it. | I26: يمسك القابض الزجاجة دون إسقاطها. | J26: A magnetic gripper can pick up steel parts. | K26: يستطيع القابض المغناطيسي التقاط القطع الفولاذية. | L26: Beginner | M26: 1 | N26: 1 – Robotics Fundamentals | أساسيات الروبوتات | O26: High | P26: S7-TRBL-006 | Q26: FutureLearn (Univ. of Reading) + Productivity Inc | R26: https://ugc.futurelearn.com/uploads/files/7a/0f/7a0fcf86-09f0-4ebf-a134-02b1290a950e/Glossary.pdf | https://www.productivity.com/wp-content/uploads/2015/04/PI_RoboticGlossaryTerms.pdf | S26: Definition paraphrased from the listed source(s); pronunciation, Arabic, examples and level are original additions.
A27: S1-TOOL-003 | B27: 23 | C27: Hand | D27: اليد | E27: HAND | F27: Tooling | G27: A clamp or gripper used as an end-effector to grasp objects. | H27: The robot hand can hold small objects. | I27: تستطيع يد الروبوت حمل الأشياء الصغيرة. | J27: A two-finger hand is enough for this task. | K27: يد بإصبعين تكفي لهذه المهمة. | L27: Beginner | M27: 1 | N27: 1 – Robotics Fundamentals | أساسيات الروبوتات | O27: Normal | Q27: Productivity Inc | R27: https://www.productivity.com/wp-content/uploads/2015/04/PI_RoboticGlossaryTerms.pdf | S27: Definition paraphrased from the listed source(s); pronunciation, Arabic, examples and level are original additions.
A28: S1-EMBD-001 | B28: 24 | C28: Hardware | D28: العتاد (الأجهزة) | E28: HARD-wair | F28: Embedded Systems | G28: The physical parts of a computer. | H28: The hardware includes the motors, sensors, and controller. | I28: يشمل العتاد المحركات والحساسات والمتحكم. | J28: We replaced the faulty hardware, not the software. | K28: استبدلنا العتاد المعطوب وليس البرمجيات. | L28: Beginner | M28: 1 | N28: 1 – Robotics Fundamentals | أساسيات الروبوتات | O28: Normal | Q28: FutureLearn (Univ. of Reading) | R28: https://ugc.futurelearn.com/uploads/files/7a/0f/7a0fcf86-09f0-4ebf-a134-02b1290a950e/Glossary.pdf | S28: Definition paraphrased from the listed source(s); pronunciation, Arabic, examples and level are original additions.
A29: S1-ROBT-014 | B29: 25 | C29: Industrial Robot | D29: روبوت صناعي | E29: in-DUS-tree-ul ROH-bot | F29: Robot Types | G29: A reprogrammable multifunction manipulator that moves materials, parts, tools, or devices through varied programmed motions. | H29: An industrial robot is a reprogrammable multi-purpose manipulator. | I29: الروبوت الصناعي ذراع متعددة الأغراض قابلة لإعادة البرمجة. | J29: The industrial robot paints car bodies all day. | K29: يطلي الروبوت الصناعي هياكل السيارات طوال اليوم. | L29: Beginner | M29: 1 | N29: 1 – Robotics Fundamentals | أساسيات الروبوتات | O29: Normal | Q29: FutureLearn (Univ. of Reading) + Productivity Inc | R29: https://ugc.futurelearn.com/uploads/files/7a/0f/7a0fcf86-09f0-4ebf-a134-02b1290a950e/Glossary.pdf | https://www.productivity.com/wp-content/uploads/2015/04/PI_RoboticGlossaryTerms.pdf | S29: Definition paraphrased from the listed source(s); pronunciation, Arabic, examples and level are original additions.
A30: S1-ROBT-015 | B30: 26 | C30: Insect robot | D30: روبوت حشري | E30: IN-sekt ROH-bot | F30: Robot Types | G30: A small mobile robot. | H30: An insect robot is small and walks on six legs. | I30: الروبوت الحشري صغير ويمشي على ست أرجل. | J30: The insect robot can climb over small obstacles. | K30: يستطيع الروبوت الحشري تسلق عوائق صغيرة. | L30: Beginner | M30: 1 | N30: 1 – Robotics Fundamentals | أساسيات الروبوتات | O30: Normal | Q30: FutureLearn (Univ. of Reading) | R30: https://ugc.futurelearn.com/uploads/files/7a/0f/7a0fcf86-09f0-4ebf-a134-02b1290a950e/Glossary.pdf | S30: Definition paraphrased from the listed source(s); pronunciation, Arabic, examples and level are original additions.
A31: S1-CMAI-004 | B31: 27 | C31: Intelligence | D31: الذكاء | E31: in-TEL-ih-juns | F31: Computing & AI | G31: The capacity to gain and use skills and knowledge. | H31: Intelligence is the ability to learn and use knowledge. | I31: الذكاء هو القدرة على التعلم واستخدام المعرفة. | J31: Robots with some intelligence can adapt to change. | K31: الروبوتات ذات الذكاء المحدود تستطيع التكيف مع التغيير. | L31: Beginner | M31: 1 | N31: 1 – Robotics Fundamentals | أساسيات الروبوتات | O31: Normal | Q31: FutureLearn (Univ. of Reading) | R31: https://ugc.futurelearn.com/uploads/files/7a/0f/7a0fcf86-09f0-4ebf-a134-02b1290a950e/Glossary.pdf | S31: Definition paraphrased from the listed source(s); pronunciation, Arabic, examples and level are original additions.
A32: S1-ROBT-016 | B32: 28 | C32: Intelligent Robot | D32: روبوت ذكي | E32: in-TEL-ih-junt ROH-bot | F32: Robot Types | G32: A robot that can make performance choices based on sensory input with little human help. | H32: An intelligent robot can choose actions based on its sensors. | I32: يستطيع الروبوت الذكي اختيار الأفعال بناءً على حساساته. | J32: Intelligent robots need little help from humans. | K32: لا تحتاج الروبوتات الذكية إلا إلى مساعدة قليلة من البشر. | L32: Beginner | M32: 1 | N32: 1 – Robotics Fundamentals | أساسيات الروبوتات | O32: Normal | Q32: FutureLearn (Univ. of Reading) + Productivity Inc | R32: https://ugc.futurelearn.com/uploads/files/7a/0f/7a0fcf86-09f0-4ebf-a134-02b1290a950e/Glossary.pdf | https://www.productivity.com/wp-content/uploads/2015/04/PI_RoboticGlossaryTerms.pdf | S32: Definition paraphrased from the listed source(s); pronunciation, Arabic, examples and level are original additions.
A33: S1-MECH-005 | B33: 29 | C33: Joint | D33: مفصل | E33: JOYNT | F33: Mechanical | G33: A rotational or translational degree of freedom between links or between a link and the end-effector. | H33: Each joint of the robot has its own motor. | I33: لكل مفصل في الروبوت محركه الخاص. | J33: The elbow joint rotates up to 150 degrees. | K33: يدور مفصل المرفق حتى 150 درجة. | L33: Beginner | M33: 1 | N33: 1 – Robotics Fundamentals | أساسيات الروبوتات | O33: High | P33: S7-INTV-002 | Q33: FutureLearn (Univ. of Reading) + Productivity Inc | R33: https://ugc.futurelearn.com/uploads/files/7a/0f/7a0fcf86-09f0-4ebf-a134-02b1290a950e/Glossary.pdf | https://www.productivity.com/wp-content/uploads/2015/04/PI_RoboticGlossaryTerms.pdf | S33: Definition paraphrased from the listed source(s); pronunciation, Arabic, examples and level are original additions.
A34: S1-ROBT-017 | B34: 30 | C34: Jointed Arm Robot | D34: روبوت ذو ذراع مفصلية | E34: JOYN-tid ARM ROH-bot | F34: Robot Types | G34: A robot arm with two junctions that allow motion similar to a human shoulder and elbow. | H34: A jointed arm robot moves like a human shoulder and elbow. | I34: يتحرك الروبوت ذو الذراع المفصلية مثل كتف الإنسان ومرفقه. | J34: Most welding robots are jointed arm robots. | K34: معظم روبوتات اللحام ذات أذرع مفصلية. | L34: Beginner | M34: 1 | N34: 1 – Robotics Fundamentals | أساسيات الروبوتات | O34: Normal | Q34: Productivity Inc | R34: https://www.productivity.com/wp-content/uploads/2015/04/PI_RoboticGlossaryTerms.pdf | S34: Definition paraphrased from the listed source(s); pronunciation, Arabic, examples and level are original additions.
A35: S1-ETHC-001 | B35: 31 | C35: Law of Robotics | D35: قوانين الروبوتات | E35: LAW uv roh-BOT-iks | F35: Robotics Ethics | G35: Rules created by Isaac Asimov in his robot stories to govern robot behavior. | H35: Asimov wrote the three laws of robotics. | I35: كتب أسيموف قوانين الروبوتات الثلاثة. | J35: The first law says a robot must not harm a human. | K35: ينص القانون الأول على أن الروبوت يجب ألا يؤذي إنساناً. | L35: Beginner | M35: 1 | N35: 1 – Robotics Fundamentals | أساسيات الروبوتات | O35: Normal | Q35: FutureLearn (Univ. of Reading) | R35: https://ugc.futurelearn.com/uploads/files/7a/0f/7a0fcf86-09f0-4ebf-a134-02b1290a950e/Glossary.pdf | S35: Definition paraphrased from the listed source(s); pronunciation, Arabic, examples and level are original additions.
A36: S1-BIOL-014 | B36: 32 | C36: Light seeker | D36: باحث الضوء | E36: LYTE SEEK-er | F36: Biology-Inspired | G36: A Braitenberg vehicle that turns toward lights. | H36: A light seeker turns toward the light. | I36: يتجه باحث الضوء نحو الضوء. | J36: The light seeker robot found the lamp. | K36: وجد روبوت باحث الضوء المصباح. | L36: Beginner | M36: 1 | N36: 1 – Robotics Fundamentals | أساسيات الروبوتات | O36: Normal | Q36: FutureLearn (Univ. of Reading) | R36: https://ugc.futurelearn.com/uploads/files/7a/0f/7a0fcf86-09f0-4ebf-a134-02b1290a950e/Glossary.pdf | S36: Definition paraphrased from the listed source(s); pronunciation, Arabic, examples and level are original additions.
A37: S1-KINE-005 | B37: 33 | C37: Linear motion | D37: الحركة الخطية | E37: LIN-ee-er MOH-shun | F37: Kinematics | G37: Movement in a straight line rather than rotation. | H37: Linear motion is movement in a straight line. | I37: الحركة الخطية هي حركة في خط مستقيم. | J37: A linear actuator creates linear motion. | K37: ينتج المشغّل الخطي حركة خطية. | L37: Beginner | M37: 1 | N37: 1 – Robotics Fundamentals | أساسيات الروبوتات | O37: Normal | Q37: FutureLearn (Univ. of Reading) | R37: https://ugc.futurelearn.com/uploads/files/7a/0f/7a0fcf86-09f0-4ebf-a134-02b1290a950e/Glossary.pdf | S37: Definition paraphrased from the listed source(s); pronunciation, Arabic, examples and level are original additions.
A38: S1-MECH-006 | B38: 34 | C38: Link | D38: وصلة | E38: LINK | F38: Mechanical | G38: A rigid part of a manipulator that connects adjacent joints. | H38: A link is a rigid part between two joints. | I38: الوصلة جزء صلب بين مفصلين. | J38: The upper arm link is made of aluminum. | K38: وصلة الذراع العلوية مصنوعة من الألمنيوم. | L38: Beginner | M38: 1 | N38: 1 – Robotics Fundamentals | أساسيات الروبوتات | O38: Normal | Q38: FutureLearn (Univ. of Reading) + Productivity Inc | R38: https://ugc.futurelearn.com/uploads/files/7a/0f/7a0fcf86-09f0-4ebf-a134-02b1290a950e/Glossary.pdf | https://www.productivity.com/wp-content/uploads/2015/04/PI_RoboticGlossaryTerms.pdf | S38: Definition paraphrased from the listed source(s); pronunciation, Arabic, examples and level are original additions.
A39: S1-ROBT-018 | B39: 35 | C39: Manipulator | D39: المُناوِل (الذراع الآلية) | E39: muh-NIP-yuh-lay-ter | F39: Robot Types | G39: A segmented, jointed mechanism that grasps or moves objects, controlled by an operator or programmable logic. | H39: The manipulator moves objects with its jointed arm. | I39: يحرّك المُناوِل الأجسام بذراعه المفصلية. | J39: A manipulator can be controlled by an operator or a program. | K39: يمكن التحكم بالمُناوِل بواسطة مشغّل أو برنامج. | L39: Beginner | M39: 1 | N39: 1 – Robotics Fundamentals | أساسيات الروبوتات | O39: Normal | Q39: FutureLearn (Univ. of Reading) + Productivity Inc | R39: https://ugc.futurelearn.com/uploads/files/7a/0f/7a0fcf86-09f0-4ebf-a134-02b1290a950e/Glossary.pdf | https://www.productivity.com/wp-content/uploads/2015/04/PI_RoboticGlossaryTerms.pdf | S39: Definition paraphrased from the listed source(s); pronunciation, Arabic, examples and level are original additions.
A40: S1-MECH-007 | B40: 36 | C40: Mechanical | D40: ميكانيكي | E40: muh-KAN-ih-kul | F40: Mechanical | G40: Relating to machines and apparatus. | H40: The mechanical parts of the robot include gears and links. | I40: تشمل الأجزاء الميكانيكية للروبوت التروس والوصلات. | J40: A mechanical fault can cause noise and vibration. | K40: قد يسبب العطل الميكانيكي ضجيجاً واهتزازاً. | L40: Beginner | M40: 1 | N40: 1 – Robotics Fundamentals | أساسيات الروبوتات | O40: Normal | Q40: Productivity Inc | R40: https://www.productivity.com/wp-content/uploads/2015/04/PI_RoboticGlossaryTerms.pdf | S40: Definition paraphrased from the listed source(s); pronunciation, Arabic, examples and level are original additions.
A41: S1-FUND-005 | B41: 37 | C41: Mechatronics | D41: الميكاترونيكس | E41: mek-uh-TRON-iks | F41: Fundamentals | G41: The integrated design approach combining mechanical, electronic, control, and software engineering in one system. | H41: Mechatronics combines mechanics, electronics, and software. | I41: تجمع الميكاترونيكس بين الميكانيك والإلكترونيات والبرمجيات. | J41: He studies mechatronics at the engineering faculty. | K41: يدرس الميكاترونيكس في كلية الهندسة. | L41: Beginner | M41: 1 | N41: 1 – Robotics Fundamentals | أساسيات الروبوتات | O41: Normal | Q41: Engineers Universe + FutureLearn (Univ. of Reading) | R41: https://engineersuniverse.com/studios/mechatronics/mechatronics-terminology-glossary | https://ugc.futurelearn.com/uploads/files/7a/0f/7a0fcf86-09f0-4ebf-a134-02b1290a950e/Glossary.pdf | S41: Definition paraphrased from the listed source(s); pronunciation, Arabic, examples and level are original additions.
A42: S1-ROBT-019 | B42: 38 | C42: Mobile Robot | D42: روبوت متنقل | E42: MOH-bul ROH-bot | F42: Robot Types | G42: A robot with its own power source that can move without path constraints. | H42: A mobile robot can move around without fixed tracks. | I42: يستطيع الروبوت المتنقل التحرك دون مسارات ثابتة. | J42: The mobile robot delivers parts across the factory floor. | K42: ينقل الروبوت المتنقل القطع عبر أرضية المصنع. | L42: Beginner | M42: 1 | N42: 1 – Robotics Fundamentals | أساسيات الروبوتات | O42: Normal | Q42: Productivity Inc | R42: https://www.productivity.com/wp-content/uploads/2015/04/PI_RoboticGlossaryTerms.pdf | S42: Definition paraphrased from the listed source(s); pronunciation, Arabic, examples and level are original additions.
A43: S1-BIOL-016 | B43: 39 | C43: Neuron | D43: عصبون (خلية عصبية) | E43: NOOR-on | F43: Biology-Inspired | G43: A basic processing unit in the brain, of which humans have billions. | H43: A neuron is a basic processing unit in the brain. | I43: العصبون وحدة معالجة أساسية في الدماغ. | J43: Artificial neurons are used in neural networks. | K43: تُستخدم العصبونات الاصطناعية في الشبكات العصبية. | L43: Beginner | M43: 1 | N43: 1 – Robotics Fundamentals | أساسيات الروبوتات | O43: Normal | Q43: FutureLearn (Univ. of Reading) | R43: https://ugc.futurelearn.com/uploads/files/7a/0f/7a0fcf86-09f0-4ebf-a134-02b1290a950e/Glossary.pdf | S43: Definition paraphrased from the listed source(s); pronunciation, Arabic, examples and level are original additions.
A44: S1-KINE-006 | B44: 40 | C44: Position | D44: الموضع | E44: puh-ZISH-un | F44: Kinematics | G44: An object's location in three-dimensional space, usually given by X, Y, and Z coordinates. | H44: The position of the tool is given by X, Y, and Z. | I44: يُعطى موضع الأداة بالقيم X وY وZ. | J44: The sensor measures the position of the arm. | K44: يقيس الحساس موضع الذراع. | L44: Beginner | M44: 1 | N44: 1 – Robotics Fundamentals | أساسيات الروبوتات | O44: Normal | Q44: FutureLearn (Univ. of Reading) + Productivity Inc | R44: https://ugc.futurelearn.com/uploads/files/7a/0f/7a0fcf86-09f0-4ebf-a134-02b1290a950e/Glossary.pdf | https://www.productivity.com/wp-content/uploads/2015/04/PI_RoboticGlossaryTerms.pdf | S44: Definition paraphrased from the listed source(s); pronunciation, Arabic, examples and level are original additions.
A45: S1-PROG-002 | B45: 41 | C45: Program | D45: برنامج / يبرمج | E45: PROH-gram | F45: Programming | G45: As a noun, a set of tasks for a controller or computer; as a verb, supplying those procedures and tasks. | H45: The robot follows a program to do its job. | I45: يتبع الروبوت برنامجاً لأداء عمله. | J45: We saved a backup copy of the program. | K45: حفظنا نسخة احتياطية من البرنامج. | L45: Beginner | M45: 1 | N45: 1 – Robotics Fundamentals | أساسيات الروبوتات | O45: Normal | Q45: FutureLearn (Univ. of Reading) + Productivity Inc | R45: https://ugc.futurelearn.com/uploads/files/7a/0f/7a0fcf86-09f0-4ebf-a134-02b1290a950e/Glossary.pdf | https://www.productivity.com/wp-content/uploads/2015/04/PI_RoboticGlossaryTerms.pdf | S45: Definition paraphrased from the listed source(s); pronunciation, Arabic, examples and level are original additions.
... A52: S1-KINE-008 | B52: 48 | C52: Rotational Motion | D52: الحركة الدورانية | E52: roh-TAY-shun-ul MOH-shun | F52: Kinematics | G52: Circular movement about an axis. | H52: Rotational motion is movement around an axis. | I52: الحركة الدورانية هي حركة حول محور. | J52: The motor produces rotational motion. | K52: ينتج المحرك حركة دورانية. | L52: Beginner | M52: 1 | N52: 1 – Robotics Fundamentals | أساسيات الروبوتات | O52: Normal | Q52: Productivity Inc | R52: https://www.productivity.com/wp-content/uploads/2015/04/PI_RoboticGlossaryTerms.pdf | S52: Definition paraphrased from the listed source(s); pronunciation, Arabic, examples and level are original additions.
A53: S1-SENS-001 | B53: 49 | C53: Sensor | D53: حساس / مستشعر | E53: SEN-ser | F53: Sensors | G53: An instrument that detects physical stimuli and reports data about the robot's environment or its own position. | H53: A sensor measures distance, temperature, or force. | I53: يقيس الحساس المسافة أو الحرارة أو القوة. | J53: The robot uses a sensor to find the object. | K53: يستخدم الروبوت حساساً لإيجاد الجسم. | L53: Beginner | M53: 1 | N53: 1 – Robotics Fundamentals | أساسيات الروبوتات | O53: High | P53: S7-TRBL-007 | Q53: FutureLearn (Univ. of Reading) + Productivity Inc | R53: https://ugc.futurelearn.com/uploads/files/7a/0f/7a0fcf86-09f0-4ebf-a134-02b1290a950e/Glossary.pdf | https://www.productivity.com/wp-content/uploads/2015/04/PI_RoboticGlossaryTerms.pdf | S53: Definition paraphrased from the listed source(s); pronunciation, Arabic, examples and level are original additions.
A54: S1-MECH-010 | B54: 50 | C54: Shoulder | D54: الكتف | E54: SHOHL-der | F54: Mechanical | G54: The joint connecting the manipulator arm to the base. | H54: The shoulder joint connects the arm to the base. | I54: يربط مفصل الكتف الذراع بالقاعدة. | J54: The shoulder motor carries the most load. | K54: يحمل محرك الكتف أكبر حِمل. | L54: Beginner | M54: 1 | N54: 1 – Robotics Fundamentals | أساسيات الروبوتات | O54: Normal | Q54: Productivity Inc | R54: https://www.productivity.com/wp-content/uploads/2015/04/PI_RoboticGlossaryTerms.pdf | S54: Definition paraphrased from the listed source(s); pronunciation, Arabic, examples and level are original additions.
A55: S1-ELEC-002 | B55: 51 | C55: Signal | D55: إشارة | E55: SIG-nul | F55: Electronics | G55: A current, voltage, or electromagnetic field used to carry information. | H55: The sensor sends a signal to the controller. | I55: يرسل الحساس إشارة إلى المتحكم. | J55: A noisy signal can cause wrong readings. | K55: قد تسبب الإشارة المشوّشة قراءات خاطئة. | L55: Beginner | M55: 1 | N55: 1 – Robotics Fundamentals | أساسيات الروبوتات | O55: High | P55: S7-TRBL-008 | Q55: FutureLearn (Univ. of Reading) | R55: https://ugc.futurelearn.com/uploads/files/7a/0f/7a0fcf86-09f0-4ebf-a134-02b1290a950e/Glossary.pdf | S55: Definition paraphrased from the listed source(s); pronunciation, Arabic, examples and level are original additions.
A56: S1-PROG-003 | B56: 52 | C56: Software | D56: البرمجيات | E56: SOFT-wair | F56: Programming | G56: A written program that instructs hardware to perform tasks. | H56: The software controls the robot's movements. | I56: تتحكم البرمجيات في حركات الروبوت. | J56: We updated the software to fix a bug. | K56: حدّثنا البرمجيات لإصلاح خلل. | L56: Beginner | M56: 1 | N56: 1 – Robotics Fundamentals | أساسيات الروبوتات | O56: Normal | Q56: FutureLearn (Univ. of Reading) + Productivity Inc | R56: https://ugc.futurelearn.com/uploads/files/7a/0f/7a0fcf86-09f0-4ebf-a134-02b1290a950e/Glossary.pdf | https://www.productivity.com/wp-content/uploads/2015/04/PI_RoboticGlossaryTerms.pdf | S56: Definition paraphrased from the listed source(s); pronunciation, Arabic, examples and level are original additions.
A57: S1-FUND-009 | B57: 53 | C57: System | D57: نظام | E57: SIS-tum | F57: Fundamentals | G57: A group of parts that work together. | H57: A robot is a system of many parts working together. | I57: الروبوت نظام من أجزاء كثيرة تعمل معاً. | J57: If one part of the system fails, the whole system may stop. | K57: إذا تعطل جزء من النظام قد يتوقف النظام بأكمله. | L57: Beginner | M57: 1 | N57: 1 – Robotics Fundamentals | أساسيات الروبوتات | O57: Normal | Q57: FutureLearn (Univ. of Reading) | R57: https://ugc.futurelearn.com/uploads/files/7a/0f/7a0fcf86-09f0-4ebf-a134-02b1290a950e/Glossary.pdf | S57: Definition paraphrased from the listed source(s); pronunciation, Arabic, examples and level are original additions.
A58: S1-TOOL-004 | B58: 54 | C58: Tool | D58: الأداة | E58: TOOL | F58: Tooling | G58: A working apparatus mounted at the arm's end, such as a gripper or welding torch. | H58: The robot changes its tool for each job. | I58: يغيّر الروبوت أداته لكل مهمة. | J58: A welding torch is a tool mounted on the arm. | K58: شعلة اللحام أداة مثبتة على الذراع. | L58: Beginner | M58: 1 | N58: 1 – Robotics Fundamentals | أساسيات الروبوتات | O58: Normal | Q58: Productivity Inc | R58: https://www.productivity.com/wp-content/uploads/2015/04/PI_RoboticGlossaryTerms.pdf | S58: Definition paraphrased from the listed source(s); pronunciation, Arabic, examples and level are original additions.
A59: S1-KINE-009 | B59: 55 | C59: Velocity | D59: السرعة المتجهة | E59: vuh-LOS-ih-tee | F59: Kinematics | G59: An object's speed together with the direction it travels. | H59: Velocity includes both speed and direction. | I59: تشمل السرعة المتجهة السرعة والاتجاه. | J59: The velocity of the arm is limited for safety. | K59: سرعة الذراع محدودة لأسباب السلامة. | L59: Beginner | M59: 1 | N59: 1 – Robotics Fundamentals | أساسيات الروبوتات | O59: Normal | Q59: FutureLearn (Univ. of Reading) | R59: https://ugc.futurelearn.com/uploads/files/7a/0f/7a0fcf86-09f0-4ebf-a134-02b1290a950e/Glossary.pdf | S59: Definition paraphrased from the listed source(s); pronunciation, Arabic, examples and level are original additions.
A60: S1-SPEC-001 | B60: 56 | C60: Workspace | D60: فضاء العمل | E60: WURK-spays | F60: Specifications | G60: The volume a robot's end effector can reach, distinguishing reachable from dexterous regions. | H60: The robot's workspace is the area it can reach. | I60: فضاء عمل الروبوت هو المنطقة التي يستطيع الوصول إليها. | J60: Remove all tools from the workspace before starting. | K60: أزل جميع الأدوات من فضاء العمل قبل البدء. | L60: Beginner | M60: 1 | N60: 1 – Robotics Fundamentals | أساسيات الروبوتات | O60: High | P60: S7-INTV-014 | Q60: Engineers Universe + Productivity Inc | R60: https://engineersuniverse.com/studios/mechatronics/mechatronics-terminology-glossary | https://www.productivity.com/wp-content/uploads/2015/04/PI_RoboticGlossaryTerms.pdf | S60: Definition paraphrased from the listed source(s); pronunciation, Arabic, examples and level are original additions.
A61: S1-MECH-011 | B61: 57 | C61: Wrist | D61: المعصم | E61: RIST | F61: Mechanical | G61: A set of rotary joints between the arm and end-effector that orient the end-effector toward the workpiece. | H61: The wrist orients the tool toward the work-piece. | I61: يوجّه المعصم الأداة نحو قطعة العمل. | J61: The wrist has three rotary joints. | K61: للمعصم ثلاثة مفاصل دوّارة. | L61: Beginner | M61: 1 | N61: 1 – Robotics Fundamentals | أساسيات الروبوتات | O61: Normal | Q61: Productivity Inc | R61: https://www.productivity.com/wp-content/uploads/2015/04/PI_RoboticGlossaryTerms.pdf | S61: Definition paraphrased from the listed source(s); pronunciation, Arabic, examples and level are original additions.
A62: S1-KINE-010 | B62: 58 | C62: XYZ Coordinates | D62: إحداثيات XYZ | E62: EKS-WY-ZEE koh-OR-dih-nits | F62: Kinematics | G62: Names for the lines forming a Cartesian solid. | H62: XYZ coordinates describe a point in three dimensions. | I62: تصف إحداثيات XYZ نقطة في ثلاثة أبعاد. | J62: Enter the XYZ coordinates of the target position. | K62: أدخل إحداثيات XYZ للموضع المستهدف. | L62: Beginner | M62: 1 | N62: 1 – Robotics Fundamentals | أساسيات الروبوتات | O62: Normal | Q62: Productivity Inc | R62: https://www.productivity.com/wp-content/uploads/2015/04/PI_RoboticGlossaryTerms.pdf | S62: Definition paraphrased from the listed source(s); pronunciation, Arabic, examples and level are original additions.
A63: S1-ROBT-002 | B63: 59 | C63: Articulated Manipulator | D63: ذراع مفصلية | E63: ar-TIK-yuh-lay-tid muh-NIP-yuh-lay-ter | F63: Robot Types | G63: A manipulator whose arm has jointed sections, with each joint adding a degree of freedom. | H63: An articulated manipulator looks like a human arm with a shoulder and elbow. | I63: يشبه الذراع المفصلية ذراع الإنسان بكتف ومرفق. | J63: Most factory robots are articulated manipulators. | K63: معظم روبوتات المصانع أذرع مفصلية. | L63: Intermediate | M63: 1 | N63: 1 – Robotics Fundamentals | أساسيات الروبوتات | O63: Normal | Q63: Productivity Inc | R63: https://www.productivity.com/wp-content/uploads/2015/04/PI_RoboticGlossaryTerms.pdf | S63: Definition paraphrased from the listed source(s); pronunciation, Arabic, examples and level are original additions.
A64: S1-MECH-002 | B64: 60 | C64: Articulation | D64: التمفصل | E64: ar-tik-yuh-LAY-shun | F64: Mechanical | G64: A jointed design that rotates and bends, letting a robot reach into confined spaces. | H64: The articulation of the arm lets it reach inside a machine. | I64: يتيح تمفصل الذراع لها الوصول إلى داخل الآلة. | J64: Good articulation gives the robot more flexibility in tight spaces. | K64: التمفصل الجيد يمنح الروبوت مرونة أكبر في الأماكن الضيقة. | L64: Intermediate | M64: 1 | N64: 1 – Robotics Fundamentals | أساسيات الروبوتات | O64: Normal | Q64: Productivity Inc | R64: https://www.productivity.com/wp-content/uploads/2015/04/PI_RoboticGlossaryTerms.pdf | S64: Definition paraphrased from the listed source(s); pronunciation, Arabic, examples and level are original additions.
A65: S1-ROBT-004 | B65: 61 | C65: Baxter robot | D65: روبوت باكستر | E65: BAK-ster ROH-bot | F65: Robot Types | G65: A modern industrial robot built to work safely alongside people. | H65: The Baxter robot was designed to work safely beside people. | I65: صُمم روبوت باكستر للعمل بأمان بجانب الناس. | J65: Small factories used Baxter for simple packing tasks. | K65: استخدمت المصانع الصغيرة باكستر لمهام تعبئة بسيطة. | L65: Intermediate | M65: 1 | N65: 1 – Robotics Fundamentals | أساسيات الروبوتات | O65: Normal | Q65: FutureLearn (Univ. of Reading) | R65: https://ugc.futurelearn.com/uploads/files/7a/0f/7a0fcf86-09f0-4ebf-a134-02b1290a950e/Glossary.pdf | S65: Definition paraphrased from the listed source(s); pronunciation, Arabic, examples and level are original additions.
A66: S1-ROBT-005 | B66: 62 | C66: Cartesian Manipulator | D66: ذراع ديكارتية | E66: kar-TEE-zhun muh-NIP-yuh-lay-ter | F66: Robot Types | G66: A robot arm with prismatic joints that move along the X, Y, and Z axes. | H66: A Cartesian manipulator uses prismatic joints on three perpendicular axes. | I66: يستخدم الذراع الديكارتي مفاصل منزلقة على ثلاثة محاور متعامدة. | J66: The Cartesian manipulator is easy to program. | K66: الذراع الديكارتي سهل البرمجة. | L66: Intermediate | M66: 1 | N66: 1 – Robotics Fundamentals | أساسيات الروبوتات | O66: Normal | Q66: Productivity Inc | R66: https://www.productivity.com/wp-content/uploads/2015/04/PI_RoboticGlossaryTerms.pdf | S66: Definition paraphrased from the listed source(s); pronunciation, Arabic, examples and level are original additions.
A67: S1-ROBT-008 | B67: 63 | C67: Cartesian-Coordinate Robot | D67: روبوت الإحداثيات الديكارتية | E67: kar-TEE-zhun koh-OR-dih-nit ROH-bot | F67: Robot Types | G67: A robot whose arm motions are defined by Cartesian coordinates, plus rotary motion for orientation. | H67: A Cartesian-coordinate robot moves along straight X, Y, and Z lines. | I67: يتحرك روبوت الإحداثيات الديكارتية على خطوط مستقيمة X وY وZ. | J67: 3D printers are simple Cartesian-coordinate robots. | K67: الطابعات ثلاثية الأبعاد روبوتات إحداثيات ديكارتية بسيطة. | L67: Intermediate | M67: 1 | N67: 1 – Robotics Fundamentals | أساسيات الروبوتات | O67: Normal | Q67: Productivity Inc | R67: https://www.productivity.com/wp-content/uploads/2015/04/PI_RoboticGlossaryTerms.pdf | S67: Definition paraphrased from the listed source(s); pronunciation, Arabic, examples and level are original additions.
A68: S1-ROBT-010 | B68: 64 | C68: Cylindrical Robot | D68: روبوت أسطواني | E68: sih-LIN-drih-kul ROH-bot | F68: Robot Types | G68: A robot whose axes correspond to a cylindrical coordinate system. | H68: A cylindrical robot moves in a circle and up and down. | I68: يتحرك الروبوت الأسطواني في دائرة وللأعلى والأسفل. | J68: The cylindrical robot loads parts into the machine. | K68: يحمّل الروبوت الأسطواني القطع في الآلة. | L68: Intermediate | M68: 1 | N68: 1 – Robotics Fundamentals | أساسيات الروبوتات | O68: Normal | Q68: Productivity Inc | R68: https://www.productivity.com/wp-content/uploads/2015/04/PI_RoboticGlossaryTerms.pdf | S68: Definition paraphrased from the listed source(s); pronunciation, Arabic, examples and level are original additions.
A69: S1-CMAI-003 | B69: 65 | C69: Human-Computer Interaction (HCI) | D69: التفاعل بين الإنسان والحاسوب | E69: HYOO-mun kum-PYOO-ter in-ter-AK-shun | F69: Computing & AI | G69: The study of how computers and humans relate to each other. | H69: HCI studies how people use computers and machines. | I69: يدرس التفاعل بين الإنسان والحاسوب كيف يستخدم الناس الحواسيب والآلات. | J69: Good HCI makes the robot panel easy to understand. | K69: التفاعل الجيد بين الإنسان والحاسوب يجعل لوحة الروبوت سهلة الفهم. | L69: Intermediate | M69: 1 | N69: 1 – Robotics Fundamentals | أساسيات الروبوتات | O69: Normal | Q69: FutureLearn (Univ. of Reading) + Productivity Inc | R69: https://ugc.futurelearn.com/uploads/files/7a/0f/7a0fcf86-09f0-4ebf-a134-02b1290a950e/Glossary.pdf | https://www.productivity.com/wp-content/uploads/2015/04/PI_RoboticGlossaryTerms.pdf | S69: Definition paraphrased from the listed source(s); pronunciation, Arabic, examples and level are original additions.
A70: S1-FUND-006 | B70: 66 | C70: Modularity | D70: النمطية / القابلية للتجزئة | E70: moj-uh-LAIR-ih-tee | F70: Fundamentals | G70: A design property allowing separate units to be easily joined or rearranged. | H70: Modularity makes the robot easy to repair and upgrade. | I70: تجعل النمطية الروبوت سهل الإصلاح والترقية. | J70: Thanks to modularity, we replaced only the gripper module. | K70: بفضل النمطية استبدلنا وحدة القابض فقط. | L70: Intermediate | M70: 1 | N70: 1 – Robotics Fundamentals | أساسيات الروبوتات | O70: Normal | Q70: Productivity Inc | R70: https://www.productivity.com/wp-content/uploads/2015/04/PI_RoboticGlossaryTerms.pdf | S70: Definition paraphrased from the listed source(s); pronunciation, Arabic, examples and level are original additions.
A71: S1-ROBT-023 | B71: 67 | C71: Rectangular-Coordinate Robot | D71: روبوت الإحداثيات المستطيلة | E71: rek-TANG-gyuh-ler koh-OR-dih-nit ROH-bot | F71: Robot Types | G71: A robot moving linearly along X, Y, and Z axes, creating a rectangular work envelope. | H71: A rectangular-coordinate robot has a box-shaped work area. | I71: لروبوت الإحداثيات المستطيلة منطقة عمل على شكل صندوق. | J71: It moves linearly along the X, Y, and Z axes. | K71: يتحرك خطياً على المحاور X وY وZ. | L71: Intermediate | M71: 1 | N71: 1 – Robotics Fundamentals | أساسيات الروبوتات | O71: Normal | Q71: Productivity Inc | R71: https://www.productivity.com/wp-content/uploads/2015/04/PI_RoboticGlossaryTerms.pdf | S71: Definition paraphrased from the listed source(s); pronunciation, Arabic, examples and level are original additions.
A72: S1-MECH-008 | B72: 68 | C72: Revolute Joint | D72: مفصل دوراني | E72: REV-uh-loot JOYNT | F72: Mechanical | G72: A joint capable of rotary motion. | H72: A revolute joint rotates around one axis. | I72: يدور المفصل الدوراني حول محور واحد. | J72: The elbow of the arm is a revolute joint. | K72: مرفق الذراع مفصل دوراني. | L72: Intermediate | M72: 1 | N72: 1 – Robotics Fundamentals | أساسيات الروبوتات | O72: Normal | Q72: Productivity Inc | R72: https://www.productivity.com/wp-content/uploads/2015/04/PI_RoboticGlossaryTerms.pdf | S72: Definition paraphrased from the listed source(s); pronunciation, Arabic, examples and level are original additions.
... A104: S1-CMAI-005 | B104: 100 | C104: World Model | D104: نموذج البيئة | E104: WURLD MOD-ul | F104: Computing & AI | G104: A stored three-dimensional representation of the robot's environment, updated as objects are sensed. | H104: The robot keeps a world model of its environment. | I104: يحتفظ الروبوت بنموذج للبيئة المحيطة به. | J104: The world model is updated when new objects are sensed. | K104: يُحدَّث نموذج البيئة عند استشعار أجسام جديدة. | L104: Advanced | M104: 1 | N104: 1 – Robotics Fundamentals | أساسيات الروبوتات | O104: Normal | Q104: Productivity Inc | R104: https://www.productivity.com/wp-content/uploads/2015/04/PI_RoboticGlossaryTerms.pdf | S104: Definition paraphrased from the listed source(s); pronunciation, Arabic, examples and level are original additions.

Sheet S2 Control & Motion
A1: Stage 2: Control & Motion — التحكم والحركة
A2: Kinematics, feedback, PID, paths, trajectories, accuracy and the math behind them. | الكينماتيكا والتغذية الراجعة وPID والمسارات والدقة والرياضيات المرتبطة بها.
A4: content_id | B4: # | C4: Term | D4: Arabic meaning | E4: Pronunciation | F4: Category | G4: Simple English definition | H4: Example 1 | I4: Arabic translation 1 | J4: Example 2 | K4: Arabic translation 2 | L4: Difficulty level | M4: Stage # | N4: Curriculum stage | O4: Interview priority | P4: Linked Q&A / troubleshooting | Q4: Source | R4: source_url | S4: Copyright/source note
A5: S2-QUAL-001 | B5: 1 | C5: Accuracy | D5: الدقة | E5: AK-yer-uh-see | F5: Quality & Measurement | G5: How closely a robot reaches a commanded point, which is usually less precise than its repeatability. | H5: The accuracy of the robot is 0.1 mm at the target point. | I5: دقة الروبوت 0.1 ملم عند النقطة المستهدفة. | J5: Accuracy is usually worse than repeatability in industrial arms. | K5: الدقة عادةً أسوأ من قابلية التكرار في الأذرع الصناعية. | L5: Beginner | M5: 2 | N5: 2 – Control & Motion | التحكم والحركة | O5: High | P5: S7-INTV-001 | Q5: FutureLearn (Univ. of Reading) + Productivity Inc | R5: https://ugc.futurelearn.com/uploads/files/7a/0f/7a0fcf86-09f0-4ebf-a134-02b1290a950e/Glossary.pdf | https://www.productivity.com/wp-content/uploads/2015/04/PI_RoboticGlossaryTerms.pdf | S5: Definition paraphrased from the listed source(s); pronunciation, Arabic, examples and level are original additions.
A6: S2-CTRL-003 | B6: 2 | C6: Closed-Loop Control | D6: التحكم بالحلقة المغلقة | E6: KLOHZD LOOP kun-TROHL | F6: Control Systems | G6: A control method that measures the output and corrects the command based on the error. | H6: Closed-loop control uses sensor feedback to correct the error. | I6: يستخدم التحكم بالحلقة المغلقة تغذية راجعة من الحساس لتصحيح الخطأ. | J6: A thermostat is a simple closed-loop control system. | K6: منظم الحرارة نظام تحكم بسيط بالحلقة المغلقة. | L6: Beginner | M6: 2 | N6: 2 – Control & Motion | التحكم والحركة | O6: High | P6: S7-INTV-003 | Q6: Engineers Universe + FutureLearn (Univ. of Reading) + Productivity Inc | R6: https://engineersuniverse.com/studios/mechatronics/mechatronics-terminology-glossary | https://ugc.futurelearn.com/uploads/files/7a/0f/7a0fcf86-09f0-4ebf-a134-02b1290a950e/Glossary.pdf | https://www.productivity.com/wp-content/uploads/2015/04/PI_RoboticGlossaryTerms.pdf | S6: Definition paraphrased from the listed source(s); pronunciation, Arabic, examples and level are original additions.
A7: S2-CTRL-005 | B7: 3 | C7: Control Engineering | D7: هندسة التحكم | E7: kun-TROHL en-juh-NEER-ing | F7: Control Systems | G7: The study of how to achieve control of systems. | H7: Control engineering designs systems that keep machines stable. | I7: تصمم هندسة التحكم أنظمة تُبقي الآلات مستقرة. | J7: He took a course in control engineering. | K7: أخذ مساقاً في هندسة التحكم. | L7: Beginner | M7: 2 | N7: 2 – Control & Motion | التحكم والحركة | O7: Normal | Q7: FutureLearn (Univ. of Reading) | R7: https://ugc.futurelearn.com/uploads/files/7a/0f/7a0fcf86-09f0-4ebf-a134-02b1290a950e/Glossary.pdf | S7: Definition paraphrased from the listed source(s); pronunciation, Arabic, examples and level are original additions.
A8: S2-CTRL-007 | B8: 4 | C8: Controller | D8: المتحكم | E8: kun-TROH-ler | F8: Control Systems | G8: A processing device that compares desired and measured values and outputs drive signals to motors or actuators. | H8: The controller compares the target value with the measured value. | I8: يقارن المتحكم القيمة المطلوبة بالقيمة المقاسة. | J8: We replaced the controller after it overheated. | K8: استبدلنا المتحكم بعد أن سخن بشكل زائد. | L8: Beginner | M8: 2 | N8: 2 – Control & Motion | التحكم والحركة | O8: High | P8: S7-TRBL-009 | Q8: FutureLearn (Univ. of Reading) + Productivity Inc | R8: https://ugc.futurelearn.com/uploads/files/7a/0f/7a0fcf86-09f0-4ebf-a134-02b1290a950e/Glossary.pdf | https://www.productivity.com/wp-content/uploads/2015/04/PI_RoboticGlossaryTerms.pdf | S8: Definition paraphrased from the listed source(s); pronunciation, Arabic, examples and level are original additions.
A9: S2-CTRL-010 | B9: 5 | C9: Error | D9: الخطأ | E9: ER-er | F9: Control Systems | G9: The difference between a robot's actual response and the command issued. | H9: The error is the difference between the target and the actual position. | I9: الخطأ هو الفرق بين الموضع المستهدف والموضع الفعلي. | J9: The controller works to reduce the error to zero. | K9: يعمل المتحكم على خفض الخطأ إلى الصفر. | L9: Beginner | M9: 2 | N9: 2 – Control & Motion | التحكم والحركة | O9: Normal | Q9: FutureLearn (Univ. of Reading) + Productivity Inc | R9: https://ugc.futurelearn.com/uploads/files/7a/0f/7a0fcf86-09f0-4ebf-a134-02b1290a950e/Glossary.pdf | https://www.productivity.com/wp-content/uploads/2015/04/PI_RoboticGlossaryTerms.pdf | S9: Definition paraphrased from the listed source(s); pronunciation, Arabic, examples and level are original additions.
A10: S2-CTRL-011 | B10: 6 | C10: Feedback | D10: التغذية الراجعة | E10: FEED-bak | F10: Control Systems | G10: A signal from robot equipment reporting actual conditions rather than what the computer commanded. | H10: Feedback tells the controller what the robot is really doing. | I10: تخبر التغذية الراجعة المتحكم بما يفعله الروبوت فعلاً. | J10: Without feedback the system cannot correct its errors. | K10: بدون تغذية راجعة لا يستطيع النظام تصحيح أخطائه. | L10: Beginner | M10: 2 | N10: 2 – Control & Motion | التحكم والحركة | O10: High | P10: S7-INTV-003 | Q10: FutureLearn (Univ. of Reading) + Productivity Inc | R10: https://ugc.futurelearn.com/uploads/files/7a/0f/7a0fcf86-09f0-4ebf-a134-02b1290a950e/Glossary.pdf | https://www.productivity.com/wp-content/uploads/2015/04/PI_RoboticGlossaryTerms.pdf | S10: Definition paraphrased from the listed source(s); pronunciation, Arabic, examples and level are original additions.
A11: S2-CTRL-012 | B11: 7 | C11: Feedback Control | D11: التحكم بالتغذية الراجعة | E11: FEED-bak kun-TROHL | F11: Control Systems | G11: Control achieved by returning manipulator or sensor information to the controller to produce a desired effect. | H11: Feedback control keeps the motor at the desired speed. | I11: يُبقي التحكم بالتغذية الراجعة المحرك عند السرعة المطلوبة. | J11: Most industrial robots use feedback control. | K11: معظم الروبوتات الصناعية تستخدم التحكم بالتغذية الراجعة. | L11: Beginner | M11: 2 | N11: 2 – Control & Motion | التحكم والحركة | O11: Normal | Q11: Productivity Inc | R11: https://www.productivity.com/wp-content/uploads/2015/04/PI_RoboticGlossaryTerms.pdf | S11: Definition paraphrased from the listed source(s); pronunciation, Arabic, examples and level are original additions.
A12: S2-CTRL-013 | B12: 8 | C12: Feedback Loop | D12: حلقة التغذية الراجعة | E12: FEED-bak LOOP | F12: Control Systems | G12: A circular route along which information travels. | H12: A feedback loop sends the output back to the input. | I12: تعيد حلقة التغذية الراجعة المخرجات إلى المدخلات. | J12: The thermostat is a classic feedback loop. | K12: منظم الحرارة مثال كلاسيكي على حلقة التغذية الراجعة. | L12: Beginner | M12: 2 | N12: 2 – Control & Motion | التحكم والحركة | O12: Normal | Q12: FutureLearn (Univ. of Reading) | R12: https://ugc.futurelearn.com/uploads/files/7a/0f/7a0fcf86-09f0-4ebf-a134-02b1290a950e/Glossary.pdf | S12: Definition paraphrased from the listed source(s); pronunciation, Arabic, examples and level are original additions.
A13: S2-CTRL-016 | B13: 9 | C13: Gain | D13: الكسب | E13: GAYN | F13: Control Systems | G13: A multiplier applied to a control signal; PID gains set responses to error, accumulated error, and error rate. | H13: Increasing the gain makes the controller respond faster. | I13: زيادة الكسب تجعل المتحكم يستجيب أسرع. | J13: Too much gain can cause oscillation. | K13: الكسب الزائد قد يسبب التذبذب. | L13: Beginner | M13: 2 | N13: 2 – Control & Motion | التحكم والحركة | O13: High | P13: S7-INTV-004; S7-TRBL-002 | Q13: Engineers Universe + FutureLearn (Univ. of Reading) | R13: https://engineersuniverse.com/studios/mechatronics/mechatronics-terminology-glossary | https://ugc.futurelearn.com/uploads/files/7a/0f/7a0fcf86-09f0-4ebf-a134-02b1290a950e/Glossary.pdf | S13: Definition paraphrased from the listed source(s); pronunciation, Arabic, examples and level are original additions.
A14: S2-CTRL-018 | B14: 10 | C14: Open-Loop Control | D14: التحكم بالحلقة المفتوحة | E14: OH-pun LOOP kun-TROHL | F14: Control Systems | G14: Control that issues commands without sensor feedback, so missed steps go undetected. | H14: Open-loop control has no sensor feedback. | I14: التحكم بالحلقة المفتوحة لا يحتوي تغذية راجعة من الحساس. | J14: A stepper motor can run with open-loop control. | K14: يستطيع المحرك الخطوي العمل بالتحكم بالحلقة المفتوحة. | L14: Beginner | M14: 2 | N14: 2 – Control & Motion | التحكم والحركة | O14: High | P14: S7-INTV-003; S7-TRBL-004 | Q14: Engineers Universe | R14: https://engineersuniverse.com/studios/mechatronics/mechatronics-terminology-glossary | S14: Definition paraphrased from the listed source(s); pronunciation, Arabic, examples and level are original additions.
A15: S2-MOTN-011 | B15: 11 | C15: Path | D15: المسار | E15: PATH | F15: Motion Control | G15: The continuous set of points traced by the tool center point in a coordinate system. | H15: The robot follows a path from point A to point B. | I15: يتبع الروبوت مساراً من النقطة A إلى النقطة B. | J15: We changed the path to avoid the obstacle. | K15: غيّرنا المسار لتجنب العائق. | L15: Beginner | M15: 2 | N15: 2 – Control & Motion | التحكم والحركة | O15: Normal | Q15: Productivity Inc | R15: https://www.productivity.com/wp-content/uploads/2015/04/PI_RoboticGlossaryTerms.pdf | S15: Definition paraphrased from the listed source(s); pronunciation, Arabic, examples and level are original additions.
A16: S2-CTRL-020 | B16: 12 | C16: PID Controller | D16: متحكم PID | E16: PEE-EYE-DEE kun-TROH-ler | F16: Control Systems | G16: A feedback controller combining proportional, integral, and derivative actions, widely used because it needs no detailed model. | H16: A PID controller uses proportional, integral, and derivative actions. | I16: يستخدم متحكم PID الإجراءات التناسبية والتكاملية والتفاضلية. | J16: We tuned the PID controller to remove the overshoot. | K16: ضبطنا متحكم PID لإزالة التجاوز. | L16: Beginner | M16: 2 | N16: 2 – Control & Motion | التحكم والحركة | O16: High | P16: S7-INTV-004; S7-TRBL-002 | Q16: Engineers Universe + FutureLearn (Univ. of Reading) | R16: https://engineersuniverse.com/studios/mechatronics/mechatronics-terminology-glossary | https://ugc.futurelearn.com/uploads/files/7a/0f/7a0fcf86-09f0-4ebf-a134-02b1290a950e/Glossary.pdf | S16: Definition paraphrased from the listed source(s); pronunciation, Arabic, examples and level are original additions.
A17: S2-QUAL-003 | B17: 13 | C17: Precision | D17: الضبط (الإحكام) | E17: prih-SIZH-un | F17: Quality & Measurement | G17: How close repeated measurements are to each other. | H17: Precision means repeated measurements are close to each other. | I17: الضبط يعني أن القياسات المتكررة متقاربة. | J17: A sensor can be precise but not accurate. | K17: قد يكون الحساس مضبوطاً لكنه غير دقيق. | L17: Beginner | M17: 2 | N17: 2 – Control & Motion | التحكم والحركة | O17: High | P17: S7-INTV-001 | Q17: FutureLearn (Univ. of Reading) | R17: https://ugc.futurelearn.com/uploads/files/7a/0f/7a0fcf86-09f0-4ebf-a134-02b1290a950e/Glossary.pdf | S17: Definition paraphrased from the listed source(s); pronunciation, Arabic, examples and level are original additions.
A18: S2-CTRL-022 | B18: 14 | C18: Proportional Control | D18: التحكم التناسبي | E18: pruh-POR-shuh-nul kun-TROHL | F18: Control Systems | G18: A control strategy where the output equals the error multiplied by a constant. | H18: Proportional control makes the output proportional to the error. | I18: يجعل التحكم التناسبي الخرج متناسباً مع الخطأ. | J18: A higher proportional gain gives a faster response. | K18: كسب تناسبي أعلى يعطي استجابة أسرع. | L18: Beginner | M18: 2 | N18: 2 – Control & Motion | التحكم والحركة | O18: Normal | Q18: FutureLearn (Univ. of Reading) | R18: https://ugc.futurelearn.com/uploads/files/7a/0f/7a0fcf86-09f0-4ebf-a134-02b1290a950e/Glossary.pdf | S18: Definition paraphrased from the listed source(s); pronunciation, Arabic, examples and level are original additions.
A19: S2-MATH-019 | B19: 15 | C19: Scale | D19: التحجيم / المقياس | E19: SKAYL | F19: Math | G19: Changing magnitude by multiplying with a scalar. | H19: We scale the signal to match the controller input range. | I19: نحجّم الإشارة لتطابق مدى دخل المتحكم. | J19: The scale factor is 0.5. | K19: معامل التحجيم 0.5. | L19: Beginner | M19: 2 | N19: 2 – Control & Motion | التحكم والحركة | O19: Normal | Q19: Productivity Inc | R19: https://www.productivity.com/wp-content/uploads/2015/04/PI_RoboticGlossaryTerms.pdf | S19: Definition paraphrased from the listed source(s); pronunciation, Arabic, examples and level are original additions.
A20: S2-KINE-025 | B20: 16 | C20: Swing | D20: التأرجح / الدوران | E20: SWING | F20: Kinematics | G20: Rotational movement of a robot about its centerline. | H20: The robot swings around its base. | I20: يدور الروبوت حول قاعدته. | J20: The swing of the arm is limited by the cable. | K20: يُحدّ الكابل من تأرجح الذراع. | L20: Beginner | M20: 2 | N20: 2 – Control & Motion | التحكم والحركة | O20: Normal | Q20: Productivity Inc | R20: https://www.productivity.com/wp-content/uploads/2015/04/PI_RoboticGlossaryTerms.pdf | S20: Definition paraphrased from the listed source(s); pronunciation, Arabic, examples and level are original additions.
A21: S2-KINE-002 | B21: 17 | C21: Actual Position | D21: الموضع الفعلي | E21: AK-choo-ul puh-ZISH-un | F21: Kinematics | G21: Where the tool control point really is, which can differ from the commanded position because of unsensed errors. | H21: The encoder reports the actual position of the joint. | I21: يُبلغ المُرمِّز عن الموضع الفعلي للمفصل. | J21: The actual position differs slightly from the command position because of load. | K21: يختلف الموضع الفعلي قليلاً عن الموضع المطلوب بسبب الحِمل. | L21: Intermediate | M21: 2 | N21: 2 – Control & Motion | التحكم والحركة | O21: Normal | Q21: Productivity Inc | R21: https://www.productivity.com/wp-content/uploads/2015/04/PI_RoboticGlossaryTerms.pdf | S21: Definition paraphrased from the listed source(s); pronunciation, Arabic, examples and level are original additions.
A22: S2-DYNM-001 | B22: 18 | C22: Centrifugal Force | D22: القوة الطاردة المركزية | E22: sen-TRIF-yuh-gul FORS | F22: Dynamics | G22: The outward radial force from a body rotating about an axis other than its center, which the joint must counter with torque. | H22: Centrifugal force pushes the load outward when the arm spins quickly. | I22: تدفع القوة الطاردة المركزية الحِمل إلى الخارج عندما تدور الذراع بسرعة. | J22: The joint motor must resist centrifugal force at high speed. | K22: يجب أن يقاوم محرك المفصل القوة الطاردة المركزية عند السرعة العالية. | L22: Intermediate | M22: 2 | N22: 2 – Control & Motion | التحكم والحركة | O22: Normal | Q22: Productivity Inc | R22: https://www.productivity.com/wp-content/uploads/2015/04/PI_RoboticGlossaryTerms.pdf | S22: Definition paraphrased from the listed source(s); pronunciation, Arabic, examples and level are original additions.
A23: S2-MOTN-001 | B23: 19 | C23: Circular Motion Type | D23: نوع الحركة الدائرية | E23: SUR-kyuh-ler MOH-shun TYPE | F23: Motion Control | G23: A programmed robot path that is circular in shape. | H23: Circular motion type moves the tool along an arc. | I23: يحرّك نوع الحركة الدائرية الأداة على قوس. | J23: We used circular motion type to weld around a pipe. | K23: استخدمنا نوع الحركة الدائرية للحام حول أنبوب. | L23: Intermediate | M23: 2 | N23: 2 – Control & Motion | التحكم والحركة | O23: Normal | Q23: Productivity Inc | R23: https://www.productivity.com/wp-content/uploads/2015/04/PI_RoboticGlossaryTerms.pdf | S23: Definition paraphrased from the listed source(s); pronunciation, Arabic, examples and level are original additions.
A24: S2-KINE-004 | B24: 20 | C24: Command Position | D24: الموضع المطلوب | E24: kuh-MAND puh-ZISH-un | F24: Kinematics | G24: The endpoint the controller is trying to reach during a motion. | H24: The controller sends the command position to the motors. | I24: يرسل المتحكم الموضع المطلوب إلى المحركات. | J24: The error is the difference between command position and actual position. | K24: الخطأ هو الفرق بين الموضع المطلوب والموضع الفعلي. | L24: Intermediate | M24: 2 | N24: 2 – Control & Motion | التحكم والحركة | O24: Normal | Q24: Productivity Inc | R24: https://www.productivity.com/wp-content/uploads/2015/04/PI_RoboticGlossaryTerms.pdf | S24: Definition paraphrased from the listed source(s); pronunciation, Arabic, examples and level are original additions.
A25: S2-MECH-001 | B25: 21 | C25: Compliance | D25: المطاوعة | E25: kum-PLY-unts | F25: Mechanical | G25: How much a structure deflects under load; the inverse of stiffness and different from backlash. | H25: Compliance measures how much a structure bends under force. | I25: تقيس المطاوعة مقدار انحناء الهيكل تحت القوة. | J25: Too much compliance makes the arm springy and less precise. | K25: المطاوعة الزائدة تجعل الذراع مرنة وأقل دقة. | L25: Intermediate | M25: 2 | N25: 2 – Control & Motion | التحكم والحركة | O25: Normal | Q25: Engineers Universe + Productivity Inc | R25: https://engineersuniverse.com/studios/mechatronics/mechatronics-terminology-glossary | https://www.productivity.com/wp-content/uploads/2015/04/PI_RoboticGlossaryTerms.pdf | S25: Definition paraphrased from the listed source(s); pronunciation, Arabic, examples and level are original additions.
A26: S2-ROBT-002 | B26: 22 | C26: Compliant Robot | D26: روبوت مطاوع | E26: kum-PLY-unt ROH-bot | F26: Robot Types | G26: A robot that adjusts its motions to minimize external forces while performing tasks. | H26: A compliant robot adjusts its motion to reduce contact forces. | I26: يعدّل الروبوت المطاوع حركته لتقليل قوى التلامس. | J26: Compliant robots are safer to work beside people. | K26: الروبوتات المطاوعة أكثر أماناً للعمل بجانب الناس. | L26: Intermediate | M26: 2 | N26: 2 – Control & Motion | التحكم والحركة | O26: Normal | Q26: Productivity Inc | R26: https://www.productivity.com/wp-content/uploads/2015/04/PI_RoboticGlossaryTerms.pdf | S26: Definition paraphrased from the listed source(s); pronunciation, Arabic, examples and level are original additions.
A27: S2-KINE-005 | B27: 23 | C27: Configuration | D27: التهيئة / الوضعية | E27: kun-fig-yuh-RAY-shun | F27: Kinematics | G27: The arrangement of links produced by a particular set of joint positions; several configurations can reach the same endpoint. | H27: The same endpoint can be reached with more than one arm configuration. | I27: يمكن الوصول إلى نقطة النهاية نفسها بأكثر من وضعية للذراع. | J27: Choose the configuration that avoids the obstacle. | K27: اختر الوضعية التي تتجنب العائق. | L27: Intermediate | M27: 2 | N27: 2 – Control & Motion | التحكم والحركة | O27: High | P27: S7-INTV-009; S7-TRBL-012 | Q27: Productivity Inc | R27: https://www.productivity.com/wp-content/uploads/2015/04/PI_RoboticGlossaryTerms.pdf | S27: Definition paraphrased from the listed source(s); pronunciation, Arabic, examples and level are original additions.
A28: S2-MOTN-003 | B28: 24 | C28: Continuous Path | D28: المسار المستمر | E28: kun-TIN-yoo-us PATH | F28: Motion Control | G28: Control over the entire traversed path for smooth motion, as in spray painting. | H28: Spray painting needs continuous path control for smooth coverage. | I28: يحتاج الطلاء بالرش إلى تحكم بالمسار المستمر لتغطية سلسة. | J28: The robot follows a continuous path along the car door. | K28: يتبع الروبوت مساراً مستمراً على طول باب السيارة. | L28: Intermediate | M28: 2 | N28: 2 – Control & Motion | التحكم والحركة | O28: Normal | Q28: Productivity Inc | R28: https://www.productivity.com/wp-content/uploads/2015/04/PI_RoboticGlossaryTerms.pdf | S28: Definition paraphrased from the listed source(s); pronunciation, Arabic, examples and level are original additions.
A29: S2-CTRL-004 | B29: 25 | C29: Control Algorithm | D29: خوارزمية التحكم | E29: kun-TROHL AL-guh-rith-um | F29: Control Systems | G29: A method that detects trajectory deviations and computes actuator torques to correct them. | H29: The control algorithm corrects the error between target and actual motion. | I29: تصحح خوارزمية التحكم الخطأ بين الحركة المطلوبة والفعلية. | J29: We tuned the control algorithm to reduce vibration. | K29: ضبطنا خوارزمية التحكم لتقليل الاهتزاز. | L29: Intermediate | M29: 2 | N29: 2 – Control & Motion | التحكم والحركة | O29: Normal | Q29: Productivity Inc | R29: https://www.productivity.com/wp-content/uploads/2015/04/PI_RoboticGlossaryTerms.pdf | S29: Definition paraphrased from the listed source(s); pronunciation, Arabic, examples and level are original additions.
A30: S2-KINE-007 | B30: 26 | C30: Dexterity | D30: البراعة / المهارة الحركية | E30: dek-STAIR-ih-tee | F30: Kinematics | G30: A measure of a robot's skill at completing difficult paths. | H30: Dexterity shows how well a robot can follow a difficult path. | I30: تُظهر البراعة مدى قدرة الروبوت على اتباع مسار صعب. | J30: Surgical robots need high dexterity. | K30: تحتاج الروبوتات الجراحية إلى براعة عالية. | L30: Intermediate | M30: 2 | N30: 2 – Control & Motion | التحكم والحركة | O30: Normal | Q30: Productivity Inc | R30: https://www.productivity.com/wp-content/uploads/2015/04/PI_RoboticGlossaryTerms.pdf | S30: Definition paraphrased from the listed source(s); pronunciation, Arabic, examples and level are original additions.
A31: S2-MATH-003 | B31: 27 | C31: Differentiation | D31: التفاضل | E31: dif-uh-ren-shee-AY-shun | F31: Math | G31: A calculus operation that finds the rate of change of a function; the reverse of integration. | H31: Differentiation gives the rate of change of a function. | I31: يعطي التفاضل معدل تغير الدالة. | J31: Velocity is found by differentiation of position. | K31: تُوجد السرعة بتفاضل الموضع. | L31: Intermediate | M31: 2 | N31: 2 – Control & Motion | التحكم والحركة | O31: Normal | Q31: FutureLearn (Univ. of Reading) | R31: https://ugc.futurelearn.com/uploads/files/7a/0f/7a0fcf86-09f0-4ebf-a134-02b1290a950e/Glossary.pdf | S31: Definition paraphrased from the listed source(s); pronunciation, Arabic, examples and level are original additions.
A32: S2-DYNM-002 | B32: 28 | C32: Dynamics | D32: الديناميكا | E32: dy-NAM-iks | F32: Dynamics | G32: The study of motion, the forces causing it, and forces arising from it, which are complex in robot arms. | H32: Robot dynamics studies motion and the forces that cause it. | I32: تدرس ديناميكا الروبوت الحركة والقوى المسببة لها. | J32: The dynamics of a long arm are complex. | K32: ديناميكا الذراع الطويلة معقدة. | L32: Intermediate | M32: 2 | N32: 2 – Control & Motion | التحكم والحركة | O32: Normal | Q32: Productivity Inc | R32: https://www.productivity.com/wp-content/uploads/2015/04/PI_RoboticGlossaryTerms.pdf | S32: Definition paraphrased from the listed source(s); pronunciation, Arabic, examples and level are original additions.
A33: S2-KINE-009 | B33: 29 | C33: Endpoint | D33: نقطة النهاية | E33: END-point | F33: Kinematics | G33: The nominal commanded position a manipulator aims for at the end of a motion path, located at the distal link. | H33: The endpoint of the motion is the target position. | I33: نقطة نهاية الحركة هي الموضع المستهدف. | J33: The robot stops at the endpoint and waits for the next command. | K33: يتوقف الروبوت عند نقطة النهاية وينتظر الأمر التالي. | L33: Intermediate | M33: 2 | N33: 2 – Control & Motion | التحكم والحركة | O33: Normal | Q33: Productivity Inc | R33: https://www.productivity.com/wp-content/uploads/2015/04/PI_RoboticGlossaryTerms.pdf | S33: Definition paraphrased from the listed source(s); pronunciation, Arabic, examples and level are original additions.
A34: S2-KINE-011 | B34: 30 | C34: Frame | D34: إطار مرجعي | E34: FRAYM | F34: Kinematics | G34: A coordinate system that defines an object's or the robot's position and orientation in space. | H34: Each tool has its own coordinate frame. | I34: لكل أداة إطار إحداثيات خاص بها. | J34: Define the base frame before teaching the points. | K34: عرِّف إطار القاعدة قبل تعليم النقاط. | L34: Intermediate | M34: 2 | N34: 2 – Control & Motion | التحكم والحركة | O34: Normal | Q34: Productivity Inc | R34: https://www.productivity.com/wp-content/uploads/2015/04/PI_RoboticGlossaryTerms.pdf | S34: Definition paraphrased from the listed source(s); pronunciation, Arabic, examples and level are original additions.
A35: S2-CTRL-017 | B35: 31 | C35: Integral control | D35: التحكم التكاملي | E35: IN-tuh-grul kun-TROHL | F35: Control Systems | G35: A feedback control method where the output depends on the error and its past values. | H35: Integral control removes the steady-state error. | I35: يزيل التحكم التكاملي الخطأ المستقر. | J35: Integral control adds up the error over time. | K35: يجمع التحكم التكاملي الخطأ عبر الزمن. | L35: Intermediate | M35: 2 | N35: 2 – Control & Motion | التحكم والحركة | O35: High | P35: S7-INTV-004 | Q35: FutureLearn (Univ. of Reading) | R35: https://ugc.futurelearn.com/uploads/files/7a/0f/7a0fcf86-09f0-4ebf-a134-02b1290a950e/Glossary.pdf | S35: Definition paraphrased from the listed source(s); pronunciation, Arabic, examples and level are original additions.
A36: S2-MATH-008 | B36: 32 | C36: Integration | D36: التكامل | E36: in-tuh-GRAY-shun | F36: Math | G36: A calculus operation that finds the area under a function; the reverse of differentiation. | H36: Integration finds the area under a curve. | I36: يجد التكامل المساحة تحت المنحنى. | J36: Position is found by integration of velocity. | K36: يُوجد الموضع بتكامل السرعة. | L36: Intermediate | M36: 2 | N36: 2 – Control & Motion | التحكم والحركة | O36: Normal | Q36: FutureLearn (Univ. of Reading) | R36: https://ugc.futurelearn.com/uploads/files/7a/0f/7a0fcf86-09f0-4ebf-a134-02b1290a950e/Glossary.pdf | S36: Definition paraphrased from the listed source(s); pronunciation, Arabic, examples and level are original additions.
A37: S2-MATH-009 | B37: 33 | C37: Iteration | D37: التكرار | E37: it-uh-RAY-shun | F37: Math | G37: Repeating a procedure to refine a solution. | H37: Each iteration brings the answer closer to the target. | I37: كل تكرار يقرّب الإجابة من الهدف. | J37: The solver stopped after ten iterations. | K37: توقف الحلّال بعد عشرة تكرارات. | L37: Intermediate | M37: 2 | N37: 2 – Control & Motion | التحكم والحركة | O37: Normal | Q37: Productivity Inc | R37: https://www.productivity.com/wp-content/uploads/2015/04/PI_RoboticGlossaryTerms.pdf | S37: Definition paraphrased from the listed source(s); pronunciation, Arabic, examples and level are original additions.
A38: S2-MOTN-007 | B38: 34 | C38: Joint Motion Type | D38: نوع الحركة المفصلية | E38: JOYNT MOH-shun TYPE | F38: Motion Control | G38: Point-to-point motion in which each joint moves directly to its target, so all axes arrive together along a non-linear path. | H38: Joint motion type moves each joint directly to its target. | I38: يحرّك نوع الحركة المفصلية كل مفصل مباشرة إلى هدفه. | J38: The path in joint motion type is not a straight line. | K38: المسار في نوع الحركة المفصلية ليس خطاً مستقيماً. | L38: Intermediate | M38: 2 | N38: 2 – Control & Motion | التحكم والحركة | O38: Normal | Q38: Productivity Inc | R38: https://www.productivity.com/wp-content/uploads/2015/04/PI_RoboticGlossaryTerms.pdf | S38: Definition paraphrased from the listed source(s); pronunciation, Arabic, examples and level are original additions.
A39: S2-KINE-015 | B39: 35 | C39: Kinematics | D39: الكينماتيكا (علم الحركة) | E39: kin-uh-MAT-iks | F39: Kinematics | G39: The study of motion geometry (position, velocity, acceleration) without considering the forces causing it. | H39: Kinematics studies motion without considering forces. | I39: تدرس الكينماتيكا الحركة دون النظر إلى القوى. | J39: Forward and inverse kinematics are basic robotics topics. | K39: الكينماتيكا الأمامية والعكسية موضوعان أساسيان في الروبوتات. | L39: Intermediate | M39: 2 | N39: 2 – Control & Motion | التحكم والحركة | O39: Normal | Q39: Engineers Universe + Productivity Inc | R39: https://engineersuniverse.com/studios/mechatronics/mechatronics-terminology-glossary | https://www.productivity.com/wp-content/uploads/2015/04/PI_RoboticGlossaryTerms.pdf | S39: Definition paraphrased from the listed source(s); pronunciation, Arabic, examples and level are original additions.
A40: S2-MOTN-009 | B40: 36 | C40: Linear Motion Type | D40: نوع الحركة الخطية | E40: LIN-ee-er MOH-shun TYPE | F40: Motion Control | G40: Coordinated joint motion that keeps the tool center point on a predictable straight path. | H40: Linear motion type keeps the tool on a straight path. | I40: يُبقي نوع الحركة الخطية الأداة على مسار مستقيم. | J40: Use linear motion type for gluing along an edge. | K40: استخدم نوع الحركة الخطية للصق على طول حافة. | L40: Intermediate | M40: 2 | N40: 2 – Control & Motion | التحكم والحركة | O40: Normal | Q40: Productivity Inc | R40: https://www.productivity.com/wp-content/uploads/2015/04/PI_RoboticGlossaryTerms.pdf | S40: Definition paraphrased from the listed source(s); pronunciation, Arabic, examples and level are original additions.
A41: S2-KINE-016 | B41: 37 | C41: Motion Axis | D41: محور الحركة | E41: MOH-shun AK-sis | F41: Kinematics | G41: The line defining the linear or rotary motion of a manipulator segment. | H41: Each motion axis can move independently. | I41: يستطيع كل محور حركة التحرك باستقلال. | J41: The robot has one rotary and two linear motion axes. | K41: للروبوت محور حركة دوراني واحد ومحورا حركة خطيان. | L41: Intermediate | M41: 2 | N41: 2 – Control & Motion | التحكم والحركة | O41: Normal | Q41: Productivity Inc | R41: https://www.productivity.com/wp-content/uploads/2015/04/PI_RoboticGlossaryTerms.pdf | S41: Definition paraphrased from the listed source(s); pronunciation, Arabic, examples and level are original additions.
A42: S2-MOTN-010 | B42: 38 | C42: Motion Profile | D42: ملف الحركة | E42: MOH-shun PROH-fyle | F42: Motion Control | G42: The planned position, velocity, and acceleration over time for a move, such as trapezoidal or S-curve. | H42: A trapezoidal motion profile has smooth acceleration and deceleration. | I42: لملف الحركة شبه المنحرف تسارع وتباطؤ سلسان. | J42: We changed the motion profile to reduce vibration. | K42: غيّرنا ملف الحركة لتقليل الاهتزاز. | L42: Intermediate | M42: 2 | N42: 2 – Control & Motion | التحكم والحركة | O42: High | P42: S7-TRBL-011 | Q42: Engineers Universe | R42: https://engineersuniverse.com/studios/mechatronics/mechatronics-terminology-glossary | S42: Definition paraphrased from the listed source(s); pronunciation, Arabic, examples and level are original additions.
A43: S2-KINE-017 | B43: 39 | C43: Orientation | D43: الاتجاه / التوجيه | E43: or-ee-en-TAY-shun | F43: Kinematics | G43: The angle of an object's major axis relative to a reference axis in three dimensions. | H43: The orientation of the tool must match the part. | I43: يجب أن يطابق اتجاه الأداة القطعة. | J43: Position and orientation together define the pose. | K43: يحدد الموضع والاتجاه معاً الوضعية. | L43: Intermediate | M43: 2 | N43: 2 – Control & Motion | التحكم والحركة | O43: Normal | Q43: Productivity Inc | R43: https://www.productivity.com/wp-content/uploads/2015/04/PI_RoboticGlossaryTerms.pdf | S43: Definition paraphrased from the listed source(s); pronunciation, Arabic, examples and level are original additions.
A44: S2-CTRL-019 | B44: 40 | C44: Overshoot | D44: التجاوز | E44: OH-ver-shoot | F44: Control Systems | G44: The amount a response exceeds its final target before settling, often caused by excessive gain. | H44: Overshoot means the response goes past the target. | I44: يعني التجاوز أن الاستجابة تتخطى الهدف. | J44: High gain often causes overshoot. | K44: الكسب العالي غالباً ما يسبب التجاوز. | L44: Intermediate | M44: 2 | N44: 2 – Control & Motion | التحكم والحركة | O44: High | P44: S7-INTV-004 | Q44: Engineers Universe | R44: https://engineersuniverse.com/studios/mechatronics/mechatronics-terminology-glossary | S44: Definition paraphrased from the listed source(s); pronunciation, Arabic, examples and level are original additions.
A45: S2-KINE-018 | B45: 41 | C45: Pitch | D45: الميل (الخطوة) | E45: PICH | F45: Kinematics | G45: Rotation of the end-effector in a vertical plane around the arm's end. | H45: Pitch rotates the end-effector up and down. | I45: يدوّر الميل المؤثر النهائي للأعلى والأسفل. | J45: The drone's pitch controls its forward motion. | K45: يتحكم ميل الطائرة المسيّرة في حركتها الأمامية. | L45: Intermediate | M45: 2 | N45: 2 – Control & Motion | التحكم والحركة | O45: Normal | Q45: FutureLearn (Univ. of Reading) + Productivity Inc | R45: https://ugc.futurelearn.com/uploads/files/7a/0f/7a0fcf86-09f0-4ebf-a134-02b1290a950e/Glossary.pdf | https://www.productivity.com/wp-content/uploads/2015/04/PI_RoboticGlossaryTerms.pdf | S45: Definition paraphrased from the listed source(s); pronunciation, Arabic, examples and level are original additions.
A46: S2-MOTN-012 | B46: 42 | C46: Point-To-Point (PTP) | D46: من نقطة إلى نقطة | E46: POYNT too POYNT | F46: Motion Control | G46: Manipulator motion through a limited set of specified points rather than a smooth continuous path. | H46: In point-to-point motion the robot goes directly from one point to the next. | I46: في حركة نقطة إلى نقطة يذهب الروبوت مباشرة من نقطة إلى التالية. | J46: PTP motion is fine for pick and place. | K46: حركة PTP مناسبة للالتقاط والوضع. | L46: Intermediate | M46: 2 | N46: 2 – Control & Motion | التحكم والحركة | O46: Normal | Q46: Productivity Inc | R46: https://www.productivity.com/wp-content/uploads/2015/04/PI_RoboticGlossaryTerms.pdf | S46: Definition paraphrased from the listed source(s); pronunciation, Arabic, examples and level are original additions.
A47: S2-KINE-019 | B47: 43 | C47: Pose | D47: الوضعية | E47: POHZ | F47: Kinematics | G47: A term for robot configuration that describes linear and angular position. | H47: The pose includes the position and orientation of the tool. | I47: تشمل الوضعية موضع الأداة واتجاهها. | J47: The camera estimates the pose of the object. | K47: تقدّر الكاميرا وضعية الجسم. | L47: Intermediate | M47: 2 | N47: 2 – Control & Motion | التحكم والحركة | O47: High | P47: S7-INTV-008 | Q47: Productivity Inc | R47: https://www.productivity.com/wp-content/uploads/2015/04/PI_RoboticGlossaryTerms.pdf | S47: Definition paraphrased from the listed source(s); pronunciation, Arabic, examples and level are original additions.
A48: S2-MATH-018 | B48: 44 | C48: Radians | D48: الراديان | E48: RAY-dee-unz | F48: Math | G48: A unit for measuring angles, where a full turn is 2π radians. | H48: Robot software often uses radians instead of degrees. | I48: غالباً ما تستخدم برمجيات الروبوت الراديان بدلاً من الدرجات. | J48: One full turn is 2π radians. | K48: الدورة الكاملة تساوي 2π راديان. | L48: Intermediate | M48: 2 | N48: 2 – Control & Motion | التحكم والحركة | O48: Normal | Q48: FutureLearn (Univ. of Reading) | R48: https://ugc.futurelearn.com/uploads/files/7a/0f/7a0fcf86-09f0-4ebf-a134-02b1290a950e/Glossary.pdf | S48: Definition paraphrased from the listed source(s); pronunciation, Arabic, examples and level are original additions.
A49: S2-QUAL-004 | B49: 45 | C49: Repeatability | D49: قابلية التكرار | E49: rih-peet-uh-BIL-ih-tee | F49: Quality & Measurement | G49: How consistently a system returns to the same commanded position; distinct from accuracy. | H49: The repeatability of the robot is plus or minus 0.02 mm. | I49: قابلية التكرار للروبوت زائد أو ناقص 0.02 ملم. | J49: Good repeatability matters more than accuracy in many tasks. | K49: قابلية التكرار الجيدة أهم من الدقة في مهام كثيرة. | L49: Intermediate | M49: 2 | N49: 2 – Control & Motion | التحكم والحركة | O49: High | P49: S7-INTV-001 | Q49: Engineers Universe + Productivity Inc | R49: https://engineersuniverse.com/studios/mechatronics/mechatronics-terminology-glossary | https://www.productivity.com/wp-content/uploads/2015/04/PI_RoboticGlossaryTerms.pdf | S49: Definition paraphrased from the listed source(s); pronunciation, Arabic, examples and level are original additions.
A50: S2-KINE-024 | B50: 46 | C50: Roll | D50: الدوران حول المحور الطولي (Roll) | E50: ROHL | F50: Kinematics | G50: Rotation of the end-effector in a plane perpendicular to the arm's end. | H50: Roll rotates the end-effector around the arm axis. | I50: يدوّر الدوران الطولي المؤثر النهائي حول محور الذراع. | J50: The pilot adjusted the aircraft's roll. | K50: عدّل الطيار دوران الطائرة الطولي. | L50: Intermediate | M50: 2 | N50: 2 – Control & Motion | التحكم والحركة | O50: Normal | Q50: FutureLearn (Univ. of Reading) + Productivity Inc | R50: https://ugc.futurelearn.com/uploads/files/7a/0f/7a0fcf86-09f0-4ebf-a134-02b1290a950e/Glossary.pdf | https://www.productivity.com/wp-content/uploads/2015/04/PI_RoboticGlossaryTerms.pdf | S50: Definition paraphrased from the listed source(s); pronunciation, Arabic, examples and level are original additions.
A51: S2-CTRL-025 | B51: 47 | C51: Servo / Servomechanism | D51: آلية مؤازرة (سيرفو) | E51: SUR-voh / sur-voh-MEK-uh-niz-um | F51: Control Systems | G51: An automatic device that uses feedback control to set its output, made up of the controlled device, sensors, and a control mechanism. | H51: A servomechanism uses feedback to control its output. | I51: تستخدم الآلية المؤازرة التغذية الراجعة للتحكم في خرجها. | J51: A hobby servo is a small servomechanism. | K51: السيرفو الهواة آلية مؤازرة صغيرة. | L51: Intermediate | M51: 2 | N51: 2 – Control & Motion | التحكم والحركة | O51: Normal | Q51: FutureLearn (Univ. of Reading) | R51: https://ugc.futurelearn.com/uploads/files/7a/0f/7a0fcf86-09f0-4ebf-a134-02b1290a950e/Glossary.pdf | S51: Definition paraphrased from the listed source(s); pronunciation, Arabic, examples and level are original additions.
A52: S2-CTRL-026 | B52: 48 | C52: Servo Control | D52: التحكم المؤازر | E52: SUR-voh kun-TROHL | F52: Control Systems | G52: Checking whether the robot's actual pose matches the pose specified by the motion plan. | H52: Servo control checks that the actual pose matches the plan. | I52: يتحقق التحكم المؤازر من أن الوضعية الفعلية تطابق الخطة. | J52: Servo control keeps the arm stable under load. | K52: يُبقي التحكم المؤازر الذراع مستقرة تحت الحِمل. | L52: Intermediate | M52: 2 | N52: 2 – Control & Motion | التحكم والحركة | O52: Normal | Q52: Productivity Inc | R52: https://www.productivity.com/wp-content/uploads/2015/04/PI_RoboticGlossaryTerms.pdf | S52: Definition paraphrased from the listed source(s); pronunciation, Arabic, examples and level are original additions.
A53: S2-ROBT-004 | B53: 49 | C53: Servo-Controlled Robot | D53: روبوت بتحكم مؤازر | E53: SUR-voh kun-TROHLD ROH-bot | F53: Robot Types | G53: A robot controlled by a closed-loop servo system that measures axis position through feedback devices. | H53: A servo-controlled robot uses feedback to reach positions accurately. | I53: يستخدم الروبوت ذو التحكم المؤازر التغذية الراجعة للوصول إلى المواضع بدقة. | J53: Most modern robots are servo-controlled robots. | K53: معظم الروبوتات الحديثة روبوتات ذات تحكم مؤازر. | L53: Intermediate | M53: 2 | N53: 2 – Control & Motion | التحكم والحركة | O53: Normal | Q53: Productivity Inc | R53: https://www.productivity.com/wp-content/uploads/2015/04/PI_RoboticGlossaryTerms.pdf | S53: Definition paraphrased from the listed source(s); pronunciation, Arabic, examples and level are original additions.
A54: S2-CTRL-027 | B54: 50 | C54: Servo-System | D54: نظام مؤازر | E54: SUR-voh SIS-tum | F54: Control Systems | G54: A loop in which the controller commands motors, and an encoder reports motion back until the arm reaches its target. | H54: A servo-system uses an encoder to report the motion back. | I54: يستخدم النظام المؤازر مُرمِّزاً لإرجاع الحركة. | J54: The servo-system corrects the position until the target is reached. | K54: يصحح النظام المؤازر الموضع حتى الوصول إلى الهدف. | L54: Intermediate | M54: 2 | N54: 2 – Control & Motion | التحكم والحركة | O54: Normal | Q54: Productivity Inc | R54: https://www.productivity.com/wp-content/uploads/2015/04/PI_RoboticGlossaryTerms.pdf | S54: Definition paraphrased from the listed source(s); pronunciation, Arabic, examples and level are original additions.
A55: S2-DYNM-006 | B55: 51 | C55: Statics | D55: الإستاتيكا (علم السكون) | E55: STAT-iks | F55: Dynamics | G55: Analysis of forces in the absence of motion. | H55: Statics studies forces when nothing is moving. | I55: تدرس الإستاتيكا القوى عندما لا يتحرك شيء. | J55: Statics is used to size the joint motors. | K55: تُستخدم الإستاتيكا لتحديد حجم محركات المفاصل. | L55: Intermediate | M55: 2 | N55: 2 – Control & Motion | التحكم والحركة | O55: Normal | Q55: Productivity Inc | R55: https://www.productivity.com/wp-content/uploads/2015/04/PI_RoboticGlossaryTerms.pdf | S55: Definition paraphrased from the listed source(s); pronunciation, Arabic, examples and level are original additions.
A56: S2-MECH-002 | B56: 52 | C56: Stiffness | D56: الجساءة (الصلابة) | E56: STIF-nis | F56: Mechanical | G56: A structure's resistance to deflection under load, which raises natural frequency and reduces positioning error. | H56: A stiff arm gives better positioning accuracy. | I56: الذراع الجاسئة تعطي دقة تموضع أفضل. | J56: Increase the stiffness to raise the natural frequency. | K56: زد الجساءة لرفع التردد الطبيعي. | L56: Intermediate | M56: 2 | N56: 2 – Control & Motion | التحكم والحركة | O56: Normal | Q56: Engineers Universe | R56: https://engineersuniverse.com/studios/mechatronics/mechatronics-terminology-glossary | S56: Definition paraphrased from the listed source(s); pronunciation, Arabic, examples and level are original additions.
A57: S2-KINE-026 | B57: 53 | C57: Tool Center Point (TCP) | D57: نقطة مركز الأداة | E57: TOOL SEN-ter POYNT | F57: Kinematics | G57: The central axis of the tool's movement. | H57: The TCP is the point on the tool that touches the work. | I57: نقطة مركز الأداة هي النقطة التي تلمس العمل. | J57: Set the TCP correctly or the robot will miss the target. | K57: اضبط نقطة مركز الأداة بشكل صحيح وإلا أخطأ الروبوت الهدف. | L57: Intermediate | M57: 2 | N57: 2 – Control & Motion | التحكم والحركة | O57: High | P57: S7-INTV-013; S7-TRBL-013 | Q57: Productivity Inc | R57: https://www.productivity.com/wp-content/uploads/2015/04/PI_RoboticGlossaryTerms.pdf | S57: Definition paraphrased from the listed source(s); pronunciation, Arabic, examples and level are original additions.
A58: S2-MOTN-016 | B58: 54 | C58: Trajectory Planning | D58: تخطيط المسار | E58: truh-JEK-tuh-ree PLAN-ing | F58: Motion Control | G58: Generating a time-based path for axes under limits on velocity, acceleration, jerk, and obstacles. | H58: Trajectory planning creates a smooth path over time. | I58: ينشئ تخطيط المسار مساراً سلساً عبر الزمن. | J58: Trajectory planning must respect the speed limits. | K58: يجب أن يحترم تخطيط المسار حدود السرعة. | L58: Intermediate | M58: 2 | N58: 2 – Control & Motion | التحكم والحركة | O58: Normal | Q58: Engineers Universe | R58: https://engineersuniverse.com/studios/mechatronics/mechatronics-terminology-glossary | S58: Definition paraphrased from the listed source(s); pronunciation, Arabic, examples and level are original additions.
A59: S2-KINE-029 | B59: 55 | C59: Yaw | D59: الانعراج (Yaw) | E59: YAW | F59: Kinematics | G59: Rotation of the end-effector in a horizontal plane around the arm's end. | H59: Yaw rotates the end-effector left and right. | I59: يدوّر الانعراج المؤثر النهائي لليسار واليمين. | J59: A drone uses yaw to change its heading. | K59: تستخدم الطائرة المسيّرة الانعراج لتغيير اتجاهها. | L59: Intermediate | M59: 2 | N59: 2 – Control & Motion | التحكم والحركة | O59: Normal | Q59: FutureLearn (Univ. of Reading) + Productivity Inc | R59: https://ugc.futurelearn.com/uploads/files/7a/0f/7a0fcf86-09f0-4ebf-a134-02b1290a950e/Glossary.pdf | https://www.productivity.com/wp-content/uploads/2015/04/PI_RoboticGlossaryTerms.pdf | S59: Definition paraphrased from the listed source(s); pronunciation, Arabic, examples and level are original additions.
A60: S2-KINE-001 | B60: 56 | C60: Acceleration Level | D60: مستوى التسارع | E60: ak-sel-er-AY-shun LEV-el | F60: Kinematics | G60: Rate at which joint speeds change over time. | H60: The acceleration level of each joint must stay within the limits of the motors. | I60: يجب أن يبقى مستوى تسارع كل مفصل ضمن حدود المحركات. | J60: A high acceleration level shortens the cycle time but increases vibration. | K60: مستوى التسارع المرتفع يقصّر زمن الدورة لكنه يزيد الاهتزاز. | L60: Advanced | M60: 2 | N60: 2 – Control & Motion | التحكم والحركة | O60: Normal | Q60: Productivity Inc | R60: https://www.productivity.com/wp-content/uploads/2015/04/PI_RoboticGlossaryTerms.pdf | S60: Definition paraphrased from the listed source(s); pronunciation, Arabic, examples and level are original additions.
A61: S2-ROBT-001 | B61: 57 | C61: Active Compliant Robot | D61: روبوت ذو مطاوعة نشطة | E61: AK-tiv kum-PLY-unt ROH-bot | F61: Robot Types | G61: A robot whose control system makes slight motion adjustments during a task to help complete it. | H61: An active compliant robot adjusts its motion when the part is slightly misaligned. | I61: يعدّل الروبوت المطاوع النشط حركته عندما تكون القطعة غير محاذاة قليلاً. | J61: We used an active compliant robot for the peg-in-hole insertion task. | K61: استخدمنا روبوتاً مطاوعاً نشطاً لمهمة إدخال الوتد في الثقب. | L61: Advanced | M61: 2 | N61: 2 – Control & Motion | التحكم والحركة | O61: Normal | Q61: Productivity Inc | R61: https://www.productivity.com/wp-content/uploads/2015/04/PI_RoboticGlossaryTerms.pdf | S61: Definition paraphrased from the listed source(s); pronunciation, Arabic, examples and level are original additions.
A62: S2-CTRL-001 | B62: 58 | C62: Actuator Saturation | D62: تشبّع المشغّل | E62: AK-choo-ay-ter sach-uh-RAY-shun | F62: Control Systems | G62: A condition where a controller asks for more output than the actuator can deliver, which can cause windup and instability. | H62: Actuator saturation happens when the controller asks for too much output. | I62: يحدث تشبّع المشغّل عندما يطلب المتحكم مخرجات زائدة. | J62: Saturation can cause the integral term to wind up. | K62: قد يتسبب التشبّع في تراكم الحد التكاملي. | L62: Advanced | M62: 2 | N62: 2 – Control & Motion | التحكم والحركة | O62: Normal | Q62: Engineers Universe | R62: https://engineersuniverse.com/studios/mechatronics/mechatronics-terminology-glossary | S62: Definition paraphrased from the listed source(s); pronunciation, Arabic, examples and level are original additions.
A63: S2-MATH-001 | B63: 59 | C63: Analytical Methods | D63: الطرق التحليلية | E63: an-uh-LIT-ik-ul METH-udz | F63: Math | G63: Solving problems mathematically without repeated approximation attempts. | H63: Analytical methods give an exact answer without repeated guessing. | I63: تعطي الطرق التحليلية إجابة دقيقة دون تخمين متكرر. | J63: Inverse kinematics can be solved with analytical methods for simple arms. | K63: يمكن حل الكينماتيكا العكسية بالطرق التحليلية للأذرع البسيطة. | L63: Advanced | M63: 2 | N63: 2 – Control & Motion | التحكم والحركة | O63: Normal | Q63: Productivity Inc | R63: https://www.productivity.com/wp-content/uploads/2015/04/PI_RoboticGlossaryTerms.pdf | S63: Definition paraphrased from the listed source(s); pronunciation, Arabic, examples and level are original additions.
A64: S2-KINE-003 | B64: 60 | C64: Axis Acceleration | D64: تسارع المحور | E64: AK-sis ak-sel-er-AY-shun | F64: Kinematics | G64: The maximum acceleration an axis can reach while carrying the suggested payload. | H64: The axis acceleration is limited when the robot carries a heavy payload. | I64: يُحدَّد تسارع المحور عندما يحمل الروبوت حمولة ثقيلة. | J64: Check the axis acceleration in the manufacturer's data sheet. | K64: تحقق من تسارع المحور في ورقة بيانات الشركة المصنعة. | L64: Advanced | M64: 2 | N64: 2 – Control & Motion | التحكم والحركة | O64: Normal | Q64: Productivity Inc | R64: https://www.productivity.com/wp-content/uploads/2015/04/PI_RoboticGlossaryTerms.pdf | S64: Definition paraphrased from the listed source(s); pronunciation, Arabic, examples and level are original additions.
A65: S2-CTRL-002 | B65: 61 | C65: Bandwidth (control loop) | D65: عرض النطاق (لحلقة التحكم) | E65: BAND-width | F65: Control Systems | G65: The frequency range over which a control loop tracks its reference, usually measured where gain falls 3 dB. | H65: A higher bandwidth means the loop reacts faster. | I65: عرض النطاق الأعلى يعني أن الحلقة تستجيب أسرع. | J65: The velocity loop has a bandwidth of 200 Hz. | K65: لحلقة السرعة عرض نطاق 200 هرتز. | L65: Advanced | M65: 2 | N65: 2 – Control & Motion | التحكم والحركة | O65: Normal | Q65: Engineers Universe | R65: https://engineersuniverse.com/studios/mechatronics/mechatronics-terminology-glossary | S65: Definition paraphrased from the listed source(s); pronunciation, Arabic, examples and level are original additions.
A66: S2-MATH-002 | B66: 62 | C66: Closed-Form | D66: الصيغة المغلقة | E66: KLOHZD-form | F66: Math | G66: A way of solving a problem with a direct formula (an exact analytical answer) instead of repeated trial-and-error steps. | H66: A closed-form solution is a direct formula with no repeated steps. | I66: الحل بالصيغة المغلقة معادلة مباشرة دون خطوات متكررة. | J66: The inverse kinematics of this arm has a closed-form solution. | K66: للكينماتيكا العكسية لهذه الذراع حل بصيغة مغلقة. | L66: Advanced | M66: 2 | N66: 2 – Control & Motion | التحكم والحركة | O66: Normal | Q66: Productivity Inc | R66: https://www.productivity.com/wp-content/uploads/2015/04/PI_RoboticGlossaryTerms.pdf | S66: Definition paraphrased from the listed source(s); pronunciation, Arabic, examples and level are original additions. The source text describes it differently; the definition here is corrected to the standard meaning.
A67: S2-MOTN-002 | B67: 63 | C67: Conservative Motion | D67: الحركة المحافظة | E67: kun-SUR-vuh-tiv MOH-shun | F67: Motion Control | G67: Motion in which the end-effector and joints always follow their specific route. | H67: Conservative motion makes the arm follow the same route every time. | I67: تجعل الحركة المحافظة الذراع تتبع المسار نفسه في كل مرة. | J67: The program uses conservative motion near the fixture. | K67: يستخدم البرنامج الحركة المحافظة بالقرب من أداة التثبيت. | L67: Advanced | M67: 2 | N67: 2 – Control & Motion | التحكم والحركة | O67: Normal | Q67: Productivity Inc | R67: https://www.productivity.com/wp-content/uploads/2015/04/PI_RoboticGlossaryTerms.pdf | S67: Definition paraphrased from the listed source(s); pronunciation, Arabic, examples and level are original additions.
A68: S2-CTRL-006 | B68: 64 | C68: Controllability | D68: قابلية التحكم | E68: kun-troh-luh-BIL-ih-tee | F68: Control Systems | G68: A system's ability to move from an initial state to a desired state along a predictable path within a set time. | H68: Controllability tells us if the system can be driven to a desired state. | I68: تخبرنا قابلية التحكم إن كان يمكن توجيه النظام إلى الحالة المطلوبة. | J68: Poor controllability makes the robot hard to tune. | K68: ضعف قابلية التحكم يجعل ضبط الروبوت صعباً. | L68: Advanced | M68: 2 | N68: 2 – Control & Motion | التحكم والحركة | O68: Normal | Q68: Productivity Inc | R68: https://www.productivity.com/wp-content/uploads/2015/04/PI_RoboticGlossaryTerms.pdf | S68: Definition paraphrased from the listed source(s); pronunciation, Arabic, examples and level are original additions.
A69: S2-MOTN-004 | B69: 65 | C69: Coordinated Straight Line Motion | D69: الحركة الخطية المنسقة | E69: koh-OR-dih-nay-tid STRAYT LYNE MOH-shun | F69: Motion Control | G69: The tool center point follows a set path while all axes reach their endpoints at the same time for smooth movement. | H69: Coordinated straight line motion keeps the tool on a straight path. | I69: تُبقي الحركة الخطية المنسقة الأداة على مسار مستقيم. | J69: All axes finish at the same time in coordinated straight line motion. | K69: تنتهي جميع المحاور في الوقت نفسه في الحركة الخطية المنسقة. | L69: Advanced | M69: 2 | N69: 2 – Control & Motion | التحكم والحركة | O69: Normal | Q69: Productivity Inc | R69: https://www.productivity.com/wp-content/uploads/2015/04/PI_RoboticGlossaryTerms.pdf | S69: Definition paraphrased from the listed source(s); pronunciation, Arabic, examples and level are original additions.
... A77: S2-CTRL-014 | B77: 73 | C77: Feedforward Control | D77: التحكم الأمامي | E77: FEED-for-werd kun-TROHL | F77: Control Systems | G77: A method that applies a command predicted from a system model before any error appears, often combined with feedback. | H77: Feedforward control acts before the error appears. | I77: يعمل التحكم الأمامي قبل ظهور الخطأ. | J77: We added feedforward control to improve tracking. | K77: أضفنا تحكماً أمامياً لتحسين التتبع. | L77: Advanced | M77: 2 | N77: 2 – Control & Motion | التحكم والحركة | O77: Normal | Q77: Engineers Universe | R77: https://engineersuniverse.com/studios/mechatronics/mechatronics-terminology-glossary | S77: Definition paraphrased from the listed source(s); pronunciation, Arabic, examples and level are original additions.
A78: S2-KINE-010 | B78: 74 | C78: Forward Kinematic Solution | D78: حل الكينماتيكا الأمامية | E78: FOR-werd kin-uh-MAT-ik suh-LOO-shun | F78: Kinematics | G78: Calculating endpoint position from joint positions, which is usually easier than the inverse problem. | H78: The forward kinematic solution finds the endpoint from the joint angles. | I78: يجد حل الكينماتيكا الأمامية نقطة النهاية من زوايا المفاصل. | J78: Forward kinematics is easier to calculate than inverse kinematics. | K78: الكينماتيكا الأمامية أسهل في الحساب من الكينماتيكا العكسية. | L78: Advanced | M78: 2 | N78: 2 – Control & Motion | التحكم والحركة | O78: High | P78: S7-INTV-008 | Q78: Productivity Inc | R78: https://www.productivity.com/wp-content/uploads/2015/04/PI_RoboticGlossaryTerms.pdf | S78: Definition paraphrased from the listed source(s); pronunciation, Arabic, examples and level are original additions.
A79: S2-CTRL-015 | B79: 75 | C79: Frequency Response | D79: الاستجابة الترددية | E79: FREE-kwun-see rih-SPONS | F79: Control Systems | G79: How a system's output amplitude and phase vary with input frequency, often shown as a Bode plot. | H79: Frequency response shows how a system reacts to different frequencies. | I79: تُظهر الاستجابة الترددية كيف يتفاعل النظام مع ترددات مختلفة. | J79: A Bode plot displays the frequency response. | K79: يعرض مخطط بود الاستجابة الترددية. | L79: Advanced | M79: 2 | N79: 2 – Control & Motion | التحكم والحركة | O79: Normal | Q79: Engineers Universe | R79: https://engineersuniverse.com/studios/mechatronics/mechatronics-terminology-glossary | S79: Definition paraphrased from the listed source(s); pronunciation, Arabic, examples and level are original additions.
A80: S2-ROBT-003 | B80: 76 | C80: Fully Constrained Robot | D80: روبوت مقيّد كلياً | E80: FUL-ee kun-STRAYND ROH-bot | F80: Robot Types | G80: A robot whose number of equality constraints equals its number of independent joints. | H80: A fully constrained robot has as many constraints as independent joints. | I80: للروبوت المقيّد كلياً قيود بعدد مفاصله المستقلة. | J80: A fully constrained robot has no extra freedom of movement. | K80: لا توجد حرية حركة إضافية لدى الروبوت المقيّد كلياً. | L80: Advanced | M80: 2 | N80: 2 – Control & Motion | التحكم والحركة | O80: Normal | Q80: Productivity Inc | R80: https://www.productivity.com/wp-content/uploads/2015/04/PI_RoboticGlossaryTerms.pdf | S80: Definition paraphrased from the listed source(s); pronunciation, Arabic, examples and level are original additions.
A81: S2-DYNM-003 | B81: 77 | C81: Gravity Loading | D81: حِمل الجاذبية | E81: GRAV-ih-tee LOH-ding | F81: Dynamics | G81: Downward force from the arm's weight and any payload, which causes position error that can be compensated for. | H81: Gravity loading causes a small position error in a long arm. | I81: يسبب حِمل الجاذبية خطأً صغيراً في الموضع لدى الذراع الطويلة. | J81: The controller compensates for gravity loading automatically. | K81: يعوّض المتحكم حِمل الجاذبية تلقائياً. | L81: Advanced | M81: 2 | N81: 2 – Control & Motion | التحكم والحركة | O81: Normal | Q81: Productivity Inc | R81: https://www.productivity.com/wp-content/uploads/2015/04/PI_RoboticGlossaryTerms.pdf | S81: Definition paraphrased from the listed source(s); pronunciation, Arabic, examples and level are original additions.
A82: S2-MATH-007 | B82: 78 | C82: Inequality Constraint | D82: قيد عدم المساواة | E82: in-ih-KWOL-ih-tee kun-STRAYNT | F82: Math | G82: A limit on a feature such as joint movement, speed, or torque. | H82: An inequality constraint limits joint speed or torque. | I82: يحدّ قيد عدم المساواة من سرعة المفصل أو عزمه. | J82: The planner respects every inequality constraint of the arm. | K82: يحترم المخطِّط كل قيود عدم المساواة للذراع. | L82: Advanced | M82: 2 | N82: 2 – Control & Motion | التحكم والحركة | O82: Normal | Q82: Productivity Inc | R82: https://www.productivity.com/wp-content/uploads/2015/04/PI_RoboticGlossaryTerms.pdf | S82: Definition paraphrased from the listed source(s); pronunciation, Arabic, examples and level are original additions.
A83: S2-MOTN-005 | B83: 79 | C83: Interpolation | D83: الاستيفاء | E83: in-tur-puh-LAY-shun | F83: Motion Control | G83: The method for creating endpoint paths by calculating intermediate positions between programmed knot points. | H83: Interpolation calculates the points between two taught positions. | I83: يحسب الاستيفاء النقاط بين موضعين معلَّمين. | J83: Linear interpolation keeps the tool on a straight line. | K83: يُبقي الاستيفاء الخطي الأداة على خط مستقيم. | L83: Advanced | M83: 2 | N83: 2 – Control & Motion | التحكم والحركة | O83: Normal | Q83: Productivity Inc | R83: https://www.productivity.com/wp-content/uploads/2015/04/PI_RoboticGlossaryTerms.pdf | S83: Definition paraphrased from the listed source(s); pronunciation, Arabic, examples and level are original additions.
A84: S2-KINE-012 | B84: 80 | C84: Inverse Kinematics (IK) | D84: الكينماتيكا العكسية | E84: IN-vurs kin-uh-MAT-iks | F84: Kinematics | G84: Calculating joint positions needed to reach a desired end-effector pose, which can have zero, one, or several solutions. | H84: Inverse kinematics finds the joint angles needed for a target pose. | I84: تجد الكينماتيكا العكسية زوايا المفاصل اللازمة لوضعية مستهدفة. | J84: Inverse kinematics can have more than one solution. | K84: قد يكون للكينماتيكا العكسية أكثر من حل. | L84: Advanced | M84: 2 | N84: 2 – Control & Motion | التحكم والحركة | O84: High | P84: S7-INTV-008 | Q84: Engineers Universe + Productivity Inc | R84: https://engineersuniverse.com/studios/mechatronics/mechatronics-terminology-glossary | https://www.productivity.com/wp-content/uploads/2015/04/PI_RoboticGlossaryTerms.pdf | S84: Definition paraphrased from the listed source(s); pronunciation, Arabic, examples and level are original additions.
A85: S2-MATH-010 | B85: 81 | C85: Jacobian | D85: اليعقوبي | E85: juh-KOH-bee-un | F85: Math | G85: The matrix of first-order partial derivatives relating joint speeds to end-effector velocity. | H85: The Jacobian links joint speeds to tool speed. | I85: يربط اليعقوبي سرعات المفاصل بسرعة الأداة. | J85: Engineers use the Jacobian to control velocity. | K85: يستخدم المهندسون اليعقوبي للتحكم في السرعة. | L85: Advanced | M85: 2 | N85: 2 – Control & Motion | التحكم والحركة | O85: Normal | Q85: Productivity Inc | R85: https://www.productivity.com/wp-content/uploads/2015/04/PI_RoboticGlossaryTerms.pdf | S85: Definition paraphrased from the listed source(s); pronunciation, Arabic, examples and level are original additions.
A86: S2-MATH-011 | B86: 82 | C86: Jacobian Matrix | D86: المصفوفة اليعقوبية | E86: juh-KOH-bee-un MAY-triks | F86: Math | G86: A matrix relating rates of change of joint values to rates of change of endpoint coordinates, used to position the robot. | H86: The Jacobian matrix relates joint rates to endpoint rates. | I86: تربط المصفوفة اليعقوبية معدلات المفاصل بمعدلات نقطة النهاية. | J86: A singular Jacobian matrix means the robot is at a singularity. | K86: المصفوفة اليعقوبية المنفردة تعني أن الروبوت عند نقطة تفرّد. | L86: Advanced | M86: 2 | N86: 2 – Control & Motion | التحكم والحركة | O86: High | P86: S7-INTV-009 | Q86: Productivity Inc | R86: https://www.productivity.com/wp-content/uploads/2015/04/PI_RoboticGlossaryTerms.pdf | S86: Definition paraphrased from the listed source(s); pronunciation, Arabic, examples and level are original additions.
A87: S2-MOTN-006 | B87: 83 | C87: Jerk | D87: الارتجاج (معدل تغير التسارع) | E87: JURK | F87: Motion Control | G87: The rate of change of acceleration; limiting it produces smoother, less shock-prone motion. | H87: Limiting jerk makes the motion smoother. | I87: تحديد الارتجاج يجعل الحركة أنعم. | J87: High jerk can damage fragile parts. | K87: قد يتلف الارتجاج العالي القطع الهشة. | L87: Advanced | M87: 2 | N87: 2 – Control & Motion | التحكم والحركة | O87: High | P87: S7-TRBL-011 | Q87: Engineers Universe | R87: https://engineersuniverse.com/studios/mechatronics/mechatronics-terminology-glossary | S87: Definition paraphrased from the listed source(s); pronunciation, Arabic, examples and level are original additions.
A88: S2-KINE-013 | B88: 84 | C88: Joint Space | D88: فضاء المفاصل | E88: JOYNT SPAYS | F88: Kinematics | G88: Describing robot configuration by joint values rather than end-effector coordinates. | H88: In joint space, the pose is described by joint values. | I88: في فضاء المفاصل تُوصف الوضعية بقيم المفاصل. | J88: Planning in joint space avoids singularities. | K88: يتجنب التخطيط في فضاء المفاصل نقاط التفرّد. | L88: Advanced | M88: 2 | N88: 2 – Control & Motion | التحكم والحركة | O88: High | P88: S7-TRBL-012 | Q88: Engineers Universe + Productivity Inc | R88: https://engineersuniverse.com/studios/mechatronics/mechatronics-terminology-glossary | https://www.productivity.com/wp-content/uploads/2015/04/PI_RoboticGlossaryTerms.pdf | S88: Definition paraphrased from the listed source(s); pronunciation, Arabic, examples and level are original additions.
A89: S2-MOTN-008 | B89: 85 | C89: Joint-Interpolated Motion | D89: حركة الاستيفاء المفصلي | E89: JOYNT in-TUR-puh-lay-tid MOH-shun | F89: Motion Control | G89: Coordinating joints to arrive simultaneously, producing a predictable path and the fastest pick-and-place cycle. | H89: In joint-interpolated motion all joints arrive at the same time. | I89: في الحركة المستوفاة مفصلياً تصل جميع المفاصل في الوقت نفسه. | J89: Joint-interpolated motion gives the fastest pick-and-place cycle. | K89: تعطي الحركة المستوفاة مفصلياً أسرع دورة التقاط ووضع. | L89: Advanced | M89: 2 | N89: 2 – Control & Motion | التحكم والحركة | O89: Normal | Q89: Productivity Inc | R89: https://www.productivity.com/wp-content/uploads/2015/04/PI_RoboticGlossaryTerms.pdf | S89: Definition paraphrased from the listed source(s); pronunciation, Arabic, examples and level are original additions.
A90: S2-KINE-014 | B90: 86 | C90: Kinematic Influence Coefficients | D90: معاملات التأثير الكينماتيكي | E90: kin-uh-MAT-ik IN-floo-unts koh-ih-FISH-unts | F90: Kinematics | G90: The effects of input joints on movement and system response, which arise from complex coupled nonlinear equations. | H90: Kinematic influence coefficients show how each joint affects the motion. | I90: توضح معاملات التأثير الكينماتيكي كيف يؤثر كل مفصل على الحركة. | J90: These coefficients appear in advanced robot models. | K90: تظهر هذه المعاملات في نماذج الروبوت المتقدمة. | L90: Advanced | M90: 2 | N90: 2 – Control & Motion | التحكم والحركة | O90: Normal | Q90: Productivity Inc | R90: https://www.productivity.com/wp-content/uploads/2015/04/PI_RoboticGlossaryTerms.pdf | S90: Definition paraphrased from the listed source(s); pronunciation, Arabic, examples and level are original additions.
A91: S2-MATH-012 | B91: 87 | C91: LaGrange Multipliers | D91: مضاعِفات لاغرانج | E91: luh-GRONJ MUL-tuh-ply-erz | F91: Math | G91: A technique that turns a constrained problem into an unconstrained one. | H91: Lagrange multipliers help solve problems with constraints. | I91: تساعد مضاعِفات لاغرانج في حل المسائل ذات القيود. | J91: The planner used Lagrange multipliers to optimize the path. | K91: استخدم المخطِّط مضاعِفات لاغرانج لتحسين المسار. | L91: Advanced | M91: 2 | N91: 2 – Control & Motion | التحكم والحركة | O91: Normal | Q91: Productivity Inc | R91: https://www.productivity.com/wp-content/uploads/2015/04/PI_RoboticGlossaryTerms.pdf | S91: Definition paraphrased from the listed source(s); pronunciation, Arabic, examples and level are original additions.
A92: S2-MATH-013 | B92: 88 | C92: Linearly Dependent | D92: مرتبط خطياً | E92: LIN-ee-er-lee dih-PEN-dunt | F92: Math | G92: Values or functions related by addition, subtraction, or scalar multiplication. | H92: Two vectors are linearly dependent if one is a multiple of the other. | I92: يكون المتجهان مرتبطين خطياً إذا كان أحدهما مضاعفاً للآخر. | J92: Linearly dependent columns make a matrix singular. | K92: الأعمدة المرتبطة خطياً تجعل المصفوفة منفردة. | L92: Advanced | M92: 2 | N92: 2 – Control & Motion | التحكم والحركة | O92: Normal | Q92: Productivity Inc | R92: https://www.productivity.com/wp-content/uploads/2015/04/PI_RoboticGlossaryTerms.pdf | S92: Definition paraphrased from the listed source(s); pronunciation, Arabic, examples and level are original additions.
A93: S2-DYNM-004 | B93: 89 | C93: Moment | D93: العزم | E93: MOH-munt | F93: Dynamics | G93: The rotational effect of a force about a reference point, line, or plane. | H93: The moment of a force depends on the distance from the pivot. | I93: تعتمد عزم القوة على المسافة من نقطة الارتكاز. | J93: A long arm creates a large moment at the base. | K93: تُنتج الذراع الطويلة عزماً كبيراً عند القاعدة. | L93: Advanced | M93: 2 | N93: 2 – Control & Motion | التحكم والحركة | O93: Normal | Q93: Productivity Inc | R93: https://www.productivity.com/wp-content/uploads/2015/04/PI_RoboticGlossaryTerms.pdf | S93: Definition paraphrased from the listed source(s); pronunciation, Arabic, examples and level are original additions.
A94: S2-DYNM-005 | B94: 90 | C94: Natural Frequency | D94: التردد الطبيعي | E94: NACH-ur-ul FREE-kwun-see | F94: Dynamics | G94: The frequency at which a structure oscillates freely, which control bandwidth must avoid exciting. | H94: The structure vibrates at its natural frequency. | I94: يهتز الهيكل عند تردده الطبيعي. | J94: Avoid exciting the natural frequency of the arm. | K94: تجنب إثارة التردد الطبيعي للذراع. | L94: Advanced | M94: 2 | N94: 2 – Control & Motion | التحكم والحركة | O94: High | P94: S7-TRBL-002 | Q94: Engineers Universe | R94: https://engineersuniverse.com/studios/mechatronics/mechatronics-terminology-glossary | S94: Definition paraphrased from the listed source(s); pronunciation, Arabic, examples and level are original additions.
